Workbook

Sheet Carbon footprint calculator
V5: Carbon footprint [kgCO2equ/FU] | W5: Gasoline car | X5: Electric car - Hard coal | Y5: Electric car electricity mix | Z5: Electric car - Wind | AA5: Electric car - Photovoltaic | AB5: E-bike - electricity mix | AC5: Conventional bike | AF5: Human health [min. lost/FU] | AG5: Gasoline car | AH5: Electric car - Hard coal | AI5: Electric car electricity mix | AJ5: Electric car - Wind | AK5: Electric car - Photovoltaic | AL5: E-bike - electricity mix | AM5: Conventional bike | AO5: Ecosystem quality impacts [species-yr/FU] | AP5: Gasoline car | AQ5: Electric car - Hard coal | AR5: Electric car electricity mix | AS5: Electric car - Wind | AT5: Electric car - Photovoltaic | AU5: E-bike - electricity mix | AV5: Conventional bike | AX5: Cumulative energy demand [MJ/FU] | AY5: Gasoline car | AZ5: Electric car - Hard coal | BA5: Electric car electricity mix | BB5: Electric car - Wind | BC5: Electric car - Photovoltaic | BD5: E-bike - electricity mix | BE5: Conventional bike
V6: Manufacturing & raw materials | W6: =SUM(I23:I35) -> 0.032727847 | X6: =SUM($I$56:$I$70) -> 0.046491543 | Y6: =SUM($I$56:$I$70) -> 0.046491543 | Z6: =SUM($I$56:$I$70) -> 0.046491543 | AA6: =SUM($I$56:$I$70) -> 0.046491543 | AB6: =SUM(I98:I99) -> 0.0048466754 | AC6: =SUM(I119:I120) -> 0.0048466754 | AF6: =V6 -> Manufacturing & raw materials | AG6: =SUM(L23:L35) -> 0.088065815 | AH6: =SUM($L$56:$L$70) -> 0.12515818 | AI6: =SUM($L$56:$L$70) -> 0.12515818 | AJ6: =SUM($L$56:$L$70) -> 0.12515818 | AK6: =SUM($L$56:$L$70) -> 0.12515818 | AL6: =SUM($L$98:$L$99) -> 0.01145343 | AM6: =SUM(L119:L120) -> 0.01145343 | AO6: =AF6 -> Manufacturing & raw materials | AP6: =SUM(O23:O35) -> 1.5987586e-10 | AQ6: =SUM($O$56:$O$70) -> 2.7067631e-10 | AR6: =SUM($O$56:$O$70) -> 2.7067631e-10 | AS6: =SUM($O$56:$O$70) -> 2.7067631e-10 | AT6: =SUM($O$56:$O$70) -> 2.7067631e-10 | AU6: =SUM($O98:$O99) -> 2.2519353e-11 | AV6: =AU6 -> 2.2519353e-11 | AX6: =AF6 -> Manufacturing & raw materials | AY6: =SUM(R23:R35) -> 0.56786645 | AZ6: =SUM($R$56:$R$70) -> 0.71482272 | BA6: =SUM($R$56:$R$70) -> 0.71482272 | BB6: =SUM($R$56:$R$70) -> 0.71482272 | BC6: =SUM($R$56:$R$70) -> 0.71482272 | BD6: =SUM($R98:$R99) -> 0.056742791 | BE6: =SUM($R98:$R99) -> 0.056742791
V7: Transportation | W7: =SUM(I37:I39) -> 0.001015679 | X7: =SUM($I$72:$I$74) -> 0.0005938773 | Y7: =SUM($I$72:$I$74) -> 0.0005938773 | Z7: =SUM($I$72:$I$74) -> 0.0005938773 | AA7: =SUM($I$72:$I$74) -> 0.0005938773 | AB7: =SUM(I101:I103) -> 0.00030603795 | AC7: =SUM(I122:I124) -> 0.00024160891 | AF7: =V7 -> Transportation | AG7: =SUM(L37:L39) -> 0.0023378932 | AH7: =SUM($L$72:$L$74) -> 0.0013419962 | AI7: =SUM($L$72:$L$74) -> 0.0013419962 | AJ7: =SUM($L$72:$L$74) -> 0.0013419962 | AK7: =SUM($L$72:$L$74) -> 0.0013419962 | AL7: =SUM($L$72:$L$74) -> 0.0013419962 | AM7: =SUM(L122:L124) -> 0.00033331625 | AO7: =AF7 -> Transportation | AP7: =SUM(O37:O39) -> 8.5706313e-12 | AQ7: =SUM($O$72:$O$74) -> 4.9267156e-12 | AR7: =SUM($O$72:$O$74) -> 4.9267156e-12 | AS7: =SUM($O$72:$O$74) -> 4.9267156e-12 | AT7: =SUM($O$72:$O$74) -> 4.9267156e-12 | AU7: =SUM($O101:$O103) -> 1.7205772e-12 | AV7: =AU7 -> 1.7205772e-12 | AX7: =AF7 -> Transportation | AY7: =SUM(R37:R39) -> 0.013882458 | AZ7: =SUM($R$72:$R$74) -> 0.0081645564 | BA7: =SUM($R$72:$R$74) -> 0.0081645564 | BB7: =SUM($R$72:$R$74) -> 0.0081645564 | BC7: =SUM($R$72:$R$74) -> 0.0081645564 | BD7: =SUM($R101:$R103) -> 0.0045043097 | BE7: =SUM($R101:$R103) -> 0.0045043097
V8: Disposal | W8: =SUM(I45:I47) -> 0.0017928846 | X8: =SUM($I$82:$I$85) -> 0.0020882669 | Y8: =SUM($I$82:$I$85) -> 0.0020882669 | Z8: =SUM($I$82:$I$85) -> 0.0020882669 | AA8: =SUM($I$82:$I$85) -> 0.0020882669 | AB8: =SUM(I108:I108) -> 7.8191141e-05 | AC8: =SUM(I129:I129) -> 7.8191141e-05 | AF8: =V8 -> Disposal | AG8: =SUM(L45:L47) -> -0.00018269536 | AH8: =SUM($L$82:$L$85) -> -0.00022737211 | AI8: =SUM($L$82:$L$85) -> -0.00022737211 | AJ8: =SUM($L$82:$L$85) -> -0.00022737211 | AK8: =SUM($L$82:$L$85) -> -0.00022737211 | AL8: =SUM($L$82:$L$85) -> -0.00022737211 | AM8: =SUM(L129:L129) -> 4.3717805e-05 | AO8: =AF8 -> Disposal | AP8: =SUM(O45:O47) -> 2.114838e-12 | AQ8: =SUM($O$82:$O$85) -> 2.407329e-12 | AR8: =SUM($O$82:$O$85) -> 2.407329e-12 | AS8: =SUM($O$82:$O$85) -> 2.407329e-12 | AT8: =SUM($O$82:$O$85) -> 2.407329e-12 | AU8: =SUM($O108:$O108) -> 2.2644518e-13 | AV8: =AU8 -> 2.2644518e-13 | AX8: =AF8 -> Disposal | AY8: =SUM(R45:R47) -> -0.037620082 | AZ8: =SUM($R$82:$R$85) -> -0.044361663 | BA8: =SUM($R$82:$R$85) -> -0.044361663 | BB8: =SUM($R$82:$R$85) -> -0.044361663 | BC8: =SUM($R$82:$R$85) -> -0.044361663 | BD8: =SUM($R108:$R108) -> 1.6240435e-05 | BE8: =SUM($R108:$R108) -> 1.6240435e-05
V9: Vehicle use | W9: =SUM(I42:I43) -> 0.27505153 | AF9: =V9 -> Vehicle use | AG9: =SUM(L42:L43) -> 0.3485735 | AO9: =AF9 -> Vehicle use | AP9: =SUM(O42:O43) -> 1.3568873e-09 | AX9: =AF9 -> Vehicle use | AY9: =SUM(R42:R43) -> 3.5141563
V10: Vehicle physical activity | AF10: =V10 -> Vehicle physical activity | AG10: =L41 -> -0.72627994 | AH10: =L76 -> -0.72627994 | AI10: =L76 -> -0.72627994 | AJ10: =L76 -> -0.72627994 | AK10: =L76 -> -0.72627994 | AL10: =L105 -> -6.2175665 | AM10: =L126 -> -9.3263497 | AO10: =AF10 -> Vehicle physical activity | AX10: =AF10 -> Vehicle physical activity
V11: Electric charging - EU | Y11: =I77 -> 0.10008312 | AB11: =SUM(I105:I106) -> 0.0026945455 | AC11: =SUM(I126:I127) -> 0 | AF11: Electric charging - EU | AI11: =L77 -> 0.12722285 | AL11: =L106 -> 0.0034252306 | AM11: =L127 -> 0 | AO11: Electric charging - EU | AR11: =O77 -> 4.7592494e-10 | AU11: =SUM(O105:O106) -> 1.2813364e-11 | AV11: 0 | AX11: Electric charging - EU | BA11: =R77 -> 2.3097052 | BD11: =SUM(R105:R106) -> 0.062184371 | BE11: 0
V12: Electric charging - wind | Z12: =I78 -> 0.0038344612 | AF12: Electric charging - wind | AJ12: =L78 -> 0.010658041 | AO12: Electric charging - wind | AS12: =O78 -> 2.1501693e-11 | AX12: Electric charging - wind | BB12: =R78 -> 0.052025962
V13: Electric charging - photovoltaic | AA13: =I79 -> 0.020865159 | AF13: Electric charging - photovoltaic | AK13: =L79 -> 0.038374462 | AO13: Electric charging - photovoltaic | AT13: =O79 -> 1.7005097e-10 | AX13: Electric charging - photovoltaic | BC13: =R79 -> 0.27552472
V14: Electric charging - hard coal | X14: =I80 -> 0.28483847 | AF14: Electric charging - hard coal | AH14: =L80 -> 0.42919009 | AO14: Electric charging - hard coal | AQ14: =O80 -> 1.5018117e-09 | AX14: Electric charging - hard coal | AZ14: =R80 -> 2.9354912
V15: Net value | W15: =SUM(W6:W14) -> 0.31058794 | X15: =SUM(X6:X14) -> 0.33401216 | Y15: =SUM(Y6:Y11) -> 0.14925681 | Z15: =SUM(Z6:Z14) -> 0.053008148 | AA15: =SUM(AA6:AA14) -> 0.070038846 | AB15: =SUM(AB6:AB14) -> 0.00792545 | AC15: =SUM(AC6:AC14) -> 0.0051664754 | AF15: Net value | AG15: =SUM(AG6:AG14) -> -0.28748543 | AH15: =SUM(AH6:AH14) -> -0.17081706 | AI15: =SUM(AI6:AI14) -> -0.47278429 | AJ15: =SUM(AJ6:AJ14) -> -0.5893491 | AK15: =SUM(AK6:AK14) -> -0.56163268 | AL15: =SUM(AL6:AL14) -> -6.2015732 | AM15: =SUM(AM6:AM14) -> -9.3145193 | AO15: Net value | AP15: =SUM(AP6:AP9) -> 1.5274486e-09 | AQ15: =SUM(AQ6:AQ14) -> 1.7798221e-09 | AR15: =SUM(AR6:AR11) -> 7.5393529e-10 | AS15: =SUM(AS6:AS8, AS12) -> 2.9951205e-10 | AT15: =SUM(AT6:AT14) -> 4.4806132e-10 | AU15: =SUM(AU6:AU14) -> 3.7279739e-11 | AV15: =SUM(AV6:AV14) -> 2.4466376e-11 | AX15: Net value | AY15: =SUM(AY6:AY9) -> 4.0582852 | AZ15: =SUM(AZ6:AZ14) -> 3.6141168 | BA15: =SUM(BA6:BA11) -> 2.9883308 | BB15: =SUM(BB6:BB8, BB12) -> 0.73065158 | BC15: =SUM(BC6:BC14) -> 0.95415034 | BD15: =SUM(BD6:BD14) -> 0.12344771 | BE15: =SUM(BE6:BE14) -> 0.061263341
A17: kg/t conversion factor | B17: 1000 | C17: Energy recovery from paper | E17: 42.5 | F17: MJ/kg
A18: g/kg, Wh/kWh | B18: 1000 | C18: Conversion efficiency | E18: 0.25
C19: Conversion factor | E19: 3.6 | F19: MJ/kWh
B20: Vehicle lifespan (km/vehicle) | C20: 150000
A21: Process # | B21: Transportation by Gas Vehicle Functional unit (FU)= 1 vehicle km Life Cycle stage (150,000 km lifespan) | C21: Ecoinvent process | D21: Region | E21: Quantity original unit | F21: Quantity per FU | G21: Unit | H21: Carbon footprint [kgCO2equ/unit] | I21: Carbon footprint [CO2equ./FU] | J21: fraction carbon footprint | K21: Human health/Unit [min. lost/unit] | L21: Human health [min. lost/FU] | M21: fraction human health | N21: Ecosystem quality impacts/Unit [species-yr/unit] | O21: Ecosystem quality impacts [Species-yr/FU] | P21: fraction ecosystem quality | Q21: Non renewable primary energy resources/unit [MJ/unit] | R21: Non renewable primary energy resources impacts [MJ/FU] | S21: fraction non renewable primary energy | T21: Check [gCO2e/MJ]
B22: Manufacturing (Materials + Processing) | C22: Manufacturing (Materials + Processing) | E22: per vehicle over lifespan | F22: per FU
A23: 17299 | B23: steel, low-alloyed, hot rolled | C23: =INDEX('Selected processes'!$E$5:$E$97, MATCH('Carbon footprint calculator'!$A23,'Selected processes'!$D$5:$D$97,0)) -> steel production, low-alloyed, hot rolled | D23: =INDEX('Selected processes'!$F$5:$F$97, MATCH('Carbon footprint calculator'!$A23,'Selected processes'!$D$5:$D$97,0)) -> RER | E23: 1040 | F23: =E23/$C$20 -> 0.0069333333 | G23: =INDEX('Selected processes'!$H$5:$H$97, MATCH('Carbon footprint calculator'!$A23,'Selected processes'!$D$5:$D$97,0)) -> kg | H23: =INDEX('Selected processes'!$J$5:$J$97, MATCH('Carbon footprint calculator'!$A23,'Selected processes'!$D$5:$D$97,0)) -> 2.1807172 | I23: =H23*$F23 -> 0.01511964 | J23: =I23/I$49 -> 0.048680705 | K23: =INDEX('Selected processes'!$K$5:$K$97, MATCH('Carbon footprint calculator'!$A23,'Selected processes'!$D$5:$D$97,0)) -> 7.9963289 | L23: =K23*$F23 -> 0.055441214 | M23: =L23/L$49 -> -0.19284878 | N23: =INDEX('Selected processes'!$L$5:$L$97, MATCH('Carbon footprint calculator'!$A23,'Selected processes'!$D$5:$D$97,0)) -> 9.7808189e-09 | O23: =N23*$F23 -> 6.7813678e-11 | P23: =O23/O$49 -> 0.0443967 | Q23: =INDEX('Selected processes'!$N$5:$N$97, MATCH('Carbon footprint calculator'!$A23,'Selected processes'!$D$5:$D$97,0)) -> 25.556652 | R23: =Q23*$F23 -> 0.17719279 | S23: =R23/R$49 -> 0.043661986 | T23: =I23/R23*$B$18 -> 85.328752
A24: 16619 | B24: sheet rolling, steel | C24: =INDEX('Selected processes'!$E$5:$E$97, MATCH('Carbon footprint calculator'!$A24,'Selected processes'!$D$5:$D$97,0)) -> sheet rolling, steel | D24: =INDEX('Selected processes'!$F$5:$F$97, MATCH('Carbon footprint calculator'!$A24,'Selected processes'!$D$5:$D$97,0)) -> RER | E24: 780 | F24: =E24/$C$20 -> 0.0052 | G24: =INDEX('Selected processes'!$H$5:$H$97, MATCH('Carbon footprint calculator'!$A24,'Selected processes'!$D$5:$D$97,0)) -> kg | H24: =INDEX('Selected processes'!$J$5:$J$97, MATCH('Carbon footprint calculator'!$A24,'Selected processes'!$D$5:$D$97,0)) -> 0.31200613 | I24: =H24*$F24 -> 0.0016224319 | J24: =I24/I$49 -> 0.005223744 | K24: =INDEX('Selected processes'!$K$5:$K$97, MATCH('Carbon footprint calculator'!$A24,'Selected processes'!$D$5:$D$97,0)) -> 0.73372079 | L24: =K24*$F24 -> 0.0038153481 | M24: =L24/L$49 -> -0.013271449 | N24: =INDEX('Selected processes'!$L$5:$L$97, MATCH('Carbon footprint calculator'!$A24,'Selected processes'!$D$5:$D$97,0)) -> 1.3767966e-09 | O24: =N24*$F24 -> 7.1593425e-12 | P24: =O24/O$49 -> 0.0046871249 | Q24: =INDEX('Selected processes'!$N$5:$N$97, MATCH('Carbon footprint calculator'!$A24,'Selected processes'!$D$5:$D$97,0)) -> 4.9309388 | R24: =Q24*$F24 -> 0.025640882 | S24: =R24/R$49 -> 0.0063181567 | T24: =I24/R24*$B$18 -> 63.275198
A25: 458 | B25: aluminium, primary, ingot | C25: =INDEX('Selected processes'!$E$5:$E$97, MATCH('Carbon footprint calculator'!$A25,'Selected processes'!$D$5:$D$97,0)) -> aluminium production, primary, ingot | D25: =INDEX('Selected processes'!$F$5:$F$97, MATCH('Carbon footprint calculator'!$A25,'Selected processes'!$D$5:$D$97,0)) -> IAI Area, EU27 & EFTA | E25: 55 | F25: =E25/$C$20 -> 0.00036666667 | G25: =INDEX('Selected processes'!$H$5:$H$97, MATCH('Carbon footprint calculator'!$A25,'Selected processes'!$D$5:$D$97,0)) -> kg | H25: =INDEX('Selected processes'!$J$5:$J$97, MATCH('Carbon footprint calculator'!$A25,'Selected processes'!$D$5:$D$97,0)) -> 7.209838 | I25: =H25*$F25 -> 0.0026436073 | J25: =I25/I$49 -> 0.0085116225 | K25: =INDEX('Selected processes'!$K$5:$K$97, MATCH('Carbon footprint calculator'!$A25,'Selected processes'!$D$5:$D$97,0)) -> 13.333429 | L25: =K25*$F25 -> 0.004888924 | M25: =L25/L$49 -> -0.017005815 | N25: =INDEX('Selected processes'!$L$5:$L$97, MATCH('Carbon footprint calculator'!$A25,'Selected processes'!$D$5:$D$97,0)) -> 3.2653298e-08 | O25: =N25*$F25 -> 1.1972876e-11 | P25: =O25/O$49 -> 0.0078384802 | Q25: =INDEX('Selected processes'!$N$5:$N$97, MATCH('Carbon footprint calculator'!$A25,'Selected processes'!$D$5:$D$97,0)) -> 115.04046 | R25: =Q25*$F25 -> 0.042181504 | S25: =R25/R$49 -> 0.010393923 | T25: =I25/R25*$B$18 -> 62.672192
A26: 16616 | B26: Copper & other metals (Zn, Ni, Pb) | C26: =INDEX('Selected processes'!$E$5:$E$97, MATCH('Carbon footprint calculator'!$A26,'Selected processes'!$D$5:$D$97,0)) -> sheet rolling, copper | D26: =INDEX('Selected processes'!$F$5:$F$97, MATCH('Carbon footprint calculator'!$A26,'Selected processes'!$D$5:$D$97,0)) -> RER | E26: 38 | F26: =E26/$C$20 -> 0.00025333333 | G26: =INDEX('Selected processes'!$H$5:$H$97, MATCH('Carbon footprint calculator'!$A26,'Selected processes'!$D$5:$D$97,0)) -> kg | H26: =INDEX('Selected processes'!$J$5:$J$97, MATCH('Carbon footprint calculator'!$A26,'Selected processes'!$D$5:$D$97,0)) -> 0.48163006 | I26: =H26*$F26 -> 0.00012201295 | J26: =I26/I$49 -> 0.0003928451 | K26: =INDEX('Selected processes'!$K$5:$K$97, MATCH('Carbon footprint calculator'!$A26,'Selected processes'!$D$5:$D$97,0)) -> 4.9624408 | L26: =K26*$F26 -> 0.0012571517 | M26: =L26/L$49 -> -0.0043729231 | N26: =INDEX('Selected processes'!$L$5:$L$97, MATCH('Carbon footprint calculator'!$A26,'Selected processes'!$D$5:$D$97,0)) -> 9.7940056e-09 | O26: =N26*$F26 -> 2.4811481e-12 | P26: =O26/O$49 -> 0.0016243742 | Q26: =INDEX('Selected processes'!$N$5:$N$97, MATCH('Carbon footprint calculator'!$A26,'Selected processes'!$D$5:$D$97,0)) -> 7.1938644 | R26: =Q26*$F26 -> 0.0018224456 | S26: =R26/R$49 -> 0.00044906791 | T26: =I26/R26*$B$18 -> 66.950117
A27: 12456 | B27: platinum | C27: =INDEX('Selected processes'!$E$5:$E$97, MATCH('Carbon footprint calculator'!$A27,'Selected processes'!$D$5:$D$97,0)) -> platinum to generic market for metal catalyst for catalytic converter | D27: =INDEX('Selected processes'!$F$5:$F$97, MATCH('Carbon footprint calculator'!$A27,'Selected processes'!$D$5:$D$97,0)) -> GLO | E27: 0.0017 | F27: =E27/$C$20 -> 1.1333333e-08 | G27: =INDEX('Selected processes'!$H$5:$H$97, MATCH('Carbon footprint calculator'!$A27,'Selected processes'!$D$5:$D$97,0)) -> kg | H27: =INDEX('Selected processes'!$J$5:$J$97, MATCH('Carbon footprint calculator'!$A27,'Selected processes'!$D$5:$D$97,0)) -> 69669.936 | I27: =H27*$F27 -> 0.0007895926 | J27: =I27/I$49 -> 0.0025422514 | K27: =INDEX('Selected processes'!$K$5:$K$97, MATCH('Carbon footprint calculator'!$A27,'Selected processes'!$D$5:$D$97,0)) -> 571917.51 | L27: =K27*$F27 -> 0.0064817318 | M27: =L27/L$49 -> -0.022546297 | N27: =INDEX('Selected processes'!$L$5:$L$97, MATCH('Carbon footprint calculator'!$A27,'Selected processes'!$D$5:$D$97,0)) -> 0.0011984346 | O27: =N27*$F27 -> 1.3582258e-11 | P27: =O27/O$49 -> 0.0088921213 | Q27: =INDEX('Selected processes'!$N$5:$N$97, MATCH('Carbon footprint calculator'!$A27,'Selected processes'!$D$5:$D$97,0)) -> 1106057.2 | R27: =Q27*$F27 -> 0.012535315 | S27: =R27/R$49 -> 0.0030888206 | T27: =I27/R27*$B$18 -> 62.989451
A28: 14632 | B28: polyethylene, polypropylene & PVC | C28: =INDEX('Selected processes'!$E$5:$E$97, MATCH('Carbon footprint calculator'!$A28,'Selected processes'!$D$5:$D$97,0)) -> market for polyethylene, high density, granulate | D28: =INDEX('Selected processes'!$F$5:$F$97, MATCH('Carbon footprint calculator'!$A28,'Selected processes'!$D$5:$D$97,0)) -> GLO | E28: 175 | F28: =E28/$C$20 -> 0.0011666667 | G28: =INDEX('Selected processes'!$H$5:$H$97, MATCH('Carbon footprint calculator'!$A28,'Selected processes'!$D$5:$D$97,0)) -> kg | H28: =INDEX('Selected processes'!$J$5:$J$97, MATCH('Carbon footprint calculator'!$A28,'Selected processes'!$D$5:$D$97,0)) -> 2.3276288 | I28: =H28*$F28 -> 0.0027155669 | J28: =I28/I$49 -> 0.008743311 | K28: =INDEX('Selected processes'!$K$5:$K$97, MATCH('Carbon footprint calculator'!$A28,'Selected processes'!$D$5:$D$97,0)) -> 2.3488561 | L28: =K28*$F28 -> 0.0027403321 | M28: =L28/L$49 -> -0.0095320732 | N28: =INDEX('Selected processes'!$L$5:$L$97, MATCH('Carbon footprint calculator'!$A28,'Selected processes'!$D$5:$D$97,0)) -> 9.3798954e-09 | O28: =N28*$F28 -> 1.0943211e-11 | P28: =O28/O$49 -> 0.0071643728 | Q28: =INDEX('Selected processes'!$N$5:$N$97, MATCH('Carbon footprint calculator'!$A28,'Selected processes'!$D$5:$D$97,0)) -> 80.670316 | R28: =Q28*$F28 -> 0.094115369 | S28: =R28/R$49 -> 0.02319092 | T28: =I28/R28*$B$18 -> 28.853597
A29: 17718 | B29: synthetic rubber | C29: =INDEX('Selected processes'!$E$5:$E$97, MATCH('Carbon footprint calculator'!$A29,'Selected processes'!$D$5:$D$97,0)) -> market for synthetic rubber | D29: =INDEX('Selected processes'!$F$5:$F$97, MATCH('Carbon footprint calculator'!$A29,'Selected processes'!$D$5:$D$97,0)) -> GLO | E29: 46 | F29: =E29/$C$20 -> 0.00030666667 | G29: =INDEX('Selected processes'!$H$5:$H$97, MATCH('Carbon footprint calculator'!$A29,'Selected processes'!$D$5:$D$97,0)) -> kg | H29: =INDEX('Selected processes'!$J$5:$J$97, MATCH('Carbon footprint calculator'!$A29,'Selected processes'!$D$5:$D$97,0)) -> 2.9677534 | I29: =H29*$F29 -> 0.00091011104 | J29: =I29/I$49 -> 0.0029302846 | K29: =INDEX('Selected processes'!$K$5:$K$97, MATCH('Carbon footprint calculator'!$A29,'Selected processes'!$D$5:$D$97,0)) -> 3.7317246 | L29: =K29*$F29 -> 0.0011443956 | M29: =L29/L$49 -> -0.003980708 | N29: =INDEX('Selected processes'!$L$5:$L$97, MATCH('Carbon footprint calculator'!$A29,'Selected processes'!$D$5:$D$97,0)) -> 1.3250334e-08 | O29: =N29*$F29 -> 4.0634356e-12 | P29: =O29/O$49 -> 0.0026602765 | Q29: =INDEX('Selected processes'!$N$5:$N$97, MATCH('Carbon footprint calculator'!$A29,'Selected processes'!$D$5:$D$97,0)) -> 85.662707 | R29: =Q29*$F29 -> 0.026269897 | S29: =R29/R$49 -> 0.006473152 | T29: =I29/R29*$B$18 -> 34.644637
A30: 7943 | B30: glas | C30: =INDEX('Selected processes'!$E$5:$E$97, MATCH('Carbon footprint calculator'!$A30,'Selected processes'!$D$5:$D$97,0)) -> market for flat glass, uncoated | D30: =INDEX('Selected processes'!$F$5:$F$97, MATCH('Carbon footprint calculator'!$A30,'Selected processes'!$D$5:$D$97,0)) -> RoW | E30: 32 | F30: =E30/$C$20 -> 0.00021333333 | G30: =INDEX('Selected processes'!$H$5:$H$97, MATCH('Carbon footprint calculator'!$A30,'Selected processes'!$D$5:$D$97,0)) -> kg | H30: =INDEX('Selected processes'!$J$5:$J$97, MATCH('Carbon footprint calculator'!$A30,'Selected processes'!$D$5:$D$97,0)) -> 1.0559546 | I30: =H30*$F30 -> 0.00022527031 | J30: =I30/I$49 -> 0.00072530283 | K30: =INDEX('Selected processes'!$K$5:$K$97, MATCH('Carbon footprint calculator'!$A30,'Selected processes'!$D$5:$D$97,0)) -> 1.4484757 | L30: =K30*$F30 -> 0.00030900814 | M30: =L30/L$49 -> -0.0010748654 | N30: =INDEX('Selected processes'!$L$5:$L$97, MATCH('Carbon footprint calculator'!$A30,'Selected processes'!$D$5:$D$97,0)) -> 5.395704e-09 | O30: =N30*$F30 -> 1.1510835e-12 | P30: =O30/O$49 -> 0.00075359885 | Q30: =INDEX('Selected processes'!$N$5:$N$97, MATCH('Carbon footprint calculator'!$A30,'Selected processes'!$D$5:$D$97,0)) -> 11.947723 | R30: =Q30*$F30 -> 0.0025488475 | S30: =R30/R$49 -> 0.00062806023 | T30: =I30/R30*$B$18 -> 88.381242
A31: 7364 | B31: electronics, for control units | C31: =INDEX('Selected processes'!$E$5:$E$97, MATCH('Carbon footprint calculator'!$A31,'Selected processes'!$D$5:$D$97,0)) -> electronics production, for control units | D31: =INDEX('Selected processes'!$F$5:$F$97, MATCH('Carbon footprint calculator'!$A31,'Selected processes'!$D$5:$D$97,0)) -> RER | E31: 6.1 | F31: =E31/$C$20 -> 4.0666667e-05 | G31: =INDEX('Selected processes'!$H$5:$H$97, MATCH('Carbon footprint calculator'!$A31,'Selected processes'!$D$5:$D$97,0)) -> kg | H31: =INDEX('Selected processes'!$J$5:$J$97, MATCH('Carbon footprint calculator'!$A31,'Selected processes'!$D$5:$D$97,0)) -> 31.86483 | I31: =H31*$F31 -> 0.0012958364 | J31: =I31/I$49 -> 0.0041722046 | K31: =INDEX('Selected processes'!$K$5:$K$97, MATCH('Carbon footprint calculator'!$A31,'Selected processes'!$D$5:$D$97,0)) -> 91.052321 | L31: =K31*$F31 -> 0.0037027944 | M31: =L31/L$49 -> -0.012879938 | N31: =INDEX('Selected processes'!$L$5:$L$97, MATCH('Carbon footprint calculator'!$A31,'Selected processes'!$D$5:$D$97,0)) -> 2.0683158e-07 | O31: =N31*$F31 -> 8.4111511e-12 | P31: =O31/O$49 -> 0.0055066671 | Q31: =INDEX('Selected processes'!$N$5:$N$97, MATCH('Carbon footprint calculator'!$A31,'Selected processes'!$D$5:$D$97,0)) -> 451.55328 | R31: =Q31*$F31 -> 0.018363167 | S31: =R31/R$49 -> 0.0045248586 | T31: =I31/R31*$B$18 -> 70.567154
A32: 7587 | B32: ethylene, paints, fluids | C32: =INDEX('Selected processes'!$E$5:$E$97, MATCH('Carbon footprint calculator'!$A32,'Selected processes'!$D$5:$D$97,0)) -> ethylene production, average | D32: =INDEX('Selected processes'!$F$5:$F$97, MATCH('Carbon footprint calculator'!$A32,'Selected processes'!$D$5:$D$97,0)) -> RER | E32: 30 | F32: =E32/$C$20 -> 0.0002 | G32: =INDEX('Selected processes'!$H$5:$H$97, MATCH('Carbon footprint calculator'!$A32,'Selected processes'!$D$5:$D$97,0)) -> kg | H32: =INDEX('Selected processes'!$J$5:$J$97, MATCH('Carbon footprint calculator'!$A32,'Selected processes'!$D$5:$D$97,0)) -> 1.4469179 | I32: =H32*$F32 -> 0.00028938357 | J32: =I32/I$49 -> 0.00093172831 | K32: =INDEX('Selected processes'!$K$5:$K$97, MATCH('Carbon footprint calculator'!$A32,'Selected processes'!$D$5:$D$97,0)) -> 1.1204239 | L32: =K32*$F32 -> 0.00022408479 | M32: =L32/L$49 -> -0.00077946486 | N32: =INDEX('Selected processes'!$L$5:$L$97, MATCH('Carbon footprint calculator'!$A32,'Selected processes'!$D$5:$D$97,0)) -> 5.2741423e-09 | O32: =N32*$F32 -> 1.0548285e-12 | P32: =O32/O$49 -> 0.00069058196 | Q32: =INDEX('Selected processes'!$N$5:$N$97, MATCH('Carbon footprint calculator'!$A32,'Selected processes'!$D$5:$D$97,0)) -> 67.934853 | R32: =Q32*$F32 -> 0.013586971 | S32: =R32/R$49 -> 0.0033479585 | T32: =I32/R32*$B$18 -> 21.298609
A33: 17773 | B33: tap water | C33: =INDEX('Selected processes'!$E$5:$E$97, MATCH('Carbon footprint calculator'!$A33,'Selected processes'!$D$5:$D$97,0)) -> tap water production, conventional treatment | D33: =INDEX('Selected processes'!$F$5:$F$97, MATCH('Carbon footprint calculator'!$A33,'Selected processes'!$D$5:$D$97,0)) -> RoW | E33: 3400 | F33: =E33/$C$20 -> 0.022666667 | G33: =INDEX('Selected processes'!$H$5:$H$97, MATCH('Carbon footprint calculator'!$A33,'Selected processes'!$D$5:$D$97,0)) -> kg | H33: =INDEX('Selected processes'!$J$5:$J$97, MATCH('Carbon footprint calculator'!$A33,'Selected processes'!$D$5:$D$97,0)) -> 0.00043545824 | I33: =H33*$F33 -> 9.8703867e-06 | J33: =I33/I$49 -> 3.1779685e-05 | K33: =INDEX('Selected processes'!$K$5:$K$97, MATCH('Carbon footprint calculator'!$A33,'Selected processes'!$D$5:$D$97,0)) -> 0.00063383807 | L33: =K33*$F33 -> 1.4366996e-05 | M33: =L33/L$49 -> -4.9974694e-05 | N33: =INDEX('Selected processes'!$L$5:$L$97, MATCH('Carbon footprint calculator'!$A33,'Selected processes'!$D$5:$D$97,0)) -> 1.9288846e-12 | O33: =N33*$F33 -> 4.3721384e-14 | P33: =O33/O$49 -> 2.86238e-05 | Q33: =INDEX('Selected processes'!$N$5:$N$97, MATCH('Carbon footprint calculator'!$A33,'Selected processes'!$D$5:$D$97,0)) -> 0.0056091535 | R33: =Q33*$F33 -> 0.00012714081 | S33: =R33/R$49 -> 3.1328703e-05 | T33: =I33/R33*$B$18 -> 77.633503
A34: 9148 | B34: heat, district or industrial, natural gas | C34: =INDEX('Selected processes'!$E$5:$E$97, MATCH('Carbon footprint calculator'!$A34,'Selected processes'!$D$5:$D$97,0)) -> heat production, natural gas, at industrial furnace >100kW | D34: =INDEX('Selected processes'!$F$5:$F$97, MATCH('Carbon footprint calculator'!$A34,'Selected processes'!$D$5:$D$97,0)) -> Europe without Switzerland | E34: 2400 | F34: =E34/$C$20 -> 0.016 | G34: =INDEX('Selected processes'!$H$5:$H$97, MATCH('Carbon footprint calculator'!$A34,'Selected processes'!$D$5:$D$97,0)) -> MJ | H34: =INDEX('Selected processes'!$J$5:$J$97, MATCH('Carbon footprint calculator'!$A34,'Selected processes'!$D$5:$D$97,0)) -> 0.075656104 | I34: =H34*$F34 -> 0.0012104977 | J34: =I34/I$49 -> 0.0038974394 | K34: =INDEX('Selected processes'!$K$5:$K$97, MATCH('Carbon footprint calculator'!$A34,'Selected processes'!$D$5:$D$97,0)) -> 0.044167738 | L34: =K34*$F34 -> 0.00070668381 | M34: =L34/L$49 -> -0.0024581552 | N34: =INDEX('Selected processes'!$L$5:$L$97, MATCH('Carbon footprint calculator'!$A34,'Selected processes'!$D$5:$D$97,0)) -> 2.338698e-10 | O34: =N34*$F34 -> 3.7419167e-12 | P34: =O34/O$49 -> 0.0024497824 | Q34: =INDEX('Selected processes'!$N$5:$N$97, MATCH('Carbon footprint calculator'!$A34,'Selected processes'!$D$5:$D$97,0)) -> 1.2643686 | R34: =Q34*$F34 -> 0.020229898 | S34: =R34/R$49 -> 0.0049848388 | T34: =I34/R34*$B$18 -> 59.837064
A35: 7235 | B35: electricity, medium voltage | C35: =INDEX('Selected processes'!$E$5:$E$97, MATCH('Carbon footprint calculator'!$A35,'Selected processes'!$D$5:$D$97,0)) -> market group for electricity, medium voltage | D35: =INDEX('Selected processes'!$F$5:$F$97, MATCH('Carbon footprint calculator'!$A35,'Selected processes'!$D$5:$D$97,0)) -> UCTE | E35: 2250 | F35: =E35/$C$20 -> 0.015 | G35: =INDEX('Selected processes'!$H$5:$H$97, MATCH('Carbon footprint calculator'!$A35,'Selected processes'!$D$5:$D$97,0)) -> kWh | H35: =INDEX('Selected processes'!$J$5:$J$97, MATCH('Carbon footprint calculator'!$A35,'Selected processes'!$D$5:$D$97,0)) -> 0.38493508 | I35: =H35*$F35 -> 0.0057740262 | J35: =I35/I$49 -> 0.018590632 | K35: =INDEX('Selected processes'!$K$5:$K$97, MATCH('Carbon footprint calculator'!$A35,'Selected processes'!$D$5:$D$97,0)) -> 0.48931866 | L35: =K35*$F35 -> 0.0073397799 | M35: =L35/L$49 -> -0.025530964 | N35: =INDEX('Selected processes'!$L$5:$L$97, MATCH('Carbon footprint calculator'!$A35,'Selected processes'!$D$5:$D$97,0)) -> 1.8304805e-09 | O35: =N35*$F35 -> 2.7457208e-11 | P35: =O35/O$49 -> 0.017975863 | Q35: =INDEX('Selected processes'!$N$5:$N$97, MATCH('Carbon footprint calculator'!$A35,'Selected processes'!$D$5:$D$97,0)) -> 8.8834816 | R35: =Q35*$F35 -> 0.13325222 | S35: =R35/R$49 -> 0.032834613 | T35: =I35/R35*$B$18 -> 43.331556
B36: Transportation | C36: Transportation | E36: per vehicle | F36: per FU
A37: 18124 | B37: transport, freight train | C37: =INDEX('Selected processes'!$E$5:$E$97, MATCH('Carbon footprint calculator'!$A37,'Selected processes'!$D$5:$D$97,0)) -> market group for transport, freight train | D37: =INDEX('Selected processes'!$F$5:$F$97, MATCH('Carbon footprint calculator'!$A37,'Selected processes'!$D$5:$D$97,0)) -> RER | E37: 556.5 | F37: =E37/$C$20 -> 0.00371 | G37: =INDEX('Selected processes'!$H$5:$H$97, MATCH('Carbon footprint calculator'!$A37,'Selected processes'!$D$5:$D$97,0)) -> metric ton*km | H37: =INDEX('Selected processes'!$J$5:$J$97, MATCH('Carbon footprint calculator'!$A37,'Selected processes'!$D$5:$D$97,0)) -> 0.045728106 | I37: =H37*$F37 -> 0.00016965127 | J37: =I37/I$49 -> 0.00054622622 | K37: =INDEX('Selected processes'!$K$5:$K$97, MATCH('Carbon footprint calculator'!$A37,'Selected processes'!$D$5:$D$97,0)) -> 0.068157807 | L37: =K37*$F37 -> 0.00025286546 | M37: =L37/L$49 -> -0.00087957663 | N37: =INDEX('Selected processes'!$L$5:$L$97, MATCH('Carbon footprint calculator'!$A37,'Selected processes'!$D$5:$D$97,0)) -> 2.5241034e-10 | O37: =N37*$F37 -> 9.3644236e-13 | P37: =O37/O$49 -> 0.00061307617 | Q37: =INDEX('Selected processes'!$N$5:$N$97, MATCH('Carbon footprint calculator'!$A37,'Selected processes'!$D$5:$D$97,0)) -> 0.71319593 | R37: =Q37*$F37 -> 0.0026459569 | S37: =R37/R$49 -> 0.00065198891 | T37: =I37/R37*$B$18 -> 64.117172
A38: 18241 | B38: transport, freight, lorry 16-32 metric ton | C38: =INDEX('Selected processes'!$E$5:$E$97, MATCH('Carbon footprint calculator'!$A38,'Selected processes'!$D$5:$D$97,0)) -> market for transport, freight, lorry 16-32 metric ton, EURO4 | D38: =INDEX('Selected processes'!$F$5:$F$97, MATCH('Carbon footprint calculator'!$A38,'Selected processes'!$D$5:$D$97,0)) -> RoW | E38: 59.1 | F38: =E38/$C$20 -> 0.000394 | G38: =INDEX('Selected processes'!$H$5:$H$97, MATCH('Carbon footprint calculator'!$A38,'Selected processes'!$D$5:$D$97,0)) -> metric ton*km | H38: =INDEX('Selected processes'!$J$5:$J$97, MATCH('Carbon footprint calculator'!$A38,'Selected processes'!$D$5:$D$97,0)) -> 0.19079134 | I38: =H38*$F38 -> 7.517179e-05 | J38: =I38/I$49 -> 0.00024203062 | K38: =INDEX('Selected processes'!$K$5:$K$97, MATCH('Carbon footprint calculator'!$A38,'Selected processes'!$D$5:$D$97,0)) -> 0.20108682 | L38: =K38*$F38 -> 7.9228205e-05 | M38: =L38/L$49 -> -0.00027559034 | N38: =INDEX('Selected processes'!$L$5:$L$97, MATCH('Carbon footprint calculator'!$A38,'Selected processes'!$D$5:$D$97,0)) -> 8.7787947e-10 | O38: =N38*$F38 -> 3.4588451e-13 | P38: =O38/O$49 -> 0.00022644592 | Q38: =INDEX('Selected processes'!$N$5:$N$97, MATCH('Carbon footprint calculator'!$A38,'Selected processes'!$D$5:$D$97,0)) -> 2.8903577 | R38: =Q38*$F38 -> 0.0011388009 | S38: =R38/R$49 -> 0.00028061136 | T38: =I38/R38*$B$18 -> 66.009596
A39: 18438 | B39: transport, freight, sea, container ship | C39: =INDEX('Selected processes'!$E$5:$E$97, MATCH('Carbon footprint calculator'!$A39,'Selected processes'!$D$5:$D$97,0)) -> transport, freight, sea, container ship | D39: =INDEX('Selected processes'!$F$5:$F$97, MATCH('Carbon footprint calculator'!$A39,'Selected processes'!$D$5:$D$97,0)) -> GLO | E39: =(E23+SUM(E25:E32))*8000/1000 -> 11376.814 | F39: =E39/$C$20 -> 0.075845424 | G39: =INDEX('Selected processes'!$H$5:$H$97, MATCH('Carbon footprint calculator'!$A39,'Selected processes'!$D$5:$D$97,0)) -> metric ton*km | H39: =INDEX('Selected processes'!$J$5:$J$97, MATCH('Carbon footprint calculator'!$A39,'Selected processes'!$D$5:$D$97,0)) -> 0.010163513 | I39: =H39*$F39 -> 0.00077085596 | J39: =I39/I$49 -> 0.002481925 | K39: =INDEX('Selected processes'!$K$5:$K$97, MATCH('Carbon footprint calculator'!$A39,'Selected processes'!$D$5:$D$97,0)) -> 0.026445888 | L39: =K39*$F39 -> 0.0020057996 | M39: =L39/L$49 -> -0.0069770478 | N39: =INDEX('Selected processes'!$L$5:$L$97, MATCH('Carbon footprint calculator'!$A39,'Selected processes'!$D$5:$D$97,0)) -> 9.6094188e-11 | O39: =N39*$F39 -> 7.2883044e-12 | P39: =O39/O$49 -> 0.0047715545 | Q39: =INDEX('Selected processes'!$N$5:$N$97, MATCH('Carbon footprint calculator'!$A39,'Selected processes'!$D$5:$D$97,0)) -> 0.13313526 | R39: =Q39*$F39 -> 0.0100977 | S39: =R39/R$49 -> 0.0024881691 | T39: =I39/R39*$B$18 -> 76.339757
B40: Use phase | C40: Use phase | E40: per V-km | F40: per FU
A41: 100002 | B41: Health benefit from driving phys. Activivity | C41: =INDEX('Selected processes'!$E$5:$E$97, MATCH('Carbon footprint calculator'!$A41,'Selected processes'!$D$5:$D$97,0)) -> Driving a car | D41: =INDEX('Selected processes'!$F$5:$F$97, MATCH('Carbon footprint calculator'!$A41,'Selected processes'!$D$5:$D$97,0)) -> driving an automobile | E41: 1 | F41: 1 | G41: =INDEX('Selected processes'!$H$5:$H$97, MATCH('Carbon footprint calculator'!$A41,'Selected processes'!$D$5:$D$97,0)) -> km | H41: =INDEX('Selected processes'!$J$5:$J$97, MATCH('Carbon footprint calculator'!$A41,'Selected processes'!$D$5:$D$97,0)) -> 0 | I41: =H41*$F41 -> 0 | J41: =I41/I$49 -> 0 | K41: =INDEX('Selected processes'!$K$5:$K$97, MATCH('Carbon footprint calculator'!$A41,'Selected processes'!$D$5:$D$97,0)) -> -0.72627994 | L41: =K41*$F41 -> -0.72627994 | M41: =L41/L$49 -> 2.5263192 | N41: =INDEX('Selected processes'!$L$5:$L$97, MATCH('Carbon footprint calculator'!$A41,'Selected processes'!$D$5:$D$97,0)) -> 0 | O41: =N41*$F41 -> 0 | P41: =O41/O$49 -> 0 | Q41: =INDEX('Selected processes'!$N$5:$N$97, MATCH('Carbon footprint calculator'!$A41,'Selected processes'!$D$5:$D$97,0)) -> 0 | R41: =Q41*$F41 -> 0 | S41: =R41/R$49 -> 0 | T41: =I41/R41*$B$18 -> #DIV/0!
A42: 14137 | B42: Supply chain petrol, low-sulfur | C42: =INDEX('Selected processes'!$E$5:$E$97, MATCH('Carbon footprint calculator'!$A42,'Selected processes'!$D$5:$D$97,0)) -> market for petrol, low-sulfur | D42: =INDEX('Selected processes'!$F$5:$F$97, MATCH('Carbon footprint calculator'!$A42,'Selected processes'!$D$5:$D$97,0)) -> Europe without Switzerland | E42: 0.061904762 | F42: =E42 -> 0.061904762 | G42: =INDEX('Selected processes'!$H$5:$H$97, MATCH('Carbon footprint calculator'!$A42,'Selected processes'!$D$5:$D$97,0)) -> kg | H42: =INDEX('Selected processes'!$J$5:$J$97, MATCH('Carbon footprint calculator'!$A42,'Selected processes'!$D$5:$D$97,0)) -> 1.0179093 | I42: =H42*$F42 -> 0.06301343 | J42: =I42/I$49 -> 0.20288435 | K42: =INDEX('Selected processes'!$K$5:$K$97, MATCH('Carbon footprint calculator'!$A42,'Selected processes'!$D$5:$D$97,0)) -> 1.0613393 | L42: =K42*$F42 -> 0.065701956 | M42: =L42/L$49 -> -0.22854013 | N42: =INDEX('Selected processes'!$L$5:$L$97, MATCH('Carbon footprint calculator'!$A42,'Selected processes'!$D$5:$D$97,0)) -> 4.4865308e-09 | O42: =N42*$F42 -> 2.7773762e-10 | P42: =O42/O$49 -> 0.18183107 | Q42: =INDEX('Selected processes'!$N$5:$N$97, MATCH('Carbon footprint calculator'!$A42,'Selected processes'!$D$5:$D$97,0)) -> 56.767141 | R42: =Q42*$F42 -> 3.5141563 | S42: =R42/R$49 -> 0.86592149 | T42: =I42/R42*$B$18 -> 17.931311
A43: 100001 | B43: Direct combustion | C43: =INDEX('Selected processes'!$E$5:$E$97, MATCH('Carbon footprint calculator'!$A43,'Selected processes'!$D$5:$D$97,0)) -> Emissions & operation of vehicle | D43: =INDEX('Selected processes'!$F$5:$F$97, MATCH('Carbon footprint calculator'!$A43,'Selected processes'!$D$5:$D$97,0)) -> RER | E43: 0.061904762 | F43: =E43 -> 0.061904762 | G43: =INDEX('Selected processes'!$H$5:$H$97, MATCH('Carbon footprint calculator'!$A43,'Selected processes'!$D$5:$D$97,0)) -> kg petrol | H43: =INDEX('Selected processes'!$J$5:$J$97, MATCH('Carbon footprint calculator'!$A43,'Selected processes'!$D$5:$D$97,0)) -> 3.4252308 | I43: =H43*$F43 -> 0.2120381 | J43: =I43/I$49 -> 0.68269907 | K43: =INDEX('Selected processes'!$K$5:$K$97, MATCH('Carbon footprint calculator'!$A43,'Selected processes'!$D$5:$D$97,0)) -> 4.5694635 | L43: =K43*$F43 -> 0.28287155 | M43: =L43/L$49 -> -0.98395091 | N43: =INDEX('Selected processes'!$L$5:$L$97, MATCH('Carbon footprint calculator'!$A43,'Selected processes'!$D$5:$D$97,0)) -> 1.7432418e-08 | O43: =N43*$F43 -> 1.0791497e-09 | P43: =O43/O$49 -> 0.70650473 | Q43: =INDEX('Selected processes'!$N$5:$N$97, MATCH('Carbon footprint calculator'!$A43,'Selected processes'!$D$5:$D$97,0)) -> 0 | R43: =Q43*$F43 -> 0 | S43: =R43/R$49 -> 0 | T43: =I43/R43*$B$18 -> #DIV/0!
B44: Disposal | C44: Disposal | E44: per vehicle over lifespan | F44: per FU
A45: 19923 | B45: plastic mixture incineration | C45: =INDEX('Selected processes'!$E$5:$E$97, MATCH('Carbon footprint calculator'!$A45,'Selected processes'!$D$5:$D$97,0)) -> treatment of waste plastic, mixture, municipal incineration | D45: =INDEX('Selected processes'!$F$5:$F$97, MATCH('Carbon footprint calculator'!$A45,'Selected processes'!$D$5:$D$97,0)) -> CH | E45: =E28+E29 -> 221 | F45: =E45/$C$20 -> 0.0014733333 | G45: =INDEX('Selected processes'!$H$5:$H$97, MATCH('Carbon footprint calculator'!$A45,'Selected processes'!$D$5:$D$97,0)) -> kg | H45: =INDEX('Selected processes'!$J$5:$J$97, MATCH('Carbon footprint calculator'!$A45,'Selected processes'!$D$5:$D$97,0)) -> 2.3457342 | I45: =H45*$F45 -> 0.0034560484 | J45: =I45/I$49 -> 0.011127439 | K45: =INDEX('Selected processes'!$K$5:$K$97, MATCH('Carbon footprint calculator'!$A45,'Selected processes'!$D$5:$D$97,0)) -> 1.3115341 | L45: =K45*$F45 -> 0.001932327 | M45: =L45/L$49 -> -0.006721478 | N45: =INDEX('Selected processes'!$L$5:$L$97, MATCH('Carbon footprint calculator'!$A45,'Selected processes'!$D$5:$D$97,0)) -> 6.7933555e-09 | O45: =N45*$F45 -> 1.0008877e-11 | P45: =O45/O$49 -> 0.0065526768 | Q45: =INDEX('Selected processes'!$N$5:$N$97, MATCH('Carbon footprint calculator'!$A45,'Selected processes'!$D$5:$D$97,0)) -> 0.48721305 | R45: =Q45*$F45 -> 0.00071782723 | S45: =R45/R$49 -> 0.00017687944 | T45: =I45/R45*$B$18 -> 4814.5964
A46: 19515 | B46: Glass to landfill | C46: =INDEX('Selected processes'!$E$5:$E$97, MATCH('Carbon footprint calculator'!$A46,'Selected processes'!$D$5:$D$97,0)) -> treatment of waste glass, inert material landfill | D46: =INDEX('Selected processes'!$F$5:$F$97, MATCH('Carbon footprint calculator'!$A46,'Selected processes'!$D$5:$D$97,0)) -> CH | E46: =E28+E29+E30+E32 -> 283 | F46: =E46/$C$20 -> 0.0018866667 | G46: =INDEX('Selected processes'!$H$5:$H$97, MATCH('Carbon footprint calculator'!$A46,'Selected processes'!$D$5:$D$97,0)) -> kg | H46: =INDEX('Selected processes'!$J$5:$J$97, MATCH('Carbon footprint calculator'!$A46,'Selected processes'!$D$5:$D$97,0)) -> 0.0056607781 | I46: =H46*$F46 -> 1.0680001e-05 | J46: =I46/I$49 -> 3.4386401e-05 | K46: =INDEX('Selected processes'!$K$5:$K$97, MATCH('Carbon footprint calculator'!$A46,'Selected processes'!$D$5:$D$97,0)) -> 0.0067425637 | L46: =K46*$F46 -> 1.272097e-05 | M46: =L46/L$49 -> -4.4249096e-05 | N46: =INDEX('Selected processes'!$L$5:$L$97, MATCH('Carbon footprint calculator'!$A46,'Selected processes'!$D$5:$D$97,0)) -> 3.4762451e-11 | O46: =N46*$F46 -> 6.5585158e-14 | P46: =O46/O$49 -> 4.2937718e-05 | Q46: =INDEX('Selected processes'!$N$5:$N$97, MATCH('Carbon footprint calculator'!$A46,'Selected processes'!$D$5:$D$97,0)) -> 0.15415625 | R46: =Q46*$F46 -> 0.00029084145 | S46: =R46/R$49 -> 7.1666095e-05 | T46: =I46/R46*$B$18 -> 36.721043
A47: 7235 | B47: Avoided electricity plastic incineration | C47: =INDEX('Selected processes'!$E$5:$E$97, MATCH('Carbon footprint calculator'!$A47,'Selected processes'!$D$5:$D$97,0)) -> market group for electricity, medium voltage | D47: =INDEX('Selected processes'!$F$5:$F$97, MATCH('Carbon footprint calculator'!$A47,'Selected processes'!$D$5:$D$97,0)) -> UCTE | E47: =E45 -> 221 | F47: =-E47/$C$20*$E$17*$E$18/$E$19 -> -0.0043483796 | G47: =INDEX('Selected processes'!$H$5:$H$97, MATCH('Carbon footprint calculator'!$A47,'Selected processes'!$D$5:$D$97,0)) -> kWh | H47: =INDEX('Selected processes'!$J$5:$J$97, MATCH('Carbon footprint calculator'!$A47,'Selected processes'!$D$5:$D$97,0)) -> 0.38493508 | I47: =H47*$F47 -> -0.0016738438 | J47: =I47/I$49 -> -0.0053892752 | K47: =INDEX('Selected processes'!$K$5:$K$97, MATCH('Carbon footprint calculator'!$A47,'Selected processes'!$D$5:$D$97,0)) -> 0.48931866 | L47: =K47*$F47 -> -0.0021277433 | M47: =L47/L$49 -> 0.0074012214 | N47: =INDEX('Selected processes'!$L$5:$L$97, MATCH('Carbon footprint calculator'!$A47,'Selected processes'!$D$5:$D$97,0)) -> 1.8304805e-09 | O47: =N47*$F47 -> -7.9596242e-12 | P47: =O47/O$49 -> -0.0052110586 | Q47: =INDEX('Selected processes'!$N$5:$N$97, MATCH('Carbon footprint calculator'!$A47,'Selected processes'!$D$5:$D$97,0)) -> 8.8834816 | R47: =Q47*$F47 -> -0.03862875 | S47: =R47/R$49 -> -0.0095184909 | T47: =I47/R47*$B$18 -> 43.331556
B48: Total | C48: Total
C49: Total | G49: - | I49: =SUM(I23:I47) -> 0.31058794 | J49: =I49/I$49 -> 1 | L49: =SUM(L23:L47) -> -0.28748543 | M49: =L49/L$49 -> 1 | O49: =SUM(O23:O47) -> 1.5274486e-09 | P49: =O49/O$49 -> 1 | R49: =SUM(R23:R47) -> 4.0582852 | S49: =R49/R$49 -> 1 | T49: =I49/R49*$B$18 -> 76.531816
B53: Vehicle lifespan (km/vehicle) | C53: 225000
A54: Process # | B54: Transportation by Electric Car FU= 1 vehicle km Life Cycle stage (225,000 km lifespan) | C54: Ecoinvent process | D54: Region | E54: Quantity per unit | F54: Quantity per FU | G54: Unit | H54: Carbon footprint [kgCO2equ/unit] | I54: Carbon footprint [CO2equ./FU] | J54: fraction carbon footprint | K54: Human health/Unit [min. lost/unit] | L54: Human health [min. lost/FU] | M54: fraction human health | N54: Ecosystem quality impacts/Unit [species-yr/unit] | O54: Ecosystem quality impacts [Species-yr/FU] | P54: fraction ecosystem quality | Q54: Non renewable primary energy resources/unit [MJ/unit] | R54: Non renewable primary energy resources impacts [MJ/FU] | S54: fraction non renewable primary energy | T54: Check [gCO2e/MJ]
B55: Manufacturing (Materials + Processing) | C55: Manufacturing (Materials + Processing) | E55: per vehicle over lifespan | F55: per V-km
A56: 17299 | B56: steel, low-alloyed, hot rolled | C56: =INDEX('Selected processes'!$E$5:$E$97, MATCH('Carbon footprint calculator'!$A56,'Selected processes'!$D$5:$D$97,0)) -> steel production, low-alloyed, hot rolled | D56: =INDEX('Selected processes'!$F$5:$F$97, MATCH('Carbon footprint calculator'!$A56,'Selected processes'!$D$5:$D$97,0)) -> RER | E56: 953.4 | F56: =E56/$C$53 -> 0.0042373333 | G56: =INDEX('Selected processes'!$H$5:$H$97, MATCH('Carbon footprint calculator'!$A56,'Selected processes'!$D$5:$D$97,0)) -> kg | H56: =INDEX('Selected processes'!$J$5:$J$97, MATCH('Carbon footprint calculator'!$A56,'Selected processes'!$D$5:$D$97,0)) -> 2.1807172 | I56: =H56*$F56 -> 0.0092404259 | J56: =I56/I$87 -> 0.061909577 | K56: =INDEX('Selected processes'!$K$5:$K$97, MATCH('Carbon footprint calculator'!$A56,'Selected processes'!$D$5:$D$97,0)) -> 7.9963289 | L56: =K56*$F56 -> 0.033883111 | M56: =L56/L$49 -> -0.11786027 | N56: =INDEX('Selected processes'!$L$5:$L$97, MATCH('Carbon footprint calculator'!$A56,'Selected processes'!$D$5:$D$97,0)) -> 9.7808189e-09 | O56: =N56*$F56 -> 4.144459e-11 | P56: =O56/O$87 -> 0.054971017 | Q56: =INDEX('Selected processes'!$N$5:$N$97, MATCH('Carbon footprint calculator'!$A56,'Selected processes'!$D$5:$D$97,0)) -> 25.556652 | R56: =Q56*$F56 -> 0.10829205 | S56: =R56/R$87 -> 0.036238309 | T56: =I56/R56*$B$18 -> 85.328752
A57: 12482 | B57: Metal working, average for steel product manufacturing | C57: =INDEX('Selected processes'!$E$5:$E$97, MATCH('Carbon footprint calculator'!$A57,'Selected processes'!$D$5:$D$97,0)) -> metal working, average for metal product manufacturing | D57: =INDEX('Selected processes'!$F$5:$F$97, MATCH('Carbon footprint calculator'!$A57,'Selected processes'!$D$5:$D$97,0)) -> RER | E57: 953.4 | F57: =E57/$C$53 -> 0.0042373333 | G57: =INDEX('Selected processes'!$H$5:$H$97, MATCH('Carbon footprint calculator'!$A57,'Selected processes'!$D$5:$D$97,0)) -> kg | H57: =INDEX('Selected processes'!$J$5:$J$97, MATCH('Carbon footprint calculator'!$A57,'Selected processes'!$D$5:$D$97,0)) -> 1.8612564 | I57: =H57*$F57 -> 0.0078867637 | J57: =I57/I$87 -> 0.052840228 | K57: =INDEX('Selected processes'!$K$5:$K$97, MATCH('Carbon footprint calculator'!$A57,'Selected processes'!$D$5:$D$97,0)) -> 6.3717697 | L57: =K57*$F57 -> 0.026999312 | M57: =L57/L$87 -> 0.10650799 | N57: =INDEX('Selected processes'!$L$5:$L$97, MATCH('Carbon footprint calculator'!$A57,'Selected processes'!$D$5:$D$97,0)) -> 1.3596458e-08 | O57: =N57*$F57 -> 5.7612727e-11 | P57: =O57/O$87 -> 0.07641601 | Q57: =INDEX('Selected processes'!$N$5:$N$97, MATCH('Carbon footprint calculator'!$A57,'Selected processes'!$D$5:$D$97,0)) -> 27.640336 | R57: =Q57*$F57 -> 0.11712132 | S57: =R57/R$87 -> 0.039192888 | T57: =I57/R57*$B$18 -> 67.338414
A58: 458 | B58: aluminium, primary, ingot | C58: =INDEX('Selected processes'!$E$5:$E$97, MATCH('Carbon footprint calculator'!$A58,'Selected processes'!$D$5:$D$97,0)) -> aluminium production, primary, ingot | D58: =INDEX('Selected processes'!$F$5:$F$97, MATCH('Carbon footprint calculator'!$A58,'Selected processes'!$D$5:$D$97,0)) -> IAI Area, EU27 & EFTA | E58: 76.5 | F58: =E58/$C$53 -> 0.00034 | G58: =INDEX('Selected processes'!$H$5:$H$97, MATCH('Carbon footprint calculator'!$A58,'Selected processes'!$D$5:$D$97,0)) -> kg | H58: =INDEX('Selected processes'!$J$5:$J$97, MATCH('Carbon footprint calculator'!$A58,'Selected processes'!$D$5:$D$97,0)) -> 7.209838 | I58: =H58*$F58 -> 0.0024513449 | J58: =I58/I$87 -> 0.016423673 | K58: =INDEX('Selected processes'!$K$5:$K$97, MATCH('Carbon footprint calculator'!$A58,'Selected processes'!$D$5:$D$97,0)) -> 13.333429 | L58: =K58*$F58 -> 0.0045333659 | M58: =L58/L$87 -> 0.017883407 | N58: =INDEX('Selected processes'!$L$5:$L$97, MATCH('Carbon footprint calculator'!$A58,'Selected processes'!$D$5:$D$97,0)) -> 3.2653298e-08 | O58: =N58*$F58 -> 1.1102121e-11 | P58: =O58/O$87 -> 0.014725562 | Q58: =INDEX('Selected processes'!$N$5:$N$97, MATCH('Carbon footprint calculator'!$A58,'Selected processes'!$D$5:$D$97,0)) -> 115.04046 | R58: =Q58*$F58 -> 0.039113758 | S58: =R58/R$87 -> 0.013088831 | T58: =I58/R58*$B$18 -> 62.672192
A59: 16616 | B59: Copper | C59: =INDEX('Selected processes'!$E$5:$E$97, MATCH('Carbon footprint calculator'!$A59,'Selected processes'!$D$5:$D$97,0)) -> sheet rolling, copper | D59: =INDEX('Selected processes'!$F$5:$F$97, MATCH('Carbon footprint calculator'!$A59,'Selected processes'!$D$5:$D$97,0)) -> RER | E59: 287.1 | F59: =E59/$C$53 -> 0.001276 | G59: =INDEX('Selected processes'!$H$5:$H$97, MATCH('Carbon footprint calculator'!$A59,'Selected processes'!$D$5:$D$97,0)) -> kg | H59: =INDEX('Selected processes'!$J$5:$J$97, MATCH('Carbon footprint calculator'!$A59,'Selected processes'!$D$5:$D$97,0)) -> 0.48163006 | I59: =H59*$F59 -> 0.00061455996 | J59: =I59/I$87 -> 0.0041174669 | K59: =INDEX('Selected processes'!$K$5:$K$97, MATCH('Carbon footprint calculator'!$A59,'Selected processes'!$D$5:$D$97,0)) -> 4.9624408 | L59: =K59*$F59 -> 0.0063320745 | M59: =L59/L$87 -> 0.024979026 | N59: =INDEX('Selected processes'!$L$5:$L$97, MATCH('Carbon footprint calculator'!$A59,'Selected processes'!$D$5:$D$97,0)) -> 9.7940056e-09 | O59: =N59*$F59 -> 1.2497151e-11 | P59: =O59/O$87 -> 0.016575894 | Q59: =INDEX('Selected processes'!$N$5:$N$97, MATCH('Carbon footprint calculator'!$A59,'Selected processes'!$D$5:$D$97,0)) -> 7.1938644 | R59: =Q59*$F59 -> 0.0091793709 | S59: =R59/R$87 -> 0.0030717385 | T59: =I59/R59*$B$18 -> 66.950117
A60: 7694 | B60: Extruded thermoformed plastic sheets | C60: =INDEX('Selected processes'!$E$5:$E$97, MATCH('Carbon footprint calculator'!$A60,'Selected processes'!$D$5:$D$97,0)) -> extrusion of plastic sheets and thermoforming, inline | D60: =INDEX('Selected processes'!$F$5:$F$97, MATCH('Carbon footprint calculator'!$A60,'Selected processes'!$D$5:$D$97,0)) -> RoW | E60: 162.9 | F60: =E60/$C$53 -> 0.000724 | G60: =INDEX('Selected processes'!$H$5:$H$97, MATCH('Carbon footprint calculator'!$A60,'Selected processes'!$D$5:$D$97,0)) -> kg | H60: =INDEX('Selected processes'!$J$5:$J$97, MATCH('Carbon footprint calculator'!$A60,'Selected processes'!$D$5:$D$97,0)) -> 1.0973734 | I60: =H60*$F60 -> 0.00079449831 | J60: =I60/I$87 -> 0.005323029 | K60: =INDEX('Selected processes'!$K$5:$K$97, MATCH('Carbon footprint calculator'!$A60,'Selected processes'!$D$5:$D$97,0)) -> 1.5186295 | L60: =K60*$F60 -> 0.0010994878 | M60: =L60/L$87 -> 0.0043373043 | N60: =INDEX('Selected processes'!$L$5:$L$97, MATCH('Carbon footprint calculator'!$A60,'Selected processes'!$D$5:$D$97,0)) -> 4.7148823e-09 | O60: =N60*$F60 -> 3.4135748e-12 | P60: =O60/O$87 -> 0.0045276761 | Q60: =INDEX('Selected processes'!$N$5:$N$97, MATCH('Carbon footprint calculator'!$A60,'Selected processes'!$D$5:$D$97,0)) -> 14.405397 | R60: =Q60*$F60 -> 0.010429507 | S60: =R60/R$87 -> 0.0034900778 | T60: =I60/R60*$B$18 -> 76.177934
A61: 14673 | B61: Polypropylene & polyurethane | C61: =INDEX('Selected processes'!$E$5:$E$97, MATCH('Carbon footprint calculator'!$A61,'Selected processes'!$D$5:$D$97,0)) -> polypropylene production, granulate | D61: =INDEX('Selected processes'!$F$5:$F$97, MATCH('Carbon footprint calculator'!$A61,'Selected processes'!$D$5:$D$97,0)) -> RER | E61: 172 | F61: =E61/$C$53 -> 0.00076444444 | G61: =INDEX('Selected processes'!$H$5:$H$97, MATCH('Carbon footprint calculator'!$A61,'Selected processes'!$D$5:$D$97,0)) -> kg | H61: =INDEX('Selected processes'!$J$5:$J$97, MATCH('Carbon footprint calculator'!$A61,'Selected processes'!$D$5:$D$97,0)) -> 1.8835237 | I61: =H61*$F61 -> 0.0014398493 | J61: =I61/I$87 -> 0.0096467912 | K61: =INDEX('Selected processes'!$K$5:$K$97, MATCH('Carbon footprint calculator'!$A61,'Selected processes'!$D$5:$D$97,0)) -> 1.6899833 | L61: =K61*$F61 -> 0.0012918984 | M61: =L61/L$87 -> 0.0050963335 | N61: =INDEX('Selected processes'!$L$5:$L$97, MATCH('Carbon footprint calculator'!$A61,'Selected processes'!$D$5:$D$97,0)) -> 7.2309967e-09 | O61: =N61*$F61 -> 5.5276953e-12 | P61: =O61/O$87 -> 0.0073317901 | Q61: =INDEX('Selected processes'!$N$5:$N$97, MATCH('Carbon footprint calculator'!$A61,'Selected processes'!$D$5:$D$97,0)) -> 78.229749 | R61: =Q61*$F61 -> 0.059802297 | S61: =R61/R$87 -> 0.02001194 | T61: =I61/R61*$B$18 -> 24.076822
A62: 17718 | B62: synthetic rubber | C62: =INDEX('Selected processes'!$E$5:$E$97, MATCH('Carbon footprint calculator'!$A62,'Selected processes'!$D$5:$D$97,0)) -> market for synthetic rubber | D62: =INDEX('Selected processes'!$F$5:$F$97, MATCH('Carbon footprint calculator'!$A62,'Selected processes'!$D$5:$D$97,0)) -> GLO | E62: 53.3 | F62: =E62/$C$53 -> 0.00023688889 | G62: =INDEX('Selected processes'!$H$5:$H$97, MATCH('Carbon footprint calculator'!$A62,'Selected processes'!$D$5:$D$97,0)) -> kg | H62: =INDEX('Selected processes'!$J$5:$J$97, MATCH('Carbon footprint calculator'!$A62,'Selected processes'!$D$5:$D$97,0)) -> 2.9677534 | I62: =H62*$F62 -> 0.00070302781 | J62: =I62/I$87 -> 0.0047101892 | K62: =INDEX('Selected processes'!$K$5:$K$97, MATCH('Carbon footprint calculator'!$A62,'Selected processes'!$D$5:$D$97,0)) -> 3.7317246 | L62: =K62*$F62 -> 0.0008840041 | M62: =L62/L$87 -> 0.0034872555 | N62: =INDEX('Selected processes'!$L$5:$L$97, MATCH('Carbon footprint calculator'!$A62,'Selected processes'!$D$5:$D$97,0)) -> 1.3250334e-08 | O62: =N62*$F62 -> 3.1388568e-12 | P62: =O62/O$87 -> 0.0041632973 | Q62: =INDEX('Selected processes'!$N$5:$N$97, MATCH('Carbon footprint calculator'!$A62,'Selected processes'!$D$5:$D$97,0)) -> 85.662707 | R62: =Q62*$F62 -> 0.020292543 | S62: =R62/R$87 -> 0.0067905947 | T62: =I62/R62*$B$18 -> 34.644637
A63: 7943 | B63: glas | C63: =INDEX('Selected processes'!$E$5:$E$97, MATCH('Carbon footprint calculator'!$A63,'Selected processes'!$D$5:$D$97,0)) -> market for flat glass, uncoated | D63: =INDEX('Selected processes'!$F$5:$F$97, MATCH('Carbon footprint calculator'!$A63,'Selected processes'!$D$5:$D$97,0)) -> RoW | E63: 49 | F63: =E63/$C$53 -> 0.00021777778 | G63: =INDEX('Selected processes'!$H$5:$H$97, MATCH('Carbon footprint calculator'!$A63,'Selected processes'!$D$5:$D$97,0)) -> kg | H63: =INDEX('Selected processes'!$J$5:$J$97, MATCH('Carbon footprint calculator'!$A63,'Selected processes'!$D$5:$D$97,0)) -> 1.0559546 | I63: =H63*$F63 -> 0.00022996344 | J63: =I63/I$87 -> 0.0015407233 | K63: =INDEX('Selected processes'!$K$5:$K$97, MATCH('Carbon footprint calculator'!$A63,'Selected processes'!$D$5:$D$97,0)) -> 1.4484757 | L63: =K63*$F63 -> 0.00031544581 | M63: =L63/L$87 -> 0.0012443835 | N63: =INDEX('Selected processes'!$L$5:$L$97, MATCH('Carbon footprint calculator'!$A63,'Selected processes'!$D$5:$D$97,0)) -> 5.395704e-09 | O63: =N63*$F63 -> 1.1750644e-12 | P63: =O63/O$87 -> 0.0015585746 | Q63: =INDEX('Selected processes'!$N$5:$N$97, MATCH('Carbon footprint calculator'!$A63,'Selected processes'!$D$5:$D$97,0)) -> 11.947723 | R63: =Q63*$F63 -> 0.0026019485 | S63: =R63/R$87 -> 0.00087070296 | T63: =I63/R63*$B$18 -> 88.381242
A64: 992 | B64: battery Li-ion recheargable, prismatic | C64: =INDEX('Selected processes'!$E$5:$E$97, MATCH('Carbon footprint calculator'!$A64,'Selected processes'!$D$5:$D$97,0)) -> battery production, Li-ion, LiMn2O4, rechargeable, prismatic | D64: =INDEX('Selected processes'!$F$5:$F$97, MATCH('Carbon footprint calculator'!$A64,'Selected processes'!$D$5:$D$97,0)) -> GLO | E64: 480 | F64: =E64/$C$53 -> 0.0021333333 | G64: =INDEX('Selected processes'!$H$5:$H$97, MATCH('Carbon footprint calculator'!$A64,'Selected processes'!$D$5:$D$97,0)) -> kg | H64: =INDEX('Selected processes'!$J$5:$J$97, MATCH('Carbon footprint calculator'!$A64,'Selected processes'!$D$5:$D$97,0)) -> 8.4296788 | I64: =H64*$F64 -> 0.017983315 | J64: =I64/I$87 -> 0.12048573 | K64: =INDEX('Selected processes'!$K$5:$K$97, MATCH('Carbon footprint calculator'!$A64,'Selected processes'!$D$5:$D$97,0)) -> 17.887181 | L64: =K64*$F64 -> 0.038159319 | M64: =L64/L$87 -> 0.15053244 | N64: =INDEX('Selected processes'!$L$5:$L$97, MATCH('Carbon footprint calculator'!$A64,'Selected processes'!$D$5:$D$97,0)) -> 4.8297512e-08 | O64: =N64*$F64 -> 1.0303469e-10 | P64: =O64/O$87 -> 0.13666251 | Q64: =INDEX('Selected processes'!$N$5:$N$97, MATCH('Carbon footprint calculator'!$A64,'Selected processes'!$D$5:$D$97,0)) -> 126.17824 | R64: =Q64*$F64 -> 0.26918025 | S64: =R64/R$87 -> 0.090077126 | T64: =I64/R64*$B$18 -> 66.807704
A65: 7364 | B65: electronics, for control units | C65: =INDEX('Selected processes'!$E$5:$E$97, MATCH('Carbon footprint calculator'!$A65,'Selected processes'!$D$5:$D$97,0)) -> electronics production, for control units | D65: =INDEX('Selected processes'!$F$5:$F$97, MATCH('Carbon footprint calculator'!$A65,'Selected processes'!$D$5:$D$97,0)) -> RER | E65: 23.3 | F65: =E65/$C$53 -> 0.00010355556 | G65: =INDEX('Selected processes'!$H$5:$H$97, MATCH('Carbon footprint calculator'!$A65,'Selected processes'!$D$5:$D$97,0)) -> kg | H65: =INDEX('Selected processes'!$J$5:$J$97, MATCH('Carbon footprint calculator'!$A65,'Selected processes'!$D$5:$D$97,0)) -> 31.86483 | I65: =H65*$F65 -> 0.0032997802 | J65: =I65/I$87 -> 0.022108071 | K65: =INDEX('Selected processes'!$K$5:$K$97, MATCH('Carbon footprint calculator'!$A65,'Selected processes'!$D$5:$D$97,0)) -> 91.052321 | L65: =K65*$F65 -> 0.0094289737 | M65: =L65/L$87 -> 0.037195801 | N65: =INDEX('Selected processes'!$L$5:$L$97, MATCH('Carbon footprint calculator'!$A65,'Selected processes'!$D$5:$D$97,0)) -> 2.0683158e-07 | O65: =N65*$F65 -> 2.141856e-11 | P65: =O65/O$87 -> 0.028409016 | Q65: =INDEX('Selected processes'!$N$5:$N$97, MATCH('Carbon footprint calculator'!$A65,'Selected processes'!$D$5:$D$97,0)) -> 451.55328 | R65: =Q65*$F65 -> 0.046760851 | S65: =R65/R$87 -> 0.015647816 | T65: =I65/R65*$B$18 -> 70.567154
A66: 7587 | B66: ethylene, paints, fluids | C66: =INDEX('Selected processes'!$E$5:$E$97, MATCH('Carbon footprint calculator'!$A66,'Selected processes'!$D$5:$D$97,0)) -> ethylene production, average | D66: =INDEX('Selected processes'!$F$5:$F$97, MATCH('Carbon footprint calculator'!$A66,'Selected processes'!$D$5:$D$97,0)) -> RER | E66: 22.2 | F66: =E66/$C$53 -> 9.8666667e-05 | G66: =INDEX('Selected processes'!$H$5:$H$97, MATCH('Carbon footprint calculator'!$A66,'Selected processes'!$D$5:$D$97,0)) -> kg | H66: =INDEX('Selected processes'!$J$5:$J$97, MATCH('Carbon footprint calculator'!$A66,'Selected processes'!$D$5:$D$97,0)) -> 1.4469179 | I66: =H66*$F66 -> 0.00014276256 | J66: =I66/I$87 -> 0.00095648946 | K66: =INDEX('Selected processes'!$K$5:$K$97, MATCH('Carbon footprint calculator'!$A66,'Selected processes'!$D$5:$D$97,0)) -> 1.1204239 | L66: =K66*$F66 -> 0.0001105485 | M66: =L66/L$87 -> 0.00043609622 | N66: =INDEX('Selected processes'!$L$5:$L$97, MATCH('Carbon footprint calculator'!$A66,'Selected processes'!$D$5:$D$97,0)) -> 5.2741423e-09 | O66: =N66*$F66 -> 5.2038204e-13 | P66: =O66/O$87 -> 0.00069022109 | Q66: =INDEX('Selected processes'!$N$5:$N$97, MATCH('Carbon footprint calculator'!$A66,'Selected processes'!$D$5:$D$97,0)) -> 67.934853 | R66: =Q66*$F66 -> 0.0067029055 | S66: =R66/R$87 -> 0.0022430266 | T66: =I66/R66*$B$18 -> 21.298609
A67: 17773 | B67: tap water | C67: =INDEX('Selected processes'!$E$5:$E$97, MATCH('Carbon footprint calculator'!$A67,'Selected processes'!$D$5:$D$97,0)) -> tap water production, conventional treatment | D67: =INDEX('Selected processes'!$F$5:$F$97, MATCH('Carbon footprint calculator'!$A67,'Selected processes'!$D$5:$D$97,0)) -> RoW | E67: 3400 | F67: =E67/$C$53 -> 0.015111111 | G67: =INDEX('Selected processes'!$H$5:$H$97, MATCH('Carbon footprint calculator'!$A67,'Selected processes'!$D$5:$D$97,0)) -> kg | H67: =INDEX('Selected processes'!$J$5:$J$97, MATCH('Carbon footprint calculator'!$A67,'Selected processes'!$D$5:$D$97,0)) -> 0.00043545824 | I67: =H67*$F67 -> 6.5802578e-06 | J67: =I67/I$87 -> 4.4086819e-05 | K67: =INDEX('Selected processes'!$K$5:$K$97, MATCH('Carbon footprint calculator'!$A67,'Selected processes'!$D$5:$D$97,0)) -> 0.00063383807 | L67: =K67*$F67 -> 9.5779975e-06 | M67: =L67/L$87 -> 3.7783676e-05 | N67: =INDEX('Selected processes'!$L$5:$L$97, MATCH('Carbon footprint calculator'!$A67,'Selected processes'!$D$5:$D$97,0)) -> 1.9288846e-12 | O67: =N67*$F67 -> 2.9147589e-14 | P67: =O67/O$87 -> 3.8660598e-05 | Q67: =INDEX('Selected processes'!$N$5:$N$97, MATCH('Carbon footprint calculator'!$A67,'Selected processes'!$D$5:$D$97,0)) -> 0.0056091535 | R67: =Q67*$F67 -> 8.4760542e-05 | S67: =R67/R$87 -> 2.8363841e-05 | T67: =I67/R67*$B$18 -> 77.633503
A68: 9148 | B68: heat, district or industrial, natural gas | C68: =INDEX('Selected processes'!$E$5:$E$97, MATCH('Carbon footprint calculator'!$A68,'Selected processes'!$D$5:$D$97,0)) -> heat production, natural gas, at industrial furnace >100kW | D68: =INDEX('Selected processes'!$F$5:$F$97, MATCH('Carbon footprint calculator'!$A68,'Selected processes'!$D$5:$D$97,0)) -> Europe without Switzerland | E68: 2400 | F68: =E68/$C$53 -> 0.010666667 | G68: =INDEX('Selected processes'!$H$5:$H$97, MATCH('Carbon footprint calculator'!$A68,'Selected processes'!$D$5:$D$97,0)) -> MJ | H68: =INDEX('Selected processes'!$J$5:$J$97, MATCH('Carbon footprint calculator'!$A68,'Selected processes'!$D$5:$D$97,0)) -> 0.075656104 | I68: =H68*$F68 -> 0.00080699845 | J68: =I68/I$87 -> 0.0054067782 | K68: =INDEX('Selected processes'!$K$5:$K$97, MATCH('Carbon footprint calculator'!$A68,'Selected processes'!$D$5:$D$97,0)) -> 0.044167738 | L68: =K68*$F68 -> 0.00047112254 | M68: =L68/L$87 -> 0.0018585034 | N68: =INDEX('Selected processes'!$L$5:$L$97, MATCH('Carbon footprint calculator'!$A68,'Selected processes'!$D$5:$D$97,0)) -> 2.338698e-10 | O68: =N68*$F68 -> 2.4946112e-12 | P68: =O68/O$87 -> 0.0033087868 | Q68: =INDEX('Selected processes'!$N$5:$N$97, MATCH('Carbon footprint calculator'!$A68,'Selected processes'!$D$5:$D$97,0)) -> 1.2643686 | R68: =Q68*$F68 -> 0.013486598 | S68: =R68/R$87 -> 0.0045130875 | T68: =I68/R68*$B$18 -> 59.837064
A69: 6295 | B69: electricity, photovoltaic, 570kWp open ground installation | C69: =INDEX('Selected processes'!$E$5:$E$97, MATCH('Carbon footprint calculator'!$A69,'Selected processes'!$D$5:$D$97,0)) -> electricity production, photovoltaic, 570kWp open ground installation, multi-Si | D69: =INDEX('Selected processes'!$F$5:$F$97, MATCH('Carbon footprint calculator'!$A69,'Selected processes'!$D$5:$D$97,0)) -> RoW | E69: 2500 | F69: =E69/$C$53 -> 0.011111111 | G69: =INDEX('Selected processes'!$H$5:$H$97, MATCH('Carbon footprint calculator'!$A69,'Selected processes'!$D$5:$D$97,0)) -> kWh | H69: =INDEX('Selected processes'!$J$5:$J$97, MATCH('Carbon footprint calculator'!$A69,'Selected processes'!$D$5:$D$97,0)) -> 0.080250611 | I69: =H69*$F69 -> 0.00089167345 | J69: =I69/I$87 -> 0.005974089 | K69: =INDEX('Selected processes'!$K$5:$K$97, MATCH('Carbon footprint calculator'!$A69,'Selected processes'!$D$5:$D$97,0)) -> 0.14759408 | L69: =K69*$F69 -> 0.0016399343 | M69: =L69/L$87 -> 0.0064692797 | N69: =INDEX('Selected processes'!$L$5:$L$97, MATCH('Carbon footprint calculator'!$A69,'Selected processes'!$D$5:$D$97,0)) -> 6.5404219e-10 | O69: =N69*$F69 -> 7.2671355e-12 | P69: =O69/O$87 -> 0.009638938 | Q69: =INDEX('Selected processes'!$N$5:$N$97, MATCH('Carbon footprint calculator'!$A69,'Selected processes'!$D$5:$D$97,0)) -> 1.0597105 | R69: =Q69*$F69 -> 0.011774561 | S69: =R69/R$87 -> 0.0039401797 | T69: =I69/R69*$B$18 -> 75.728809
B71: Transportation | C71: Transportation | E71: per vehicle | F71: per V-km
A72: 18124 | B72: transport, freight train | C72: =INDEX('Selected processes'!$E$5:$E$97, MATCH('Carbon footprint calculator'!$A72,'Selected processes'!$D$5:$D$97,0)) -> market group for transport, freight train | D72: =INDEX('Selected processes'!$F$5:$F$97, MATCH('Carbon footprint calculator'!$A72,'Selected processes'!$D$5:$D$97,0)) -> RER | E72: 556.5 | F72: =E72/$C$53 -> 0.0024733333 | G72: =INDEX('Selected processes'!$H$5:$H$97, MATCH('Carbon footprint calculator'!$A72,'Selected processes'!$D$5:$D$97,0)) -> metric ton*km | H72: =INDEX('Selected processes'!$J$5:$J$97, MATCH('Carbon footprint calculator'!$A72,'Selected processes'!$D$5:$D$97,0)) -> 0.045728106 | I72: =H72*$F72 -> 0.00011310085 | J72: =I72/I$87 -> 0.00075776007 | K72: =INDEX('Selected processes'!$K$5:$K$97, MATCH('Carbon footprint calculator'!$A72,'Selected processes'!$D$5:$D$97,0)) -> 0.068157807 | L72: =K72*$F72 -> 0.00016857698 | M72: =L72/L$87 -> 0.00066500934 | N72: =INDEX('Selected processes'!$L$5:$L$97, MATCH('Carbon footprint calculator'!$A72,'Selected processes'!$D$5:$D$97,0)) -> 2.5241034e-10 | O72: =N72*$F72 -> 6.2429491e-13 | P72: =O72/O$87 -> 0.00082804839 | Q72: =INDEX('Selected processes'!$N$5:$N$97, MATCH('Carbon footprint calculator'!$A72,'Selected processes'!$D$5:$D$97,0)) -> 0.71319593 | R72: =Q72*$F72 -> 0.0017639713 | S72: =R72/R$87 -> 0.00059028647 | T72: =I72/R72*$B$18 -> 64.117172
A73: 18241 | B73: transport, freight, lorry 16-32 metric ton | C73: =INDEX('Selected processes'!$E$5:$E$97, MATCH('Carbon footprint calculator'!$A73,'Selected processes'!$D$5:$D$97,0)) -> market for transport, freight, lorry 16-32 metric ton, EURO4 | D73: =INDEX('Selected processes'!$F$5:$F$97, MATCH('Carbon footprint calculator'!$A73,'Selected processes'!$D$5:$D$97,0)) -> RoW | E73: 59.1 | F73: =E73/$C$53 -> 0.00026266667 | G73: =INDEX('Selected processes'!$H$5:$H$97, MATCH('Carbon footprint calculator'!$A73,'Selected processes'!$D$5:$D$97,0)) -> metric ton*km | H73: =INDEX('Selected processes'!$J$5:$J$97, MATCH('Carbon footprint calculator'!$A73,'Selected processes'!$D$5:$D$97,0)) -> 0.19079134 | I73: =H73*$F73 -> 5.0114526e-05 | J73: =I73/I$87 -> 0.00033576041 | K73: =INDEX('Selected processes'!$K$5:$K$97, MATCH('Carbon footprint calculator'!$A73,'Selected processes'!$D$5:$D$97,0)) -> 0.20108682 | L73: =K73*$F73 -> 5.2818804e-05 | M73: =L73/L$87 -> 0.00020836177 | N73: =INDEX('Selected processes'!$L$5:$L$97, MATCH('Carbon footprint calculator'!$A73,'Selected processes'!$D$5:$D$97,0)) -> 8.7787947e-10 | O73: =N73*$F73 -> 2.3058967e-13 | P73: =O73/O$87 -> 0.0003058481 | Q73: =INDEX('Selected processes'!$N$5:$N$97, MATCH('Carbon footprint calculator'!$A73,'Selected processes'!$D$5:$D$97,0)) -> 2.8903577 | R73: =Q73*$F73 -> 0.00075920062 | S73: =R73/R$87 -> 0.00025405508 | T73: =I73/R73*$B$18 -> 66.009596
A74: 18438 | B74: transport, freight, sea, container ship | C74: =INDEX('Selected processes'!$E$5:$E$97, MATCH('Carbon footprint calculator'!$A74,'Selected processes'!$D$5:$D$97,0)) -> transport, freight, sea, container ship | D74: =INDEX('Selected processes'!$F$5:$F$97, MATCH('Carbon footprint calculator'!$A74,'Selected processes'!$D$5:$D$97,0)) -> GLO | E74: 9534 | F74: =E74/$C$53 -> 0.042373333 | G74: =INDEX('Selected processes'!$H$5:$H$97, MATCH('Carbon footprint calculator'!$A74,'Selected processes'!$D$5:$D$97,0)) -> metric ton*km | H74: =INDEX('Selected processes'!$J$5:$J$97, MATCH('Carbon footprint calculator'!$A74,'Selected processes'!$D$5:$D$97,0)) -> 0.010163513 | I74: =H74*$F74 -> 0.00043066193 | J74: =I74/I$87 -> 0.0028853754 | K74: =INDEX('Selected processes'!$K$5:$K$97, MATCH('Carbon footprint calculator'!$A74,'Selected processes'!$D$5:$D$97,0)) -> 0.026445888 | L74: =K74*$F74 -> 0.0011206004 | M74: =L74/L$87 -> 0.0044205903 | N74: =INDEX('Selected processes'!$L$5:$L$97, MATCH('Carbon footprint calculator'!$A74,'Selected processes'!$D$5:$D$97,0)) -> 9.6094188e-11 | O74: =N74*$F74 -> 4.071831e-12 | P74: =O74/O$87 -> 0.0054007699 | Q74: =INDEX('Selected processes'!$N$5:$N$97, MATCH('Carbon footprint calculator'!$A74,'Selected processes'!$D$5:$D$97,0)) -> 0.13313526 | R74: =Q74*$F74 -> 0.0056413845 | S74: =R74/R$87 -> 0.0018878046 | T74: =I74/R74*$B$18 -> 76.339757
C75: Use phase | E75: per V-km | F75: per V-km
A76: 100002 | B76: Health benefit from driving phys. Activivity | C76: =INDEX('Selected processes'!$E$5:$E$97, MATCH('Carbon footprint calculator'!$A76,'Selected processes'!$D$5:$D$97,0)) -> Driving a car | D76: =INDEX('Selected processes'!$F$5:$F$97, MATCH('Carbon footprint calculator'!$A76,'Selected processes'!$D$5:$D$97,0)) -> driving an automobile | E76: 1 | F76: 1 | G76: =INDEX('Selected processes'!$H$5:$H$97, MATCH('Carbon footprint calculator'!$A76,'Selected processes'!$D$5:$D$97,0)) -> km | H76: =INDEX('Selected processes'!$J$5:$J$97, MATCH('Carbon footprint calculator'!$A76,'Selected processes'!$D$5:$D$97,0)) -> 0 | I76: =H76*$F76 -> 0 | J76: =I76/I$49 -> 0 | K76: =INDEX('Selected processes'!$K$5:$K$97, MATCH('Carbon footprint calculator'!$A76,'Selected processes'!$D$5:$D$97,0)) -> -0.72627994 | L76: =K76*$F76 -> -0.72627994 | M76: =L76/L$49 -> 2.5263192 | N76: =INDEX('Selected processes'!$L$5:$L$97, MATCH('Carbon footprint calculator'!$A76,'Selected processes'!$D$5:$D$97,0)) -> 0 | O76: =N76*$F76 -> 0 | P76: =O76/O$49 -> 0 | Q76: =INDEX('Selected processes'!$N$5:$N$97, MATCH('Carbon footprint calculator'!$A76,'Selected processes'!$D$5:$D$97,0)) -> 0 | R76: =Q76*$F76 -> 0 | S76: =R76/R$49 -> 0 | T76: =I76/R76*$B$18 -> #DIV/0!
A77: 7235 | B77: Electricity Europe average --> change to DK market for electricity low voltage | C77: =INDEX('Selected processes'!$E$5:$E$97, MATCH('Carbon footprint calculator'!$A77,'Selected processes'!$D$5:$D$97,0)) -> market group for electricity, medium voltage | D77: =INDEX('Selected processes'!$F$5:$F$97, MATCH('Carbon footprint calculator'!$A77,'Selected processes'!$D$5:$D$97,0)) -> UCTE | E77: 0.26 | F77: =E77 -> 0.26 | G77: =INDEX('Selected processes'!$H$5:$H$97, MATCH('Carbon footprint calculator'!$A77,'Selected processes'!$D$5:$D$97,0)) -> kWh | H77: =INDEX('Selected processes'!$J$5:$J$97, MATCH('Carbon footprint calculator'!$A77,'Selected processes'!$D$5:$D$97,0)) -> 0.38493508 | I77: =H77*$F77 -> 0.10008312 | J77: =I77/I$87 -> 0.67054309 | K77: =INDEX('Selected processes'!$K$5:$K$97, MATCH('Carbon footprint calculator'!$A77,'Selected processes'!$D$5:$D$97,0)) -> 0.48931866 | L77: =K77*$F77 -> 0.12722285 | M77: =L77/L$87 -> 0.5018739 | N77: =INDEX('Selected processes'!$L$5:$L$97, MATCH('Carbon footprint calculator'!$A77,'Selected processes'!$D$5:$D$97,0)) -> 1.8304805e-09 | O77: =N77*$F77 -> 4.7592494e-10 | P77: =O77/O$87 -> 0.63125436 | Q77: =INDEX('Selected processes'!$N$5:$N$97, MATCH('Carbon footprint calculator'!$A77,'Selected processes'!$D$5:$D$97,0)) -> 8.8834816 | R77: =Q77*$F77 -> 2.3097052 | S77: =R77/R$87 -> 0.77290814 | T77: =I77/R77*$B$18 -> 43.331556
A78: 4527 | B78: Electricity Wind on shore | C78: =INDEX('Selected processes'!$E$5:$E$97, MATCH('Carbon footprint calculator'!$A78,'Selected processes'!$D$5:$D$97,0)) -> electricity production, wind, 1-3MW turbine, onshore | D78: =INDEX('Selected processes'!$F$5:$F$97, MATCH('Carbon footprint calculator'!$A78,'Selected processes'!$D$5:$D$97,0)) -> RoW | E78: 0.26 | F78: =E78 -> 0.26 | G78: =INDEX('Selected processes'!$H$5:$H$97, MATCH('Carbon footprint calculator'!$A78,'Selected processes'!$D$5:$D$97,0)) -> kWh | H78: =INDEX('Selected processes'!$J$5:$J$97, MATCH('Carbon footprint calculator'!$A78,'Selected processes'!$D$5:$D$97,0)) -> 0.014747928 | I78: =H78*$F78 -> 0.0038344612 | J78: ='Carbon footprint calculator'!$I78/I88 -> 0.072337203 | K78: =INDEX('Selected processes'!$K$5:$K$97, MATCH('Carbon footprint calculator'!$A78,'Selected processes'!$D$5:$D$97,0)) -> 0.040992466 | L78: =K78*$F78 -> 0.010658041 | M78: ='Carbon footprint calculator'!$L78/L88 -> 0.077835214 | N78: =INDEX('Selected processes'!$L$5:$L$97, MATCH('Carbon footprint calculator'!$A78,'Selected processes'!$D$5:$D$97,0)) -> 8.2698819e-11 | O78: =N78*$F78 -> 2.1501693e-11 | P78: =O78/O$87 -> 0.028519282 | Q78: =INDEX('Selected processes'!$N$5:$N$97, MATCH('Carbon footprint calculator'!$A78,'Selected processes'!$D$5:$D$97,0)) -> 0.20009985 | R78: =Q78*$F78 -> 0.052025962 | S78: =R78/R$87 -> 0.017409706 | T78: =I78/R78*$B$18 -> 73.702841
A79: 6295 | B79: Electricity photovoltaic | C79: =INDEX('Selected processes'!$E$5:$E$97, MATCH('Carbon footprint calculator'!$A79,'Selected processes'!$D$5:$D$97,0)) -> electricity production, photovoltaic, 570kWp open ground installation, multi-Si | D79: =INDEX('Selected processes'!$F$5:$F$97, MATCH('Carbon footprint calculator'!$A79,'Selected processes'!$D$5:$D$97,0)) -> RoW | E79: 0.26 | F79: =E79 -> 0.26 | G79: =INDEX('Selected processes'!$H$5:$H$97, MATCH('Carbon footprint calculator'!$A79,'Selected processes'!$D$5:$D$97,0)) -> kWh | H79: =INDEX('Selected processes'!$J$5:$J$97, MATCH('Carbon footprint calculator'!$A79,'Selected processes'!$D$5:$D$97,0)) -> 0.080250611 | I79: =H79*$F79 -> 0.020865159 | J79: ='Carbon footprint calculator'!$I79/I89 -> 0.29790837 | K79: =INDEX('Selected processes'!$K$5:$K$97, MATCH('Carbon footprint calculator'!$A79,'Selected processes'!$D$5:$D$97,0)) -> 0.14759408 | L79: =K79*$F79 -> 0.038374462 | M79: ='Carbon footprint calculator'!$L79/L89 -> 0.23307076 | N79: =INDEX('Selected processes'!$L$5:$L$97, MATCH('Carbon footprint calculator'!$A79,'Selected processes'!$D$5:$D$97,0)) -> 6.5404219e-10 | O79: =N79*$F79 -> 1.7005097e-10 | P79: =O79/O$87 -> 0.22555115 | Q79: =INDEX('Selected processes'!$N$5:$N$97, MATCH('Carbon footprint calculator'!$A79,'Selected processes'!$D$5:$D$97,0)) -> 1.0597105 | R79: =Q79*$F79 -> 0.27552472 | S79: =R79/R$87 -> 0.092200206 | T79: =I79/R79*$B$18 -> 75.728809
A80: 3591 | B80: Electricity coal | C80: =INDEX('Selected processes'!$E$5:$E$97, MATCH('Carbon footprint calculator'!$A80,'Selected processes'!$D$5:$D$97,0)) -> electricity production, hard coal | D80: =INDEX('Selected processes'!$F$5:$F$97, MATCH('Carbon footprint calculator'!$A80,'Selected processes'!$D$5:$D$97,0)) -> RoW | E80: 0.26 | F80: =E80 -> 0.26 | G80: =INDEX('Selected processes'!$H$5:$H$97, MATCH('Carbon footprint calculator'!$A80,'Selected processes'!$D$5:$D$97,0)) -> kWh | H80: =INDEX('Selected processes'!$J$5:$J$97, MATCH('Carbon footprint calculator'!$A80,'Selected processes'!$D$5:$D$97,0)) -> 1.0955326 | I80: =H80*$F80 -> 0.28483847 | J80: ='Carbon footprint calculator'!$I80/I90 -> 0.85277875 | K80: =INDEX('Selected processes'!$K$5:$K$97, MATCH('Carbon footprint calculator'!$A80,'Selected processes'!$D$5:$D$97,0)) -> 1.6507311 | L80: =K80*$F80 -> 0.42919009 | M80: ='Carbon footprint calculator'!$L80/L90 -> 0.77267104 | N80: =INDEX('Selected processes'!$L$5:$L$97, MATCH('Carbon footprint calculator'!$A80,'Selected processes'!$D$5:$D$97,0)) -> 5.7761989e-09 | O80: =N80*$F80 -> 1.5018117e-09 | P80: =O80/O$87 -> 1.9919637 | Q80: =INDEX('Selected processes'!$N$5:$N$97, MATCH('Carbon footprint calculator'!$A80,'Selected processes'!$D$5:$D$97,0)) -> 11.290351 | R80: =Q80*$F80 -> 2.9354912 | S80: =R80/R$87 -> 0.98231801 | T80: =I80/R80*$B$18 -> 97.032645
C81: Disposal | E81: per vehicle | F81: per V-km
A82: 19923 | B82: plastic mixture incineration | C82: =INDEX('Selected processes'!$E$5:$E$97, MATCH('Carbon footprint calculator'!$A82,'Selected processes'!$D$5:$D$97,0)) -> treatment of waste plastic, mixture, municipal incineration | D82: =INDEX('Selected processes'!$F$5:$F$97, MATCH('Carbon footprint calculator'!$A82,'Selected processes'!$D$5:$D$97,0)) -> CH | E82: =E60+E61+E62 -> 388.2 | F82: =E82/$C$53 -> 0.0017253333 | G82: =INDEX('Selected processes'!$H$5:$H$97, MATCH('Carbon footprint calculator'!$A82,'Selected processes'!$D$5:$D$97,0)) -> kg | H82: =INDEX('Selected processes'!$J$5:$J$97, MATCH('Carbon footprint calculator'!$A82,'Selected processes'!$D$5:$D$97,0)) -> 2.3457342 | I82: =H82*$F82 -> 0.0040471734 | J82: =I82/I$87 -> 0.027115503 | K82: =INDEX('Selected processes'!$K$5:$K$97, MATCH('Carbon footprint calculator'!$A82,'Selected processes'!$D$5:$D$97,0)) -> 1.3115341 | L82: =K82*$F82 -> 0.0022628336 | M82: =L82/L$87 -> 0.0089265183 | N82: =INDEX('Selected processes'!$L$5:$L$97, MATCH('Carbon footprint calculator'!$A82,'Selected processes'!$D$5:$D$97,0)) -> 6.7933555e-09 | O82: =N82*$F82 -> 1.1720803e-11 | P82: =O82/O$87 -> 0.015546165 | Q82: =INDEX('Selected processes'!$N$5:$N$97, MATCH('Carbon footprint calculator'!$A82,'Selected processes'!$D$5:$D$97,0)) -> 0.48721305 | R82: =Q82*$F82 -> 0.00084060492 | S82: =R82/R$87 -> 0.0002812958 | T82: =I82/R82*$B$18 -> 4814.5964
A83: 19515 | B83: Glass to landfill | C83: =INDEX('Selected processes'!$E$5:$E$97, MATCH('Carbon footprint calculator'!$A83,'Selected processes'!$D$5:$D$97,0)) -> treatment of waste glass, inert material landfill | D83: =INDEX('Selected processes'!$F$5:$F$97, MATCH('Carbon footprint calculator'!$A83,'Selected processes'!$D$5:$D$97,0)) -> CH | E83: =E63 -> 49 | F83: =E83/$C$53 -> 0.00021777778 | G83: =INDEX('Selected processes'!$H$5:$H$97, MATCH('Carbon footprint calculator'!$A83,'Selected processes'!$D$5:$D$97,0)) -> kg | H83: =INDEX('Selected processes'!$J$5:$J$97, MATCH('Carbon footprint calculator'!$A83,'Selected processes'!$D$5:$D$97,0)) -> 0.0056607781 | I83: =H83*$F83 -> 1.2327917e-06 | J83: =I83/I$87 -> 8.259534e-06 | K83: =INDEX('Selected processes'!$K$5:$K$97, MATCH('Carbon footprint calculator'!$A83,'Selected processes'!$D$5:$D$97,0)) -> 0.0067425637 | L83: =K83*$F83 -> 1.4683805e-06 | M83: =L83/L$87 -> 5.7925275e-06 | N83: =INDEX('Selected processes'!$L$5:$L$97, MATCH('Carbon footprint calculator'!$A83,'Selected processes'!$D$5:$D$97,0)) -> 3.4762451e-11 | O83: =N83*$F83 -> 7.5704894e-15 | P83: =O83/O$87 -> 1.0041299e-05 | Q83: =INDEX('Selected processes'!$N$5:$N$97, MATCH('Carbon footprint calculator'!$A83,'Selected processes'!$D$5:$D$97,0)) -> 0.15415625 | R83: =Q83*$F83 -> 3.3571805e-05 | S83: =R83/R$87 -> 1.12343e-05 | T83: =I83/R83*$B$18 -> 36.721043
A84: 7235 | B84: Avoided electricity plastic incineration | C84: =INDEX('Selected processes'!$E$5:$E$97, MATCH('Carbon footprint calculator'!$A84,'Selected processes'!$D$5:$D$97,0)) -> market group for electricity, medium voltage | D84: =INDEX('Selected processes'!$F$5:$F$97, MATCH('Carbon footprint calculator'!$A84,'Selected processes'!$D$5:$D$97,0)) -> UCTE | E84: =E82 -> 388.2 | F84: =-E84/$C$53*$E$17*$E$18/$E$19 -> -0.0050921296 | G84: =INDEX('Selected processes'!$H$5:$H$97, MATCH('Carbon footprint calculator'!$A84,'Selected processes'!$D$5:$D$97,0)) -> kWh | H84: =INDEX('Selected processes'!$J$5:$J$97, MATCH('Carbon footprint calculator'!$A84,'Selected processes'!$D$5:$D$97,0)) -> 0.38493508 | I84: =H84*$F84 -> -0.0019601393 | J84: =I84/I$87 -> -0.013132663 | K84: =INDEX('Selected processes'!$K$5:$K$97, MATCH('Carbon footprint calculator'!$A84,'Selected processes'!$D$5:$D$97,0)) -> 0.48931866 | L84: =K84*$F84 -> -0.0024916741 | M84: =L84/L$87 -> -0.0098292576 | N84: =INDEX('Selected processes'!$L$5:$L$97, MATCH('Carbon footprint calculator'!$A84,'Selected processes'!$D$5:$D$97,0)) -> 1.8304805e-09 | O84: =N84*$F84 -> -9.3210441e-12 | P84: =O84/O$87 -> -0.012363189 | Q84: =INDEX('Selected processes'!$N$5:$N$97, MATCH('Carbon footprint calculator'!$A84,'Selected processes'!$D$5:$D$97,0)) -> 8.8834816 | R84: =Q84*$F84 -> -0.04523584 | S84: =R84/R$87 -> -0.015137494 | T84: =I84/R84*$B$18 -> 43.331556
C86: Total
C87: Total electricity mix grid | G87: - | I87: =SUM(I$56:I$70)+SUM(I$72:I$74)+SUM(I$82:I$84)+I77 -> 0.14925681 | J87: =I87/I$87 -> 1 | L87: =SUM(L$56:L$70)+SUM(L$72:L$74)+SUM(L$82:L$84)+L77 -> 0.25349565 | M87: =L87/L$87 -> 1 | O87: =SUM(O$56:O$70)+SUM(O$72:O$74)+SUM(O$82:O$84)+O77 -> 7.5393529e-10 | P87: =O87/O$87 -> 1 | R87: =SUM(R$56:R$70)+SUM(R$72:R$74)+SUM(R$82:R$84)+R77 -> 2.9883308 | S87: =R87/R$87 -> 1 | T87: =I87/R87*$B$18 -> 49.946547
C88: Total EU electricity wind | G88: - | I88: =SUM(I$56:I$70)+SUM(I$72:I$74)+SUM(I$82:I$84)+I78 -> 0.053008148 | J88: =I88/I$87 -> 0.35514728 | L88: =SUM(L$56:L$70)+SUM(L$72:L$74)+SUM(L$82:L$84)+L78 -> 0.13693084 | M88: =L88/L$87 -> 0.54017037 | O88: =SUM(O$56:O$70)+SUM(O$72:O$74)+SUM(O$82:O$84)+O78 -> 2.9951205e-10 | P88: =O88/O$87 -> 0.39726492 | R88: =SUM(R$56:R$70)+SUM(R$72:R$74)+SUM(R$82:R$84)+R78 -> 0.73065158 | S88: =R88/R$87 -> 0.24450157 | T88: =I88/R88*$B$18 -> 72.549146
C89: Total EU electricity photovoltaic | G89: - | I89: =SUM(I$56:I$70)+SUM(I$72:I$74)+SUM(I$82:I$84)+I79 -> 0.070038846 | J89: =I89/I$87 -> 0.4692506 | L89: =SUM(L$56:L$70)+SUM(L$72:L$74)+SUM(L$82:L$84)+L79 -> 0.16464726 | M89: =L89/L$87 -> 0.64950724 | O89: =SUM(O$56:O$70)+SUM(O$72:O$74)+SUM(O$82:O$84)+O79 -> 4.4806132e-10 | P89: =O89/O$87 -> 0.59429679 | R89: =SUM(R$56:R$70)+SUM(R$72:R$74)+SUM(R$82:R$84)+R79 -> 0.95415034 | S89: =R89/R$87 -> 0.31929207 | T89: =I89/R89*$B$18 -> 73.404414
C90: Total EU electricity hard coal | G90: - | I90: =SUM(I$56:I$70)+SUM(I$72:I$74)+SUM(I$82:I$84)+I80 -> 0.33401216 | J90: =I90/I$87 -> 2.2378354 | L90: =SUM(L$56:L$70)+SUM(L$72:L$74)+SUM(L$82:L$84)+L80 -> 0.55546289 | M90: =L90/L$87 -> 2.1912127 | O90: =SUM(O$56:O$70)+SUM(O$72:O$74)+SUM(O$82:O$84)+O80 -> 1.7798221e-09 | P90: =O90/O$87 -> 2.3607093 | R90: =SUM(R$56:R$70)+SUM(R$72:R$74)+SUM(R$82:R$84)+R80 -> 3.6141168 | S90: =R90/R$87 -> 1.2094099 | T90: =I90/R90*$B$18 -> 92.418751
B93: Biking electric bike | BF93: GHG CO2equ. kgCO2equ/FU | BG93: Graph per FU
B94: Battery lifespan | C94: 15000
B95: Vehicle lifespan (km/vehicle) | C95: 30000 | D95: e-bike weight with battery [kg] | F95: =15+E99 -> 19
A96: Process # | B96: Transportation by e-bike FU= 1 vehicle km Life Cycle stage (30,000 km lifespan) | C96: Ecoinvent process | D96: Region | E96: Quantity per unit | F96: Quantity per FU | G96: Unit | H96: Carbon footprint [kgCO2equ/unit] | I96: Carbon footprint [CO2equ./FU] | J96: fraction carbon footprint | K96: Human health/Unit [min. lost/unit] | L96: Human health [min. lost/FU] | M96: fraction human health | N96: Ecosystem quality impacts/Unit [species-yr/unit] | O96: Ecosystem quality impacts [Species-yr/FU] | P96: fraction ecosystem quality | Q96: Non renewable primary energy resources/unit [MJ/unit] | R96: Non renewable primary energy resources impacts [MJ/FU] | S96: fraction non renewable primary energy | T96: Check [gCO2e/MJ] | BF96: Distance over Lifetime | BG96: Incandescent bulb lighting DK electricity | BH96: Fluorescent bulb lighting- DK electricity mix | BI96: Fluorescent bulb lighting - Wind | BJ96: Fluorescent bulb lighting - Photovoltaic | BK96: Fluorescent bulb lighting - hard coal
B97: Manufacturing (Materials + Processing) | C97: Manufacturing (Materials + Processing) | E97: per vehicle over lifespan | F97: per V-km | BF97: 0.01 | BG97: =AY97/$BF97 -> 0 | BH97: =BA97/$BF97 -> 0 | BI97: =BB97/$BF97 -> 0 | BJ97: =BC97/$BF97 -> 0 | BK97: =BD97/$BF97 -> 0
A98: 1066 | B98: Bike production | C98: =INDEX('Selected processes'!$E$5:$E$97, MATCH('Carbon footprint calculator'!$A98,'Selected processes'!$D$5:$D$97,0)) -> bicycle production | D98: =INDEX('Selected processes'!$F$5:$F$97, MATCH('Carbon footprint calculator'!$A98,'Selected processes'!$D$5:$D$97,0)) -> RER | E98: 1 | F98: =E98/C95 -> 3.3333333e-05 | G98: =INDEX('Selected processes'!$H$5:$H$97, MATCH('Carbon footprint calculator'!$A98,'Selected processes'!$D$5:$D$97,0)) -> unit | H98: =INDEX('Selected processes'!$J$5:$J$97, MATCH('Carbon footprint calculator'!$A98,'Selected processes'!$D$5:$D$97,0)) -> 145.40026 | I98: =H98*$F98 -> 0.0048466754 | J98: =I98/I$111 -> 0.61153315 | K98: =INDEX('Selected processes'!$K$5:$K$97, MATCH('Carbon footprint calculator'!$A98,'Selected processes'!$D$5:$D$97,0)) -> 343.6029 | L98: =K98*$F98 -> 0.01145343 | M98: =L98/L$111 -> -0.0018466656 | N98: =INDEX('Selected processes'!$L$5:$L$97, MATCH('Carbon footprint calculator'!$A98,'Selected processes'!$D$5:$D$97,0)) -> 6.755806e-07 | O98: =N98*$F98 -> 2.2519353e-11 | P98: =O98/O$111 -> 0.60406413 | Q98: =INDEX('Selected processes'!$N$5:$N$97, MATCH('Carbon footprint calculator'!$A98,'Selected processes'!$D$5:$D$97,0)) -> 1702.2837 | R98: =Q98*$F98 -> 0.056742791 | S98: =R98/R$111 -> 0.45965041 | T98: =I98/R98*$B$18 -> 85.414821 | BF98: =AX98 -> 0 | BG98: =AY98/$BF98 -> #DIV/0! | BH98: =BA98/$BF98 -> #DIV/0! | BI98: =BB98/$BF98 -> #DIV/0! | BJ98: =BC98/$BF98 -> #DIV/0! | BK98: =BD98/$BF98 -> #DIV/0!
A99: 992 | B99: E-bike battery | C99: =INDEX('Selected processes'!$E$5:$E$97, MATCH('Carbon footprint calculator'!$A99,'Selected processes'!$D$5:$D$97,0)) -> battery production, Li-ion, LiMn2O4, rechargeable, prismatic | D99: =INDEX('Selected processes'!$F$5:$F$97, MATCH('Carbon footprint calculator'!$A99,'Selected processes'!$D$5:$D$97,0)) -> GLO | E99: 4 | G99: =INDEX('Selected processes'!$H$5:$H$97, MATCH('Carbon footprint calculator'!$A99,'Selected processes'!$D$5:$D$97,0)) -> kg | H99: =INDEX('Selected processes'!$J$5:$J$97, MATCH('Carbon footprint calculator'!$A99,'Selected processes'!$D$5:$D$97,0)) -> 8.4296788 | I99: =H99*$F99 -> 0 | J99: =I99/I$111 -> 0 | K99: =INDEX('Selected processes'!$K$5:$K$97, MATCH('Carbon footprint calculator'!$A99,'Selected processes'!$D$5:$D$97,0)) -> 17.887181 | L99: =K99*$F99 -> 0 | M99: =L99/L$111 -> 0 | N99: =INDEX('Selected processes'!$L$5:$L$97, MATCH('Carbon footprint calculator'!$A99,'Selected processes'!$D$5:$D$97,0)) -> 4.8297512e-08 | O99: =N99*$F99 -> 0 | P99: =O99/O$111 -> 0 | Q99: =INDEX('Selected processes'!$N$5:$N$97, MATCH('Carbon footprint calculator'!$A99,'Selected processes'!$D$5:$D$97,0)) -> 126.17824 | R99: =Q99*$F99 -> 0 | S99: =R99/R$111 -> 0 | T99: =I99/R99*$B$18 -> #DIV/0! | BF99: =AX99 -> 0 | BG99: =AY99/$BF99 -> #DIV/0! | BH99: =BA99/$BF99 -> #DIV/0! | BI99: =BB99/$BF99 -> #DIV/0! | BJ99: =BC99/$BF99 -> #DIV/0! | BK99: =BD99/$BF99 -> #DIV/0!
B100: Transportation | C100: Transportation | E100: km transport per vehicle | F100: per V-km | BF100: =AX100 -> 0 | BG100: =AY100/$BF100 -> #DIV/0! | BH100: =BA100/$BF100 -> #DIV/0! | BI100: =BB100/$BF100 -> #DIV/0! | BJ100: =BC100/$BF100 -> #DIV/0! | BK100: =BD100/$BF100 -> #DIV/0!
A101: 18124 | B101: transport, freight train | C101: =INDEX('Selected processes'!$E$5:$E$97, MATCH('Carbon footprint calculator'!$A101,'Selected processes'!$D$5:$D$97,0)) -> market group for transport, freight train | D101: =INDEX('Selected processes'!$F$5:$F$97, MATCH('Carbon footprint calculator'!$A101,'Selected processes'!$D$5:$D$97,0)) -> RER | E101: 0 | G101: =INDEX('Selected processes'!$H$5:$H$97, MATCH('Carbon footprint calculator'!$A101,'Selected processes'!$D$5:$D$97,0)) -> metric ton*km | H101: =INDEX('Selected processes'!$J$5:$J$97, MATCH('Carbon footprint calculator'!$A101,'Selected processes'!$D$5:$D$97,0)) -> 0.045728106 | I101: =H101*$F101 -> 0 | J101: =I101/I$111 -> 0 | K101: =INDEX('Selected processes'!$K$5:$K$97, MATCH('Carbon footprint calculator'!$A101,'Selected processes'!$D$5:$D$97,0)) -> 0.068157807 | L101: =K101*$F101 -> 0 | M101: =L101/L$111 -> 0 | N101: =INDEX('Selected processes'!$L$5:$L$97, MATCH('Carbon footprint calculator'!$A101,'Selected processes'!$D$5:$D$97,0)) -> 2.5241034e-10 | O101: =N101*$F101 -> 0 | P101: =O101/O$111 -> 0 | Q101: =INDEX('Selected processes'!$N$5:$N$97, MATCH('Carbon footprint calculator'!$A101,'Selected processes'!$D$5:$D$97,0)) -> 0.71319593 | R101: =Q101*$F101 -> 0 | S101: =R101/R$111 -> 0 | T101: =I101/R101*$B$18 -> #DIV/0! | BF101: =AX101 -> 0 | BG101: =AY101/$BF101 -> #DIV/0! | BH101: =BA101/$BF101 -> #DIV/0! | BI101: =BB101/$BF101 -> #DIV/0! | BJ101: =BC101/$BF101 -> #DIV/0! | BK101: =BD101/$BF101 -> #DIV/0!
A102: 18241 | B102: transport, freight, lorry 16-32 metric ton | C102: =INDEX('Selected processes'!$E$5:$E$97, MATCH('Carbon footprint calculator'!$A102,'Selected processes'!$D$5:$D$97,0)) -> market for transport, freight, lorry 16-32 metric ton, EURO4 | D102: =INDEX('Selected processes'!$F$5:$F$97, MATCH('Carbon footprint calculator'!$A102,'Selected processes'!$D$5:$D$97,0)) -> RoW | E102: 2000 | F102: =E102*F95/$B$17/C$95 -> 0.0012666667 | G102: =INDEX('Selected processes'!$H$5:$H$97, MATCH('Carbon footprint calculator'!$A102,'Selected processes'!$D$5:$D$97,0)) -> metric ton*km | H102: =INDEX('Selected processes'!$J$5:$J$97, MATCH('Carbon footprint calculator'!$A102,'Selected processes'!$D$5:$D$97,0)) -> 0.19079134 | I102: =H102*$F102 -> 0.00024166904 | J102: =I102/I$111 -> 0.030492784 | K102: =INDEX('Selected processes'!$K$5:$K$97, MATCH('Carbon footprint calculator'!$A102,'Selected processes'!$D$5:$D$97,0)) -> 0.20108682 | L102: =K102*$F102 -> 0.00025470997 | M102: =L102/L$111 -> -4.1067535e-05 | N102: =INDEX('Selected processes'!$L$5:$L$97, MATCH('Carbon footprint calculator'!$A102,'Selected processes'!$D$5:$D$97,0)) -> 8.7787947e-10 | O102: =N102*$F102 -> 1.1119807e-12 | P102: =O102/O$111 -> 0.029828016 | Q102: =INDEX('Selected processes'!$N$5:$N$97, MATCH('Carbon footprint calculator'!$A102,'Selected processes'!$D$5:$D$97,0)) -> 2.8903577 | R102: =Q102*$F102 -> 0.0036611198 | S102: =R102/R$111 -> 0.029657251 | T102: =I102/R102*$B$18 -> 66.009596 | BF102: =AX102 -> 0 | BG102: =AY102/$BF102 -> #DIV/0! | BH102: =BA102/$BF102 -> #DIV/0! | BI102: =BB102/$BF102 -> #DIV/0! | BJ102: =BC102/$BF102 -> #DIV/0! | BK102: =BD102/$BF102 -> #DIV/0!
A103: 18438 | B103: transport, freight, sea, container ship (15 kg) | C103: =INDEX('Selected processes'!$E$5:$E$97, MATCH('Carbon footprint calculator'!$A103,'Selected processes'!$D$5:$D$97,0)) -> transport, freight, sea, container ship | D103: =INDEX('Selected processes'!$F$5:$F$97, MATCH('Carbon footprint calculator'!$A103,'Selected processes'!$D$5:$D$97,0)) -> GLO | E103: 10000 | F103: =E103*F95/$B$17/C$95 -> 0.0063333333 | G103: =INDEX('Selected processes'!$H$5:$H$97, MATCH('Carbon footprint calculator'!$A103,'Selected processes'!$D$5:$D$97,0)) -> metric ton*km | H103: =INDEX('Selected processes'!$J$5:$J$97, MATCH('Carbon footprint calculator'!$A103,'Selected processes'!$D$5:$D$97,0)) -> 0.010163513 | I103: =H103*$F103 -> 6.4368916e-05 | J103: =I103/I$111 -> 0.0081217995 | K103: =INDEX('Selected processes'!$K$5:$K$97, MATCH('Carbon footprint calculator'!$A103,'Selected processes'!$D$5:$D$97,0)) -> 0.026445888 | L103: =K103*$F103 -> 0.00016749062 | M103: =L103/L$111 -> -2.7004939e-05 | N103: =INDEX('Selected processes'!$L$5:$L$97, MATCH('Carbon footprint calculator'!$A103,'Selected processes'!$D$5:$D$97,0)) -> 9.6094188e-11 | O103: =N103*$F103 -> 6.0859652e-13 | P103: =O103/O$87 -> 0.00080722647 | Q103: =INDEX('Selected processes'!$N$5:$N$97, MATCH('Carbon footprint calculator'!$A103,'Selected processes'!$D$5:$D$97,0)) -> 0.13313526 | R103: =Q103*$F103 -> 0.00084318995 | S103: =R103/R$111 -> 0.0068303408 | T103: =I103/R103*$B$18 -> 76.339757 | BF103: =AX103 -> 0 | BG103: =AY103/$BF103 -> #DIV/0! | BH103: =BA103/$BF103 -> #DIV/0! | BI103: =BB103/$BF103 -> #DIV/0! | BJ103: =BC103/$BF103 -> #DIV/0! | BK103: =BD103/$BF103 -> #DIV/0!
C104: Use phase | E104: per V-km | F104: per V-km | BF104: =AX104 -> 0 | BG104: =AY104/$BF104 -> #DIV/0! | BH104: =BA104/$BF104 -> #DIV/0! | BI104: =BB104/$BF104 -> #DIV/0! | BJ104: =BC104/$BF104 -> #DIV/0! | BK104: =BD104/$BF104 -> #DIV/0!
A105: 100003 | B105: Exercising with e-bike | C105: =INDEX('Selected processes'!$E$5:$E$97, MATCH('Carbon footprint calculator'!$A105,'Selected processes'!$D$5:$D$97,0)) -> Biking gain in health, electric bike | D105: =INDEX('Selected processes'!$F$5:$F$97, MATCH('Carbon footprint calculator'!$A105,'Selected processes'!$D$5:$D$97,0)) -> e.biking | F105: 1 | G105: =INDEX('Selected processes'!$H$5:$H$97, MATCH('Carbon footprint calculator'!$A105,'Selected processes'!$D$5:$D$97,0)) -> km | H105: =INDEX('Selected processes'!$J$5:$J$97, MATCH('Carbon footprint calculator'!$A105,'Selected processes'!$D$5:$D$97,0)) -> 0 | I105: =H105*$F105 -> 0 | J105: =I105/I$111 -> 0 | K105: =INDEX('Selected processes'!$K$5:$K$97, MATCH('Carbon footprint calculator'!$A105,'Selected processes'!$D$5:$D$97,0)) -> -6.2175665 | L105: =K105*$F105 -> -6.2175665 | M105: =L105/L$111 -> 1.002474 | N105: =INDEX('Selected processes'!$L$5:$L$97, MATCH('Carbon footprint calculator'!$A105,'Selected processes'!$D$5:$D$97,0)) -> 0 | O105: =N105*$F105 -> 0 | P105: =O105/O$111 -> 0 | Q105: =INDEX('Selected processes'!$N$5:$N$97, MATCH('Carbon footprint calculator'!$A105,'Selected processes'!$D$5:$D$97,0)) -> 0 | R105: =Q105*$F105 -> 0 | S105: =R105/R$111 -> 0 | T105: =I105/R105*$B$18 -> #DIV/0! | BF105: =AX105 -> 0 | BG105: =AY105/$BF105 -> #DIV/0! | BH105: =BA105/$BF105 -> #DIV/0! | BI105: =BB105/$BF105 -> #DIV/0! | BJ105: =BC105/$BF105 -> #DIV/0! | BK105: =BD105/$BF105 -> #DIV/0!
A106: 7235 | B106: Electricity Europe average --> change to DK market for electricity low voltage | C106: =INDEX('Selected processes'!$E$5:$E$97, MATCH('Carbon footprint calculator'!$A106,'Selected processes'!$D$5:$D$97,0)) -> market group for electricity, medium voltage | D106: =INDEX('Selected processes'!$F$5:$F$97, MATCH('Carbon footprint calculator'!$A106,'Selected processes'!$D$5:$D$97,0)) -> UCTE | E106: 0.007 | F106: =E106 -> 0.007 | G106: =INDEX('Selected processes'!$H$5:$H$97, MATCH('Carbon footprint calculator'!$A106,'Selected processes'!$D$5:$D$97,0)) -> kWh | H106: =INDEX('Selected processes'!$J$5:$J$97, MATCH('Carbon footprint calculator'!$A106,'Selected processes'!$D$5:$D$97,0)) -> 0.38493508 | I106: =H106*$F106 -> 0.0026945455 | J106: =I106/I$111 -> 0.33998644 | K106: =INDEX('Selected processes'!$K$5:$K$97, MATCH('Carbon footprint calculator'!$A106,'Selected processes'!$D$5:$D$97,0)) -> 0.48931866 | L106: =K106*$F106 -> 0.0034252306 | M106: =L106/L$111 -> -0.00055225864 | N106: =INDEX('Selected processes'!$L$5:$L$97, MATCH('Carbon footprint calculator'!$A106,'Selected processes'!$D$5:$D$97,0)) -> 1.8304805e-09 | O106: =N106*$F106 -> 1.2813364e-11 | P106: =O106/O$111 -> 0.34370851 | Q106: =INDEX('Selected processes'!$N$5:$N$97, MATCH('Carbon footprint calculator'!$A106,'Selected processes'!$D$5:$D$97,0)) -> 8.8834816 | R106: =Q106*$F106 -> 0.062184371 | S106: =R106/R$111 -> 0.50373044 | T106: =I106/R106*$B$18 -> 43.331556 | BF106: =AX106 -> 0 | BG106: =AY106/$BF106 -> #DIV/0! | BH106: =BA106/$BF106 -> #DIV/0! | BI106: =BB106/$BF106 -> #DIV/0! | BJ106: =BC106/$BF106 -> #DIV/0! | BK106: =BD106/$BF106 -> #DIV/0!
C107: Disposal | E107: per vehicle | F107: per V-km | BF107: =AX107 -> 0 | BG107: =AY107/$BF107 -> #DIV/0! | BH107: =BA107/$BF107 -> #DIV/0! | BI107: =BB107/$BF107 -> #DIV/0! | BJ107: =BC107/$BF107 -> #DIV/0! | BK107: =BD107/$BF107 -> #DIV/0!
A108: 19923 | B108: plastic mixture incineration | C108: =INDEX('Selected processes'!$E$5:$E$97, MATCH('Carbon footprint calculator'!$A108,'Selected processes'!$D$5:$D$97,0)) -> treatment of waste plastic, mixture, municipal incineration | D108: =INDEX('Selected processes'!$F$5:$F$97, MATCH('Carbon footprint calculator'!$A108,'Selected processes'!$D$5:$D$97,0)) -> CH | F108: =F98+F99 -> 3.3333333e-05 | G108: =INDEX('Selected processes'!$H$5:$H$97, MATCH('Carbon footprint calculator'!$A108,'Selected processes'!$D$5:$D$97,0)) -> kg | H108: =INDEX('Selected processes'!$J$5:$J$97, MATCH('Carbon footprint calculator'!$A108,'Selected processes'!$D$5:$D$97,0)) -> 2.3457342 | I108: =H108*$F108 -> 7.8191141e-05 | J108: =I108/I$111 -> 0.0098658298 | K108: =INDEX('Selected processes'!$K$5:$K$97, MATCH('Carbon footprint calculator'!$A108,'Selected processes'!$D$5:$D$97,0)) -> 1.3115341 | L108: =K108*$F108 -> 4.3717805e-05 | M108: =L108/L$111 -> -7.0487327e-06 | N108: =INDEX('Selected processes'!$L$5:$L$97, MATCH('Carbon footprint calculator'!$A108,'Selected processes'!$D$5:$D$97,0)) -> 6.7933555e-09 | O108: =N108*$F108 -> 2.2644518e-13 | P108: =O108/O$111 -> 0.0060742158 | Q108: =INDEX('Selected processes'!$N$5:$N$97, MATCH('Carbon footprint calculator'!$A108,'Selected processes'!$D$5:$D$97,0)) -> 0.48721305 | R108: =Q108*$F108 -> 1.6240435e-05 | S108: =R108/R$111 -> 0.0001315572 | T108: =I108/R108*$B$18 -> 4814.5964 | BF108: =AX108 -> 0 | BG108: =AY108/$BF108 -> #DIV/0! | BH108: =BA108/$BF108 -> #DIV/0! | BI108: =BB108/$BF108 -> #DIV/0! | BJ108: =BC108/$BF108 -> #DIV/0! | BK108: =BD108/$BF108 -> #DIV/0!
BF109: =AX109 -> 0 | BG109: =AY109/$BF109 -> #DIV/0! | BH109: =BA109/$BF109 -> #DIV/0! | BI109: =BB109/$BF109 -> #DIV/0! | BJ109: =BC109/$BF109 -> #DIV/0! | BK109: =BD109/$BF109 -> #DIV/0!
C110: Total | BF110: =AX110 -> 0 | BG110: =AY110/$BF110 -> #DIV/0! | BH110: =BA110/$BF110 -> #DIV/0! | BI110: =BB110/$BF110 -> #DIV/0! | BJ110: =BC110/$BF110 -> #DIV/0! | BK110: =BD110/$BF110 -> #DIV/0!
C111: Total electricity mix grid | G111: - | I111: =SUM(I98:I108) -> 0.00792545 | J111: =I111/I$111 -> 1 | L111: =SUM(L98:L108) -> -6.2022219 | M111: =L111/L$111 -> 1 | O111: =SUM(O98:O108) -> 3.7279739e-11 | P111: =O111/O$111 -> 1 | R111: =SUM(R98:R108) -> 0.12344771 | S111: =R111/R$111 -> 1 | T111: =I111/R111*$B$18 -> 64.200866 | BF111: =AX111 -> 0 | BG111: =AY111/$BF111 -> #DIV/0! | BH111: =BA111/$BF111 -> #DIV/0! | BI111: =BB111/$BF111 -> #DIV/0! | BJ111: =BC111/$BF111 -> #DIV/0! | BK111: =BD111/$BF111 -> #DIV/0!
BF112: =AX112 -> 0 | BG112: =AY112/$BF112 -> #DIV/0! | BH112: =BA112/$BF112 -> #DIV/0! | BI112: =BB112/$BF112 -> #DIV/0! | BJ112: =BC112/$BF112 -> #DIV/0! | BK112: =BD112/$BF112 -> #DIV/0!
...

Sheet Life cycle costing
A3: Vehicle lifetime before resale | B3: 10
A4: Vehicle lifespan (km/vehicle) | B4: 150000 | F4: Costs | J4: Costs
A5: Transportation by Gas Vehicle FU= 1 vehicle km Life Cycle stage (150,000 km lifespan) | C5: Quantity original unit | D5: Quantity per FU | E5: Unit | F5: price/Unit [Euro/Unit] | G5: Cost per FU [Euro/V-km] | H5: fraction costs | J5: Euro/V-km | K5: Petrol Vehicle | L5: Electric Vehicle | M5: Electric Vehicle - Wind | N5: Electric Vehicle - Photovoltaic | O5: Electric Vehicle - hard coal
A6: Purchase | B6: Cost relevant distance | C6: per vehicle over lifespan | D6: per FU | J6: Purchase | K6: =SUM(G7:G8) -> 0.21333333 | L6: =SUM(G29:G30) -> 0.22222222 | M6: =$L6 -> 0.22222222 | N6: =$L6 -> 0.22222222 | O6: =$L6 -> 0.22222222
A7: 1 vehicle | B7: =$B$4 -> 150000 | C7: 1 | D7: =C7/B7 -> 6.6666667e-06 | E7: p | F7: 30000 | G7: =F7*D7 -> 0.2 | H7: =G7/G$20 -> 0.44349293 | J7: Fixed annual costs | K7: =SUM(G10:G11) -> 0.046666667 | L7: =SUM(G32:G33) -> 0.035555556 | M7: =$L7 -> 0.035555556 | N7: =$L7 -> 0.035555556 | O7: =$L7 -> 0.035555556
A8: Tax on vehicle at purchase | B8: =$B$4 -> 150000 | C8: 1 | D8: =C8/B8 -> 6.6666667e-06 | E8: p | F8: 2000 | G8: =F8*D8 -> 0.013333333 | H8: =G8/G$20 -> 0.029566195 | J8: Variable cost maintenance | K8: =SUM(G13:G14) -> 0.105 | L8: =SUM(G35:G36) -> 0.06 | M8: =$L8 -> 0.06 | N8: =$L8 -> 0.06 | O8: =$L8 -> 0.06
A9: Fixed annual costs | B9: km/yr | C9: per year | D9: per FU | J9: Variable cost Fuel - Use phase | K9: =G16 -> 0.10596548 | L9: =G38 -> 0.052
A10: Insurance per year | B10: =B4/B3 -> 15000 | C10: 1 | D10: =C10/B10 -> 6.6666667e-05 | E10: p | F10: 500 | G10: =F10*$D10 -> 0.033333333 | H10: =G10/G$20 -> 0.073915488 | J10: Resale | K10: =G18 -> -0.02 | L10: =G40 -> -0.013333333 | M10: =$L10 -> -0.013333333
A11: Taxes for immatriculation per year | B11: =B4/B3 -> 15000 | C11: 1 | D11: =C11/B11 -> 6.6666667e-05 | E11: p | F11: 200 | G11: =F11*$D11 -> 0.013333333 | H11: =G11/G$20 -> 0.029566195 | J11: Electric charging - wind | M11: =$L$8*M$17 -> 0.036
A12: Variabl cost maintenance | B12: km until change | D12: per FU | J12: Electric charging - photovoltaic | N12: =$L$8*N$17 -> 0.054
A13: maintenance per 10000km | B13: 10000 | C13: 1 | D13: =C13/B13 -> 0.0001 | E13: p | F13: 750 | G13: =F13*$D13 -> 0.075 | H13: =G13/G$20 -> 0.16630985 | J13: Electric charging - hard coal | O13: =$L$8*O$17 -> 0.078
A14: Tires change every 20000 km | B14: 20000 | C14: 4 | D14: =C14/B14 -> 0.0002 | E14: p | F14: 150 | G14: =F14*$D14 -> 0.03 | H14: =G14/G$20 -> 0.066523939 | J14: Total | K14: =SUM(K6:K10) -> 0.45096548 | L14: =SUM(L6:L10) -> 0.35644444 | M14: =SUM(M6:M10) -> 0.30444444 | N14: =SUM(N6:N10) -> 0.31777778 | O14: =SUM(O6:O10) -> 0.31777778
A15: Variable cost Fuel - Use phase | C15: per V-km | D15: per FU
A16: Supply chain petrol, low-sulfur | B16: 1 | C16: =0.0619047619047619*0.835 -> 0.051690476 | D16: =C16/B16 -> 0.051690476 | E16: L | F16: 2.05 | G16: =F16*$D16 -> 0.10596548 | H16: =G16/G$20 -> 0.2349747
A17: Resale value - end of life | C17: per vehicle over lifespan | D17: per FU | J17: relative price by soure | K17: GUESS so far | L17: 1 | M17: 0.6 | N17: 0.9 | O17: 1.3
A18: 1 vehicle | B18: =$B$4 -> 150000 | C18: -1 | D18: =C18/B18 -> -6.6666667e-06 | E18: p | F18: 3000 | G18: =F18*$D18 -> -0.02 | H18: =G18/G$20 -> -0.044349293
A19: Total | D19: per FU
A20: Total | B20: Euro/V-km | C20: - | E20: - | G20: =SUM(G7:G18) -> 0.45096548 | H20: =G20/G$20 -> 1
A21: Conversion rate | B21: Kr/Euro | C21: 7.44 | D21: Total DKK | G21: Kr/V-km | H21: =SUM(H7:H17) -> 1.0443493
A22: Total | B22: DKK/V-km | G22: =G20*$C$21 -> 3.3551831
A25: Vehicle lifetime before resale | B25: 10
A26: Vehicle lifespan (km/vehicle) | B26: 225000 | F26: Costs
A27: Transportation by Electric Vehicle FU= 1 vehicle km Life Cycle stage (225000 km lifespan) | C27: Quantity original unit | D27: Quantity per FU | E27: Unit | F27: price/Unit [Euro/Unit] | G27: Cost per FU [Euro/V-km] | H27: fraction costs
A28: Purchase | B28: Cost relevant distance | C28: per vehicle over lifespan | D28: per FU
A29: 1 vehicle | B29: =$B$26 -> 225000 | C29: 1 | D29: =C29/B29 -> 4.4444444e-06 | E29: p | F29: 50000 | G29: =F29*D29 -> 0.22222222 | H29: =G29/G$42 -> 0.6234414
A30: Tax on vehicle at purchase | B30: =$B$26 -> 225000 | C30: 1 | D30: =C30/B30 -> 4.4444444e-06 | E30: p | F30: 0 | G30: =F30*D30 -> 0 | H30: =G30/G$42 -> 0
A31: Fixed annual costs | C31: annual purchase | D31: per FU
A32: Insurance per year | B32: =$B$26/$B$25 -> 22500 | C32: 1 | D32: =C32/B32 -> 4.4444444e-05 | E32: p | F32: 700 | G32: =F32*$D32 -> 0.031111111 | H32: =G32/G$42 -> 0.087281796
A33: Taxes for immatriculation per year | B33: =$B$26/$B$25 -> 22500 | C33: 1 | D33: =C33/B33 -> 4.4444444e-05 | E33: p | F33: 100 | G33: =F33*$D33 -> 0.0044444444 | H33: =G33/G$42 -> 0.012468828
A34: Variable cost maintenance | D34: per FU
A35: maintenance per 10000km | B35: 10000 | C35: 1 | D35: =C35/B35 -> 0.0001 | E35: p | F35: 300 | G35: =F35*$D35 -> 0.03 | H35: =G35/G$42 -> 0.084164589
A36: Tires change every 20000 km | B36: 20000 | C36: 4 | D36: =C36/B36 -> 0.0002 | E36: p | F36: 150 | G36: =F36*$D36 -> 0.03 | H36: =G36/G$42 -> 0.084164589
A37: Variable cost Fuel - Use phase | C37: per V-km | D37: per FU
A38: Electricity consumption | B38: 1 | C38: 0.26 | D38: =C38/B38 -> 0.26 | E38: L | F38: 0.2 | G38: =F38*$D38 -> 0.052 | H38: =G38/G$42 -> 0.14588529
A39: Resale value - end of life | C39: per vehicle over lifespan | D39: per FU
A40: 1 vehicle | B40: =$B$26 -> 225000 | C40: -1 | D40: =C40/B40 -> -4.4444444e-06 | E40: p | F40: 3000 | G40: =F40*$D40 -> -0.013333333 | H40: =G40/G$42 -> -0.037406484
A41: Total | D41: per FU
A42: Total | C42: - | E42: - | G42: =SUM(G29:G40) -> 0.35644444 | H42: =G42/G$42 -> 1
G43: Kr/V-km | H43: =SUM(H29:H39) -> 1.0374065
G44: =G42*$C$21 -> 2.6519467
A47: If leasing
D86: year | E86: yearly distance
A111: Transportation by Electric Vehicle FU= 1 vehicle km Life Cycle stage (225,000 km lifespan) | C111: Quantity original unit | D111: Quantity per FU | E111: Unit | F111: Energy/Unit [MJ/Unit] | G111: Energy per FU [MJ/FU] | H111: fraction energy
A112: Manufacturing (Materials + Processing) | C112: per vehicle over lifespan
A113: steel, low-alloyed, hot rolled | C113: 953.4 | D113: =C113/$C$26 -> #DIV/0! | E113: kg | F113: 25.220541 | G113: =F113*$D113 -> #DIV/0! | H113: =G113/G$144 -> #DIV/0!
A114: Metal working, average for steel product manufacturing | C114: 953.4 | D114: =C114/$C$26 -> #DIV/0! | E114: kg | F114: 25.190272 | G114: =F114*$D114 -> #DIV/0! | H114: =G114/G$144 -> #DIV/0!
A115: aluminium, primary, ingot | C115: 76.5 | D115: =C115/$C$26 -> #DIV/0! | E115: kg | F115: 218.89578 | G115: =F115*$D115 -> #DIV/0! | H115: =G115/G$144 -> #DIV/0!
A116: Copper | C116: 287.1 | D116: =C116/$C$26 -> #DIV/0! | E116: kg | F116: 74.579203 | G116: =F116*$D116 -> #DIV/0! | H116: =G116/G$144 -> #DIV/0!
A117: Extruded thermoformed plastic sheets | C117: 162.9 | D117: =C117/$C$26 -> #DIV/0! | E117: kg | F117: 14.297489 | G117: =F117*$D117 -> #DIV/0! | H117: =G117/G$144 -> #DIV/0!
A118: Polypropylene & polyurethane | C118: 172 | D118: =C118/$C$26 -> #DIV/0! | E118: kg | F118: 77.070943 | G118: =F118*$D118 -> #DIV/0! | H118: =G118/G$144 -> #DIV/0!
A119: synthetic rubber | C119: 53.3 | D119: =C119/$C$26 -> #DIV/0! | E119: kg | F119: 83.602397 | G119: =F119*$D119 -> #DIV/0! | H119: =G119/G$144 -> #DIV/0!
A120: glas | C120: 49 | D120: =C120/$C$26 -> #DIV/0! | E120: kg | F120: 11.436901 | G120: =F120*$D120 -> #DIV/0! | H120: =G120/G$144 -> #DIV/0!
A121: battery Li-ion recheargable, prismatic | C121: 82 | D121: =C121/$C$26 -> #DIV/0! | E121: kg | F121: 114.5666 | G121: =F121*$D121 -> #DIV/0! | H121: =G121/G$144 -> #DIV/0!
A122: electronics, for control units | C122: 23.3 | D122: =C122/$C$26 -> #DIV/0! | E122: kg | F122: 448.24729 | G122: =F122*$D122 -> #DIV/0! | H122: =G122/G$144 -> #DIV/0!
A123: ethylene, paints, fluids | C123: 22.2 | D123: =C123/$C$26 -> #DIV/0! | E123: kg | F123: 49.878196 | G123: =F123*$D123 -> #DIV/0! | H123: =G123/G$144 -> #DIV/0!
A124: tap water | C124: 3400 | D124: =C124/$B$4 -> 0.022666667 | E124: kg | F124: 0.0052467568 | G124: =F124*#REF! -> #REF! | H124: =G124/G$20 -> #REF!
A125: heat, district or industrial, natural gas | C125: 2400 | D125: =C125/$B$4 -> 0.016 | E125: MJ | F125: 0.66634297 | G125: =F125*#REF! -> #REF! | H125: =G125/G$20 -> #REF!
A126: electricity, photovoltaic, 570kWp open ground installation | C126: 2500 | D126: =C126/$C$26 -> #DIV/0! | E126: kWh | F126: 1.0261753 | G126: =F126*$D126 -> #DIV/0! | H126: =G126/G$20 -> #DIV/0!
A127: Transportation | C127: per vehicle
A128: transport, freight train | C128: 556.5 | D128: =C128/$C$26 -> #DIV/0! | E128: t-km | F128: 0.7022219 | G128: =F128*$D128 -> #DIV/0! | H128: =G128/G$144 -> #DIV/0!
A129: transport, freight, lorry 16-32 metric ton | C129: 59.1 | D129: =C129/$C$26 -> #DIV/0! | E129: t-km | F129: 2.7131612 | G129: =F129*$D129 -> #DIV/0! | H129: =G129/G$144 -> #DIV/0!
A130: transport, freight, sea, container ship | C130: 9534 | D130: =C130/$C$26 -> #DIV/0! | E130: t-km | F130: 0.12785666 | G130: =F130*$D130 -> #DIV/0! | H130: =G130/G$144 -> #DIV/0!
A131: Use phase | C131: per V-km
A132: electricity, medium voltage RER | C132: 0.26 | D132: =C132 -> 0.26 | E132: kWh | F132: 9.068338 | G132: =F132*$D132 -> 2.3577679 | H132: =G132/G$144 -> #REF!
A133: electricity, wind, 1-3MW turbine, onshore | C133: 0.26 | D133: =C133 -> 0.26 | E133: kWh | F133: 0.19506231 | G133: =F133*$D133 -> 0.050716201 | H133: #REF!
A134: electricity, photovoltaic, 570kWp open ground installation | C134: 0.26 | D134: =C134 -> 0.26 | E134: kWh | F134: 1.0261753 | G134: =F134*$D134 -> 0.26680557 | H134: #REF!
A135: electricity, hard coal | C135: 0.26 | D135: =C135 -> 0.26 | E135: kWh | F135: 10.339041 | G135: =F135*$D135 -> 2.6881507 | H135: #REF!
A136: Disposal | C136: per vehicle over lifespan
A137: glass at landfill | C137: 49 | D137: =C137/$C$26 -> #DIV/0! | E137: kg | F137: 0.14588608 | G137: =F137*$D137 -> #DIV/0! | H137: =G137/G$144 -> #DIV/0!
A138: mineral oil incineration | C138: 3.4 | D138: =C138/$C$26 -> #DIV/0! | E138: kg | F138: 0.24716555 | G138: =F138*$D138 -> #DIV/0! | H138: =G138/G$144 -> #DIV/0! | J138: Manufacturing (Materials + Processing)
A139: plastic, mixture at landfill | C139: 162.9 | D139: =C139/$C$26 -> #DIV/0! | E139: kg | F139: 0.23960025 | G139: =F139*$D139 -> #DIV/0! | H139: =G139/G$144 -> #DIV/0! | J139: steel, low-alloyed, hot rolled | K139: =C113 -> 953.4
A140: waste polyurethane foam | C140: 9.1 | D140: =C140/$C$26 -> #DIV/0! | E140: kg | F140: 0.67096498 | G140: =F140*$D140 -> #DIV/0! | H140: =G140/G$144 -> #DIV/0! | J140: Metal working, average for steel product manufacturing | K140: 953.4
A141: aluminium recycled | C141: =C115 -> 76.5 | D141: =C141/$C$26 -> #DIV/0! | J141: aluminium, primary, ingot | K141: =C115 -> 76.5
A142: Iron and mixed metal scrap recycled | C142: 956.9 | D142: =C142/$C$26 -> #DIV/0! | J142: Copper | K142: =C116 -> 287.1
A143: Total | J143: Extruded thermoformed plastic sheets | K143: =C117 -> 162.9
A144: Total EU electricity grid | C144: - | E144: - | G144: =SUM(#REF!)+SUM(G$137:G$140)+G132 -> #REF! | H144: =G144/G$144 -> #REF! | J144: Polypropylene & polyurethane | K144: =C118+#REF! -> #REF!
A145: Total EU electricity wind | C145: - | E145: - | G145: =SUM(#REF!)+SUM(G$137:G$140)+G133 -> #REF! | H145: =G145/G$144 -> #REF! | J145: synthetic rubber | K145: =C119 -> 53.3
A146: Total EU electricity photovoltaic | C146: - | E146: - | G146: =SUM(#REF!)+SUM(G$137:G$140)+G134 -> #REF! | H146: =G146/G$144 -> #REF! | J146: glas | K146: =C120 -> 49
A147: Total EU electricity hard coal | C147: - | E147: - | G147: =SUM(#REF!)+SUM(G$137:G$140)+G135 -> #REF! | H147: =G147/G$144 -> #REF! | J147: battery Li-ion recheargable, prismatic | K147: =C121 -> 82
J148: electronics, for control units | K148: =C122 -> 23.3
J149: ethylene, paints, fluids | K149: =#REF!+C123+#REF! -> #REF!
J150: tap water
J151: heat, district or industrial, natural gas
J152: electricity, photovoltaic, 570kWp open ground installation | K152: 2400

Sheet Absolute sustainability
A1: Absolute sustainability assessment for carbon footprint per FU | C1: Vehicule case study
C2: World population on 15.11.2022
A3: Determination of Absolute sustainability: climate change | B3: Absolute radiative forcing | C3: Values
A5: Planetary Boundary (PB) - radiative forcing | B5: W/m2 | C5: 1
A6: CF | B6: W/m2/ (kgCO2e/yr) | C6: 3.53e-13
A7: Planetary Boundary (PB) - climate change in CO2e | B7: kgCO2e/yr | C7: =C5/C6 -> 2.8328612e+12
A9: World population | B9: pers | C9: 8000000000
A10: Share of PB per person | B10: 1/pers | C10: =1/C9 -> 1.25e-10
A11: Planetary Boundary (PB) - CO2e impacts per person | B11: kgCO2e/pers/yr | C11: =C7*C10 -> 354.10765
A12: Economic allocation | D12: Grand fathering
A13: Country (see ISO code in "World carbon footprint" tab) | B13: Denmark | C13: DNK
A14: GDP Denmark PPP Kr./cap/yr | B14: CUR/cap/yr | C14: =INDEX('World carbon footprint'!$N$16:$N$131,MATCH('Absolute sustainability'!$C$13,'World carbon footprint'!$C$16:$C$131,0)) -> 361868.04 | D14: Total present consumption-based impact DK | E14: kgCO2e/pers/yr | F14: =INDEX('World carbon footprint'!$K$16:$K$131,MATCH('Absolute sustainability'!$C$13,'World carbon footprint'!$C$16:$C$131,0))*'Carbon footprint calculator'!$B$17 -> 10287.356
A15: Life cycle cost per FU (per V-km), module 5 | B15: CUR/V-km gasoline car | C15: ='Life cycle costing'!G22 -> 3.3551831
A16: Share of total boundary attributable to 1 vehicle km | B16: - | C16: =C15/C14 -> 9.2718415e-06 | D16: Reduction factor to reach PB | E16: - | F16: =F14/C11 -> 29.051493
A18: Sustainable boundary assigned to FU of 1 V-km | B18: kgCO2e/V-km | C18: =C16*C11 -> 0.00328323 | D18: Sustainable boundary assigned to 1 V-km | E18: kgCO2e/V-km | F18: =C21/F16 -> 0.010690946
A20: Impact | C20: Reference scenario Gas Vehicle | D20: Electric Vehicle - EU average | E20: Electric Vehicle - Wind | F20: Electric Vehicle - Photovoltaic | G20: Electric Vehicle - Hard coal | H20: E-bike - EU average | I20: Bike
A21: Carbon footprint impact per V-km, module 3 | B21: kgCO2e/V-km | C21: ='Carbon footprint calculator'!W15 -> 0.31058794 | D21: ='Carbon footprint calculator'!Y15 -> 0.14925681 | E21: ='Carbon footprint calculator'!Z15 -> 0.053008148 | F21: ='Carbon footprint calculator'!AA15 -> 0.070038846 | G21: ='Carbon footprint calculator'!X15 -> 0.33401216 | H21: ='Carbon footprint calculator'!AB15 -> 0.00792545 | I21: ='Carbon footprint calculator'!AC15 -> 0.0051664754
A22: Sustainable boundary target per V-km, economic allocation | C22: =C18 -> 0.00328323
A23: Sustainable boundary target per V-km, grand fathering | C23: =F18 -> 0.010690946
A25: Absolute Sust. Ratio & exceedance economic allocation | C25: =C21/$C$18 -> 94.598288 | D25: =D21/$C$18 -> 45.460357 | E25: =E21/$C$18 -> 16.145122 | F25: =F21/$C$18 -> 21.3323 | G25: =G21/$C$18 -> 101.73279 | H25: =H21/$C$18 -> 2.4139186 | I25: =I21/$C$18 -> 1.5735954
A26: Absolute Sust. Ratio & exceedance grand fathering | C26: =C21/$F$18 -> 29.051493 | D26: =D21/$F$18 -> 13.961048 | E26: =E21/$F$18 -> 4.9582281 | F26: =F21/$F$18 -> 6.55123 | G26: =G21/$F$18 -> 31.242527 | H26: =H21/$F$18 -> 0.74132356 | I26: =I21/$F$18 -> 0.48325709
A28: Comments: | B28: For the electric bike, it would reach the absolute sustainability level if the bike production would be reduced by e.g. electrification

Sheet Selected processes
I1: Method | J1: IPCC 2021 | K1: ReCiPe 2016 v1.03, endpoint (H) | L1: ReCiPe 2016 v1.03, endpoint (H) | M1: ReCiPe 2016 v1.03, endpoint (H) | N1: Cumulative Energy Demand (CED) | O1: selected LCI results | P1: Ratio CO2 fossil/non ren. cum. energy demand
D2: Conversion factors | E2: kg_to_g | F2: g/kg | G2: 1000 | I2: Category | J2: climate change | K2: total: human health | L2: total: ecosystem quality | M2: total: natural resources | N2: energy resources: non-renewable | O2: air | P2: CO2 fossil/total non renewable energy
C3: =INDEX('Ecoinvent data'!$B$5:$B$21242, MATCH('Selected processes'!D3,'Ecoinvent data'!$D$5:$D$21242,0)) -> #N/A | I3: Indicator | J3: global warming potential (GWP100) | K3: human health | L3: ecosystem quality | M3: natural resources | N3: energy content (HHV) | O3: CO2, fossil | P3: Check combustion included
D4: Process # | E4: Activity Name | F4: Geography | G4: Reference Product Name | H4: Reference Product Unit | I4: Reference Product Amount | J4: kg CO2-Eq | K4: min.lost | L4: species.yr | M4: USD 2013 | N4: MJ-Eq | O4: kg | P4: gCO2/MJ
A5: alkyd paint production, white, solvent-based, product in 60% solution stateRERalkyd paint, white, without solvent, in 60% solution statekg | B5: 17446 | C5: =INDEX('Ecoinvent data'!$B$5:$B$21242, MATCH('Selected processes'!D5,'Ecoinvent data'!$D$5:$D$21242,0)) -> 17299 | D5: 17299 | E5: steel production, low-alloyed, hot rolled | F5: RER | G5: =INDEX('Ecoinvent data'!G$5:G$21242,MATCH($D5,'Ecoinvent data'!$D$5:$D$21242,0)) -> steel, low-alloyed, hot rolled | H5: =INDEX('Ecoinvent data'!H$5:H$21242,MATCH($D5,'Ecoinvent data'!$D$5:$D$21242,0)) -> kg | I5: =INDEX('Ecoinvent data'!I$5:I$21242,MATCH($D5,'Ecoinvent data'!$D$5:$D$21242,0)) -> 1 | J5: =INDEX('Ecoinvent data'!J$5:J$21242,MATCH($D5,'Ecoinvent data'!$D$5:$D$21242,0)) -> 2.1807172 | K5: =INDEX('Ecoinvent data'!K$5:K$21242,MATCH($D5,'Ecoinvent data'!$D$5:$D$21242,0)) -> 7.9963289 | L5: =INDEX('Ecoinvent data'!L$5:L$21242,MATCH($D5,'Ecoinvent data'!$D$5:$D$21242,0)) -> 9.7808189e-09 | M5: =INDEX('Ecoinvent data'!M$5:M$21242,MATCH($D5,'Ecoinvent data'!$D$5:$D$21242,0)) -> 0.24593889 | N5: =INDEX('Ecoinvent data'!N$5:N$21242,MATCH($D5,'Ecoinvent data'!$D$5:$D$21242,0)) -> 25.556652 | ... P5: =INDEX('Ecoinvent data'!P$5:P$21242,MATCH($D5,'Ecoinvent data'!$D$5:$D$21242,0)) -> 76.062947
A6: aluminium production, primary, ingotRoWaluminium, primary, ingotkg | B6: 17078 | C6: =INDEX('Ecoinvent data'!$B$5:$B$21242, MATCH('Selected processes'!D6,'Ecoinvent data'!$D$5:$D$21242,0)) -> 16619 | D6: 16619 | E6: =INDEX('Ecoinvent data'!E$5:E$21242,MATCH($D6,'Ecoinvent data'!$D$5:$D$21242,0)) -> sheet rolling, steel | F6: =INDEX('Ecoinvent data'!F$5:F$21242,MATCH($D6,'Ecoinvent data'!$D$5:$D$21242,0)) -> RER | G6: =INDEX('Ecoinvent data'!G$5:G$21242,MATCH($D6,'Ecoinvent data'!$D$5:$D$21242,0)) -> sheet rolling, steel | H6: =INDEX('Ecoinvent data'!H$5:H$21242,MATCH($D6,'Ecoinvent data'!$D$5:$D$21242,0)) -> kg | I6: =INDEX('Ecoinvent data'!I$5:I$21242,MATCH($D6,'Ecoinvent data'!$D$5:$D$21242,0)) -> 1 | J6: =INDEX('Ecoinvent data'!J$5:J$21242,MATCH($D6,'Ecoinvent data'!$D$5:$D$21242,0)) -> 0.31200613 | K6: =INDEX('Ecoinvent data'!K$5:K$21242,MATCH($D6,'Ecoinvent data'!$D$5:$D$21242,0)) -> 0.73372079 | L6: =INDEX('Ecoinvent data'!L$5:L$21242,MATCH($D6,'Ecoinvent data'!$D$5:$D$21242,0)) -> 1.3767966e-09 | ... P6: =INDEX('Ecoinvent data'!P$5:P$21242,MATCH($D6,'Ecoinvent data'!$D$5:$D$21242,0)) -> 56.58959
A7: chromium oxide production, flakesRoWchromium oxide, flakeskg | B7: 323 | C7: =INDEX('Ecoinvent data'!$B$5:$B$21242, MATCH('Selected processes'!D7,'Ecoinvent data'!$D$5:$D$21242,0)) -> 458 | D7: 458 | E7: aluminium production, primary, ingot | F7: IAI Area, EU27 & EFTA | G7: =INDEX('Ecoinvent data'!G$5:G$21242,MATCH($D7,'Ecoinvent data'!$D$5:$D$21242,0)) -> aluminium, primary, ingot | H7: =INDEX('Ecoinvent data'!H$5:H$21242,MATCH($D7,'Ecoinvent data'!$D$5:$D$21242,0)) -> kg | I7: =INDEX('Ecoinvent data'!I$5:I$21242,MATCH($D7,'Ecoinvent data'!$D$5:$D$21242,0)) -> 1 | J7: =INDEX('Ecoinvent data'!J$5:J$21242,MATCH($D7,'Ecoinvent data'!$D$5:$D$21242,0)) -> 7.209838 | K7: =INDEX('Ecoinvent data'!K$5:K$21242,MATCH($D7,'Ecoinvent data'!$D$5:$D$21242,0)) -> 13.333429 | L7: =INDEX('Ecoinvent data'!L$5:L$21242,MATCH($D7,'Ecoinvent data'!$D$5:$D$21242,0)) -> 3.2653298e-08 | M7: =INDEX('Ecoinvent data'!M$5:M$21242,MATCH($D7,'Ecoinvent data'!$D$5:$D$21242,0)) -> 0.57610667 | N7: =INDEX('Ecoinvent data'!N$5:N$21242,MATCH($D7,'Ecoinvent data'!$D$5:$D$21242,0)) -> 115.04046 | ... P7: =INDEX('Ecoinvent data'!P$5:P$21242,MATCH($D7,'Ecoinvent data'!$D$5:$D$21242,0)) -> 55.834159
A8: sheet rolling, copperRERsheet rolling, copperkg | B8: 17076 | C8: =INDEX('Ecoinvent data'!$B$5:$B$21242, MATCH('Selected processes'!D8,'Ecoinvent data'!$D$5:$D$21242,0)) -> 16616 | D8: 16616 | E8: =INDEX('Ecoinvent data'!E$5:E$21242,MATCH($D8,'Ecoinvent data'!$D$5:$D$21242,0)) -> sheet rolling, copper | F8: =INDEX('Ecoinvent data'!F$5:F$21242,MATCH($D8,'Ecoinvent data'!$D$5:$D$21242,0)) -> RER | G8: =INDEX('Ecoinvent data'!G$5:G$21242,MATCH($D8,'Ecoinvent data'!$D$5:$D$21242,0)) -> sheet rolling, copper | H8: =INDEX('Ecoinvent data'!H$5:H$21242,MATCH($D8,'Ecoinvent data'!$D$5:$D$21242,0)) -> kg | I8: =INDEX('Ecoinvent data'!I$5:I$21242,MATCH($D8,'Ecoinvent data'!$D$5:$D$21242,0)) -> 1 | J8: =INDEX('Ecoinvent data'!J$5:J$21242,MATCH($D8,'Ecoinvent data'!$D$5:$D$21242,0)) -> 0.48163006 | K8: =INDEX('Ecoinvent data'!K$5:K$21242,MATCH($D8,'Ecoinvent data'!$D$5:$D$21242,0)) -> 4.9624408 | L8: =INDEX('Ecoinvent data'!L$5:L$21242,MATCH($D8,'Ecoinvent data'!$D$5:$D$21242,0)) -> 9.7940056e-09 | ... P8: =INDEX('Ecoinvent data'!P$5:P$21242,MATCH($D8,'Ecoinvent data'!$D$5:$D$21242,0)) -> 58.647233
A9: electronics production, for control unitsRERelectronics, for control unitskg | B9: 16311 | C9: =INDEX('Ecoinvent data'!$B$5:$B$21242, MATCH('Selected processes'!D9,'Ecoinvent data'!$D$5:$D$21242,0)) -> 12456 | D9: 12456 | E9: =INDEX('Ecoinvent data'!E$5:E$21242,MATCH($D9,'Ecoinvent data'!$D$5:$D$21242,0)) -> platinum to generic market for metal catalyst for catalytic converter | F9: =INDEX('Ecoinvent data'!F$5:F$21242,MATCH($D9,'Ecoinvent data'!$D$5:$D$21242,0)) -> GLO | G9: =INDEX('Ecoinvent data'!G$5:G$21242,MATCH($D9,'Ecoinvent data'!$D$5:$D$21242,0)) -> metal catalyst for catalytic converter | H9: =INDEX('Ecoinvent data'!H$5:H$21242,MATCH($D9,'Ecoinvent data'!$D$5:$D$21242,0)) -> kg | I9: =INDEX('Ecoinvent data'!I$5:I$21242,MATCH($D9,'Ecoinvent data'!$D$5:$D$21242,0)) -> 1 | J9: =INDEX('Ecoinvent data'!J$5:J$21242,MATCH($D9,'Ecoinvent data'!$D$5:$D$21242,0)) -> 69669.936 | K9: =INDEX('Ecoinvent data'!K$5:K$21242,MATCH($D9,'Ecoinvent data'!$D$5:$D$21242,0)) -> 571917.51 | L9: =INDEX('Ecoinvent data'!L$5:L$21242,MATCH($D9,'Ecoinvent data'!$D$5:$D$21242,0)) -> 0.0011984346 | ... P9: =INDEX('Ecoinvent data'!P$5:P$21242,MATCH($D9,'Ecoinvent data'!$D$5:$D$21242,0)) -> 57.364786
A10: ethylene production, averageRERethylenekg | B10: 12104 | C10: =INDEX('Ecoinvent data'!$B$5:$B$21242, MATCH('Selected processes'!D10,'Ecoinvent data'!$D$5:$D$21242,0)) -> 14632 | D10: 14632 | E10: =INDEX('Ecoinvent data'!E$5:E$21242,MATCH($D10,'Ecoinvent data'!$D$5:$D$21242,0)) -> market for polyethylene, high density, granulate | F10: =INDEX('Ecoinvent data'!F$5:F$21242,MATCH($D10,'Ecoinvent data'!$D$5:$D$21242,0)) -> GLO | G10: =INDEX('Ecoinvent data'!G$5:G$21242,MATCH($D10,'Ecoinvent data'!$D$5:$D$21242,0)) -> polyethylene, high density, granulate | H10: =INDEX('Ecoinvent data'!H$5:H$21242,MATCH($D10,'Ecoinvent data'!$D$5:$D$21242,0)) -> kg | I10: =INDEX('Ecoinvent data'!I$5:I$21242,MATCH($D10,'Ecoinvent data'!$D$5:$D$21242,0)) -> 1 | J10: =INDEX('Ecoinvent data'!J$5:J$21242,MATCH($D10,'Ecoinvent data'!$D$5:$D$21242,0)) -> 2.3276288 | K10: =INDEX('Ecoinvent data'!K$5:K$21242,MATCH($D10,'Ecoinvent data'!$D$5:$D$21242,0)) -> 2.3488561 | L10: =INDEX('Ecoinvent data'!L$5:L$21242,MATCH($D10,'Ecoinvent data'!$D$5:$D$21242,0)) -> 9.3798954e-09 | ... P10: =INDEX('Ecoinvent data'!P$5:P$21242,MATCH($D10,'Ecoinvent data'!$D$5:$D$21242,0)) -> 23.819736
A11: ethylene glycol productionRERethylene glycolkg | B11: 5070 | C11: =INDEX('Ecoinvent data'!$B$5:$B$21242, MATCH('Selected processes'!D11,'Ecoinvent data'!$D$5:$D$21242,0)) -> 7364 | D11: 7364 | E11: =INDEX('Ecoinvent data'!E$5:E$21242,MATCH($D11,'Ecoinvent data'!$D$5:$D$21242,0)) -> electronics production, for control units | F11: =INDEX('Ecoinvent data'!F$5:F$21242,MATCH($D11,'Ecoinvent data'!$D$5:$D$21242,0)) -> RER | G11: =INDEX('Ecoinvent data'!G$5:G$21242,MATCH($D11,'Ecoinvent data'!$D$5:$D$21242,0)) -> electronics, for control units | H11: =INDEX('Ecoinvent data'!H$5:H$21242,MATCH($D11,'Ecoinvent data'!$D$5:$D$21242,0)) -> kg | I11: =INDEX('Ecoinvent data'!I$5:I$21242,MATCH($D11,'Ecoinvent data'!$D$5:$D$21242,0)) -> 1 | J11: =INDEX('Ecoinvent data'!J$5:J$21242,MATCH($D11,'Ecoinvent data'!$D$5:$D$21242,0)) -> 31.86483 | K11: =INDEX('Ecoinvent data'!K$5:K$21242,MATCH($D11,'Ecoinvent data'!$D$5:$D$21242,0)) -> 91.052321 | L11: =INDEX('Ecoinvent data'!L$5:L$21242,MATCH($D11,'Ecoinvent data'!$D$5:$D$21242,0)) -> 2.0683158e-07 | ... P11: =INDEX('Ecoinvent data'!P$5:P$21242,MATCH($D11,'Ecoinvent data'!$D$5:$D$21242,0)) -> 61.755144
A12: market for flat glass, uncoatedRoWflat glass, uncoatedkg | B12: 5253 | C12: =INDEX('Ecoinvent data'!$B$5:$B$21242, MATCH('Selected processes'!D12,'Ecoinvent data'!$D$5:$D$21242,0)) -> 7587 | D12: 7587 | E12: =INDEX('Ecoinvent data'!E$5:E$21242,MATCH($D12,'Ecoinvent data'!$D$5:$D$21242,0)) -> ethylene production, average | F12: =INDEX('Ecoinvent data'!F$5:F$21242,MATCH($D12,'Ecoinvent data'!$D$5:$D$21242,0)) -> RER | G12: =INDEX('Ecoinvent data'!G$5:G$21242,MATCH($D12,'Ecoinvent data'!$D$5:$D$21242,0)) -> ethylene | H12: =INDEX('Ecoinvent data'!H$5:H$21242,MATCH($D12,'Ecoinvent data'!$D$5:$D$21242,0)) -> kg | I12: =INDEX('Ecoinvent data'!I$5:I$21242,MATCH($D12,'Ecoinvent data'!$D$5:$D$21242,0)) -> 1 | J12: =INDEX('Ecoinvent data'!J$5:J$21242,MATCH($D12,'Ecoinvent data'!$D$5:$D$21242,0)) -> 1.4469179 | K12: =INDEX('Ecoinvent data'!K$5:K$21242,MATCH($D12,'Ecoinvent data'!$D$5:$D$21242,0)) -> 1.1204239 | L12: =INDEX('Ecoinvent data'!L$5:L$21242,MATCH($D12,'Ecoinvent data'!$D$5:$D$21242,0)) -> 5.2741423e-09 | ... P12: =INDEX('Ecoinvent data'!P$5:P$21242,MATCH($D12,'Ecoinvent data'!$D$5:$D$21242,0)) -> 16.638073
A13: market for heat, district or industrial, natural gasRoWheat, district or industrial, natural gasMJ | B13: 17736 | C13: =INDEX('Ecoinvent data'!$B$5:$B$21242, MATCH('Selected processes'!D13,'Ecoinvent data'!$D$5:$D$21242,0)) -> 17773 | D13: 17773 | E13: =INDEX('Ecoinvent data'!E$5:E$21242,MATCH($D13,'Ecoinvent data'!$D$5:$D$21242,0)) -> tap water production, conventional treatment | F13: =INDEX('Ecoinvent data'!F$5:F$21242,MATCH($D13,'Ecoinvent data'!$D$5:$D$21242,0)) -> RoW | G13: =INDEX('Ecoinvent data'!G$5:G$21242,MATCH($D13,'Ecoinvent data'!$D$5:$D$21242,0)) -> tap water | H13: =INDEX('Ecoinvent data'!H$5:H$21242,MATCH($D13,'Ecoinvent data'!$D$5:$D$21242,0)) -> kg | I13: =INDEX('Ecoinvent data'!I$5:I$21242,MATCH($D13,'Ecoinvent data'!$D$5:$D$21242,0)) -> 1 | J13: =INDEX('Ecoinvent data'!J$5:J$21242,MATCH($D13,'Ecoinvent data'!$D$5:$D$21242,0)) -> 0.00043545824 | K13: =INDEX('Ecoinvent data'!K$5:K$21242,MATCH($D13,'Ecoinvent data'!$D$5:$D$21242,0)) -> 0.00063383807 | L13: =INDEX('Ecoinvent data'!L$5:L$21242,MATCH($D13,'Ecoinvent data'!$D$5:$D$21242,0)) -> 1.9288846e-12 | ... P13: =INDEX('Ecoinvent data'!P$5:P$21242,MATCH($D13,'Ecoinvent data'!$D$5:$D$21242,0)) -> 68.243499
A14: market for leadGLOleadkg | B14: 6843 | C14: =INDEX('Ecoinvent data'!$B$5:$B$21242, MATCH('Selected processes'!D14,'Ecoinvent data'!$D$5:$D$21242,0)) -> 9148 | D14: 9148 | E14: =INDEX('Ecoinvent data'!E$5:E$21242,MATCH($D14,'Ecoinvent data'!$D$5:$D$21242,0)) -> heat production, natural gas, at industrial furnace >100kW | F14: =INDEX('Ecoinvent data'!F$5:F$21242,MATCH($D14,'Ecoinvent data'!$D$5:$D$21242,0)) -> Europe without Switzerland | G14: =INDEX('Ecoinvent data'!G$5:G$21242,MATCH($D14,'Ecoinvent data'!$D$5:$D$21242,0)) -> heat, district or industrial, natural gas | H14: =INDEX('Ecoinvent data'!H$5:H$21242,MATCH($D14,'Ecoinvent data'!$D$5:$D$21242,0)) -> MJ | I14: =INDEX('Ecoinvent data'!I$5:I$21242,MATCH($D14,'Ecoinvent data'!$D$5:$D$21242,0)) -> 1 | J14: =INDEX('Ecoinvent data'!J$5:J$21242,MATCH($D14,'Ecoinvent data'!$D$5:$D$21242,0)) -> 0.075656104 | K14: =INDEX('Ecoinvent data'!K$5:K$21242,MATCH($D14,'Ecoinvent data'!$D$5:$D$21242,0)) -> 0.044167738 | L14: =INDEX('Ecoinvent data'!L$5:L$21242,MATCH($D14,'Ecoinvent data'!$D$5:$D$21242,0)) -> 2.338698e-10 | ... P14: =INDEX('Ecoinvent data'!P$5:P$21242,MATCH($D14,'Ecoinvent data'!$D$5:$D$21242,0)) -> 53.883249
A15: light fuel oil, burned in industrial furnace 1MW, non-modulatingRERLight fuel oil, burned in furnace 1MW of greenhouse/MJMJ | B15: 14708 | C15: =INDEX('Ecoinvent data'!$B$5:$B$21242, MATCH('Selected processes'!D15,'Ecoinvent data'!$D$5:$D$21242,0)) -> 7235 | D15: 7235 | E15: market group for electricity, medium voltage | F15: UCTE | G15: =INDEX('Ecoinvent data'!G$5:G$21242,MATCH($D15,'Ecoinvent data'!$D$5:$D$21242,0)) -> electricity, medium voltage | H15: =INDEX('Ecoinvent data'!H$5:H$21242,MATCH($D15,'Ecoinvent data'!$D$5:$D$21242,0)) -> kWh | I15: =INDEX('Ecoinvent data'!I$5:I$21242,MATCH($D15,'Ecoinvent data'!$D$5:$D$21242,0)) -> 1 | J15: =INDEX('Ecoinvent data'!J$5:J$21242,MATCH($D15,'Ecoinvent data'!$D$5:$D$21242,0)) -> 0.38493508 | K15: =INDEX('Ecoinvent data'!K$5:K$21242,MATCH($D15,'Ecoinvent data'!$D$5:$D$21242,0)) -> 0.48931866 | L15: =INDEX('Ecoinvent data'!L$5:L$21242,MATCH($D15,'Ecoinvent data'!$D$5:$D$21242,0)) -> 1.8304805e-09 | M15: =INDEX('Ecoinvent data'!M$5:M$21242,MATCH($D15,'Ecoinvent data'!$D$5:$D$21242,0)) -> 0.019620494 | N15: =INDEX('Ecoinvent data'!N$5:N$21242,MATCH($D15,'Ecoinvent data'!$D$5:$D$21242,0)) -> 8.8834816 | ... P15: =INDEX('Ecoinvent data'!P$5:P$21242,MATCH($D15,'Ecoinvent data'!$D$5:$D$21242,0)) -> 39.707089
A16: market for nickel, class 1GLOnickel, class 1kg | B16: 14738 | C16: =INDEX('Ecoinvent data'!$B$5:$B$21242, MATCH('Selected processes'!D16,'Ecoinvent data'!$D$5:$D$21242,0)) -> 18124 | D16: 18124 | E16: =INDEX('Ecoinvent data'!E$5:E$21242,MATCH($D16,'Ecoinvent data'!$D$5:$D$21242,0)) -> market group for transport, freight train | F16: =INDEX('Ecoinvent data'!F$5:F$21242,MATCH($D16,'Ecoinvent data'!$D$5:$D$21242,0)) -> RER | G16: =INDEX('Ecoinvent data'!G$5:G$21242,MATCH($D16,'Ecoinvent data'!$D$5:$D$21242,0)) -> transport, freight train | H16: =INDEX('Ecoinvent data'!H$5:H$21242,MATCH($D16,'Ecoinvent data'!$D$5:$D$21242,0)) -> metric ton*km | I16: =INDEX('Ecoinvent data'!I$5:I$21242,MATCH($D16,'Ecoinvent data'!$D$5:$D$21242,0)) -> 1 | J16: =INDEX('Ecoinvent data'!J$5:J$21242,MATCH($D16,'Ecoinvent data'!$D$5:$D$21242,0)) -> 0.045728106 | K16: =INDEX('Ecoinvent data'!K$5:K$21242,MATCH($D16,'Ecoinvent data'!$D$5:$D$21242,0)) -> 0.068157807 | L16: =INDEX('Ecoinvent data'!L$5:L$21242,MATCH($D16,'Ecoinvent data'!$D$5:$D$21242,0)) -> 2.5241034e-10 | ... P16: =INDEX('Ecoinvent data'!P$5:P$21242,MATCH($D16,'Ecoinvent data'!$D$5:$D$21242,0)) -> 58.032086
A17: market for polyethylene, high density, granulateGLOpolyethylene, high density, granulatekg | B17: 13322 | C17: =INDEX('Ecoinvent data'!$B$5:$B$21242, MATCH('Selected processes'!D17,'Ecoinvent data'!$D$5:$D$21242,0)) -> 18241 | D17: 18241 | E17: =INDEX('Ecoinvent data'!E$5:E$21242,MATCH($D17,'Ecoinvent data'!$D$5:$D$21242,0)) -> market for transport, freight, lorry 16-32 metric ton, EURO4 | F17: =INDEX('Ecoinvent data'!F$5:F$21242,MATCH($D17,'Ecoinvent data'!$D$5:$D$21242,0)) -> RoW | G17: =INDEX('Ecoinvent data'!G$5:G$21242,MATCH($D17,'Ecoinvent data'!$D$5:$D$21242,0)) -> transport, freight, lorry 16-32 metric ton, EURO4 | H17: =INDEX('Ecoinvent data'!H$5:H$21242,MATCH($D17,'Ecoinvent data'!$D$5:$D$21242,0)) -> metric ton*km | I17: =INDEX('Ecoinvent data'!I$5:I$21242,MATCH($D17,'Ecoinvent data'!$D$5:$D$21242,0)) -> 1 | J17: =INDEX('Ecoinvent data'!J$5:J$21242,MATCH($D17,'Ecoinvent data'!$D$5:$D$21242,0)) -> 0.19079134 | K17: =INDEX('Ecoinvent data'!K$5:K$21242,MATCH($D17,'Ecoinvent data'!$D$5:$D$21242,0)) -> 0.20108682 | L17: =INDEX('Ecoinvent data'!L$5:L$21242,MATCH($D17,'Ecoinvent data'!$D$5:$D$21242,0)) -> 8.7787947e-10 | ... P17: =INDEX('Ecoinvent data'!P$5:P$21242,MATCH($D17,'Ecoinvent data'!$D$5:$D$21242,0)) -> 60.008519
A18: polypropylene production, granulateRERpolypropylene, granulatekg | B18: 18150 | C18: =INDEX('Ecoinvent data'!$B$5:$B$21242, MATCH('Selected processes'!D18,'Ecoinvent data'!$D$5:$D$21242,0)) -> 18438 | D18: 18438 | E18: =INDEX('Ecoinvent data'!E$5:E$21242,MATCH($D18,'Ecoinvent data'!$D$5:$D$21242,0)) -> transport, freight, sea, container ship | F18: =INDEX('Ecoinvent data'!F$5:F$21242,MATCH($D18,'Ecoinvent data'!$D$5:$D$21242,0)) -> GLO | G18: =INDEX('Ecoinvent data'!G$5:G$21242,MATCH($D18,'Ecoinvent data'!$D$5:$D$21242,0)) -> transport, freight, sea, container ship | H18: =INDEX('Ecoinvent data'!H$5:H$21242,MATCH($D18,'Ecoinvent data'!$D$5:$D$21242,0)) -> metric ton*km | I18: =INDEX('Ecoinvent data'!I$5:I$21242,MATCH($D18,'Ecoinvent data'!$D$5:$D$21242,0)) -> 1 | J18: =INDEX('Ecoinvent data'!J$5:J$21242,MATCH($D18,'Ecoinvent data'!$D$5:$D$21242,0)) -> 0.010163513 | K18: =INDEX('Ecoinvent data'!K$5:K$21242,MATCH($D18,'Ecoinvent data'!$D$5:$D$21242,0)) -> 0.026445888 | L18: =INDEX('Ecoinvent data'!L$5:L$21242,MATCH($D18,'Ecoinvent data'!$D$5:$D$21242,0)) -> 9.6094188e-11 | ... P18: =INDEX('Ecoinvent data'!P$5:P$21242,MATCH($D18,'Ecoinvent data'!$D$5:$D$21242,0)) -> 69.871717
A19: market for polyvinylchloride, suspension polymerisedGLOpolyvinylchloride, suspension polymerisedkg | B19: 11946 | C19: =INDEX('Ecoinvent data'!$B$5:$B$21242, MATCH('Selected processes'!D19,'Ecoinvent data'!$D$5:$D$21242,0)) -> 14137 | D19: 14137 | E19: =INDEX('Ecoinvent data'!E$5:E$21242,MATCH($D19,'Ecoinvent data'!$D$5:$D$21242,0)) -> market for petrol, low-sulfur | F19: =INDEX('Ecoinvent data'!F$5:F$21242,MATCH($D19,'Ecoinvent data'!$D$5:$D$21242,0)) -> Europe without Switzerland | G19: =INDEX('Ecoinvent data'!G$5:G$21242,MATCH($D19,'Ecoinvent data'!$D$5:$D$21242,0)) -> petrol, low-sulfur | H19: =INDEX('Ecoinvent data'!H$5:H$21242,MATCH($D19,'Ecoinvent data'!$D$5:$D$21242,0)) -> kg | I19: =INDEX('Ecoinvent data'!I$5:I$21242,MATCH($D19,'Ecoinvent data'!$D$5:$D$21242,0)) -> 1 | J19: =INDEX('Ecoinvent data'!J$5:J$21242,MATCH($D19,'Ecoinvent data'!$D$5:$D$21242,0)) -> 1.0179093 | K19: =INDEX('Ecoinvent data'!K$5:K$21242,MATCH($D19,'Ecoinvent data'!$D$5:$D$21242,0)) -> 1.0613393 | L19: =INDEX('Ecoinvent data'!L$5:L$21242,MATCH($D19,'Ecoinvent data'!$D$5:$D$21242,0)) -> 4.4865308e-09 | ... P19: =INDEX('Ecoinvent data'!P$5:P$21242,MATCH($D19,'Ecoinvent data'!$D$5:$D$21242,0)) -> 11.612072
A20: sheet rolling, steelRERsheet rolling, steelkg | B20: 20237 | C20: =INDEX('Ecoinvent data'!$B$5:$B$21242, MATCH('Selected processes'!D20,'Ecoinvent data'!$D$5:$D$21242,0)) -> 19923 | D20: 19923 | E20: =INDEX('Ecoinvent data'!E$5:E$21242,MATCH($D20,'Ecoinvent data'!$D$5:$D$21242,0)) -> treatment of waste plastic, mixture, municipal incineration | F20: =INDEX('Ecoinvent data'!F$5:F$21242,MATCH($D20,'Ecoinvent data'!$D$5:$D$21242,0)) -> CH | G20: =INDEX('Ecoinvent data'!G$5:G$21242,MATCH($D20,'Ecoinvent data'!$D$5:$D$21242,0)) -> waste plastic, mixture | H20: =INDEX('Ecoinvent data'!H$5:H$21242,MATCH($D20,'Ecoinvent data'!$D$5:$D$21242,0)) -> kg | I20: =INDEX('Ecoinvent data'!I$5:I$21242,MATCH($D20,'Ecoinvent data'!$D$5:$D$21242,0)) -> -1 | J20: =INDEX('Ecoinvent data'!J$5:J$21242,MATCH($D20,'Ecoinvent data'!$D$5:$D$21242,0)) -> 2.3457342 | K20: =INDEX('Ecoinvent data'!K$5:K$21242,MATCH($D20,'Ecoinvent data'!$D$5:$D$21242,0)) -> 1.3115341 | L20: =INDEX('Ecoinvent data'!L$5:L$21242,MATCH($D20,'Ecoinvent data'!$D$5:$D$21242,0)) -> 6.7933555e-09 | ... P20: =INDEX('Ecoinvent data'!P$5:P$21242,MATCH($D20,'Ecoinvent data'!$D$5:$D$21242,0)) -> 4791.4643
A21: steel production, low-alloyed, hot rolledRERsteel, low-alloyed, hot rolledkg | B21: 20052 | C21: =INDEX('Ecoinvent data'!$B$5:$B$21242, MATCH('Selected processes'!D21,'Ecoinvent data'!$D$5:$D$21242,0)) -> 19515 | D21: 19515 | E21: =INDEX('Ecoinvent data'!E$5:E$21242,MATCH($D21,'Ecoinvent data'!$D$5:$D$21242,0)) -> treatment of waste glass, inert material landfill | F21: =INDEX('Ecoinvent data'!F$5:F$21242,MATCH($D21,'Ecoinvent data'!$D$5:$D$21242,0)) -> CH | G21: =INDEX('Ecoinvent data'!G$5:G$21242,MATCH($D21,'Ecoinvent data'!$D$5:$D$21242,0)) -> waste glass | H21: =INDEX('Ecoinvent data'!H$5:H$21242,MATCH($D21,'Ecoinvent data'!$D$5:$D$21242,0)) -> kg | I21: =INDEX('Ecoinvent data'!I$5:I$21242,MATCH($D21,'Ecoinvent data'!$D$5:$D$21242,0)) -> -1 | J21: =INDEX('Ecoinvent data'!J$5:J$21242,MATCH($D21,'Ecoinvent data'!$D$5:$D$21242,0)) -> 0.0056607781 | K21: =INDEX('Ecoinvent data'!K$5:K$21242,MATCH($D21,'Ecoinvent data'!$D$5:$D$21242,0)) -> 0.0067425637 | L21: =INDEX('Ecoinvent data'!L$5:L$21242,MATCH($D21,'Ecoinvent data'!$D$5:$D$21242,0)) -> 3.4762451e-11 | ... P21: =INDEX('Ecoinvent data'!P$5:P$21242,MATCH($D21,'Ecoinvent data'!$D$5:$D$21242,0)) -> 27.641328
A22: market for sulfuric acidRERsulfuric acidkg | B22: 14809 | C22: =INDEX('Ecoinvent data'!$B$5:$B$21242, MATCH('Selected processes'!D22,'Ecoinvent data'!$D$5:$D$21242,0)) -> 12482 | D22: 12482 | E22: =INDEX('Ecoinvent data'!E$5:E$21242,MATCH($D22,'Ecoinvent data'!$D$5:$D$21242,0)) -> metal working, average for metal product manufacturing | F22: =INDEX('Ecoinvent data'!F$5:F$21242,MATCH($D22,'Ecoinvent data'!$D$5:$D$21242,0)) -> RER | G22: =INDEX('Ecoinvent data'!G$5:G$21242,MATCH($D22,'Ecoinvent data'!$D$5:$D$21242,0)) -> metal working, average for metal product manufacturing | H22: =INDEX('Ecoinvent data'!H$5:H$21242,MATCH($D22,'Ecoinvent data'!$D$5:$D$21242,0)) -> kg | I22: =INDEX('Ecoinvent data'!I$5:I$21242,MATCH($D22,'Ecoinvent data'!$D$5:$D$21242,0)) -> 1 | J22: =INDEX('Ecoinvent data'!J$5:J$21242,MATCH($D22,'Ecoinvent data'!$D$5:$D$21242,0)) -> 1.8612564 | K22: =INDEX('Ecoinvent data'!K$5:K$21242,MATCH($D22,'Ecoinvent data'!$D$5:$D$21242,0)) -> 6.3717697 | L22: =INDEX('Ecoinvent data'!L$5:L$21242,MATCH($D22,'Ecoinvent data'!$D$5:$D$21242,0)) -> 1.3596458e-08 | ... P22: =INDEX('Ecoinvent data'!P$5:P$21242,MATCH($D22,'Ecoinvent data'!$D$5:$D$21242,0)) -> 58.985007
A23: market for synthetic rubberGLOsynthetic rubberkg | B23: 5316 | C23: =INDEX('Ecoinvent data'!$B$5:$B$21242, MATCH('Selected processes'!D23,'Ecoinvent data'!$D$5:$D$21242,0)) -> 7694 | D23: 7694 | E23: =INDEX('Ecoinvent data'!E$5:E$21242,MATCH($D23,'Ecoinvent data'!$D$5:$D$21242,0)) -> extrusion of plastic sheets and thermoforming, inline | F23: =INDEX('Ecoinvent data'!F$5:F$21242,MATCH($D23,'Ecoinvent data'!$D$5:$D$21242,0)) -> RoW | G23: =INDEX('Ecoinvent data'!G$5:G$21242,MATCH($D23,'Ecoinvent data'!$D$5:$D$21242,0)) -> extrusion of plastic sheets and thermoforming, inline | H23: =INDEX('Ecoinvent data'!H$5:H$21242,MATCH($D23,'Ecoinvent data'!$D$5:$D$21242,0)) -> kg | I23: =INDEX('Ecoinvent data'!I$5:I$21242,MATCH($D23,'Ecoinvent data'!$D$5:$D$21242,0)) -> 1 | J23: =INDEX('Ecoinvent data'!J$5:J$21242,MATCH($D23,'Ecoinvent data'!$D$5:$D$21242,0)) -> 1.0973734 | K23: =INDEX('Ecoinvent data'!K$5:K$21242,MATCH($D23,'Ecoinvent data'!$D$5:$D$21242,0)) -> 1.5186295 | L23: =INDEX('Ecoinvent data'!L$5:L$21242,MATCH($D23,'Ecoinvent data'!$D$5:$D$21242,0)) -> 4.7148823e-09 | ... P23: =INDEX('Ecoinvent data'!P$5:P$21242,MATCH($D23,'Ecoinvent data'!$D$5:$D$21242,0)) -> 67.288316
A24: tap water production, conventional treatmentRoWtap waterkg | B24: 16391 | C24: =INDEX('Ecoinvent data'!$B$5:$B$21242, MATCH('Selected processes'!D24,'Ecoinvent data'!$D$5:$D$21242,0)) -> 14673 | D24: 14673 | E24: =INDEX('Ecoinvent data'!E$5:E$21242,MATCH($D24,'Ecoinvent data'!$D$5:$D$21242,0)) -> polypropylene production, granulate | F24: =INDEX('Ecoinvent data'!F$5:F$21242,MATCH($D24,'Ecoinvent data'!$D$5:$D$21242,0)) -> RER | G24: =INDEX('Ecoinvent data'!G$5:G$21242,MATCH($D24,'Ecoinvent data'!$D$5:$D$21242,0)) -> polypropylene, granulate | H24: =INDEX('Ecoinvent data'!H$5:H$21242,MATCH($D24,'Ecoinvent data'!$D$5:$D$21242,0)) -> kg | I24: =INDEX('Ecoinvent data'!I$5:I$21242,MATCH($D24,'Ecoinvent data'!$D$5:$D$21242,0)) -> 1 | J24: =INDEX('Ecoinvent data'!J$5:J$21242,MATCH($D24,'Ecoinvent data'!$D$5:$D$21242,0)) -> 1.8835237 | K24: =INDEX('Ecoinvent data'!K$5:K$21242,MATCH($D24,'Ecoinvent data'!$D$5:$D$21242,0)) -> 1.6899833 | L24: =INDEX('Ecoinvent data'!L$5:L$21242,MATCH($D24,'Ecoinvent data'!$D$5:$D$21242,0)) -> 7.2309967e-09 | ... P24: =INDEX('Ecoinvent data'!P$5:P$21242,MATCH($D24,'Ecoinvent data'!$D$5:$D$21242,0)) -> 19.199338
A25: market for zincGLOzinckg | B25: 666 | C25: =INDEX('Ecoinvent data'!$B$5:$B$21242, MATCH('Selected processes'!D25,'Ecoinvent data'!$D$5:$D$21242,0)) -> 992 | D25: 992 | E25: battery production, Li-ion, LiMn2O4, rechargeable, prismatic | F25: GLO | G25: =INDEX('Ecoinvent data'!G$5:G$21242,MATCH($D25,'Ecoinvent data'!$D$5:$D$21242,0)) -> battery, Li-ion, LiMn2O4, rechargeable, prismatic | H25: =INDEX('Ecoinvent data'!H$5:H$21242,MATCH($D25,'Ecoinvent data'!$D$5:$D$21242,0)) -> kg | I25: =INDEX('Ecoinvent data'!I$5:I$21242,MATCH($D25,'Ecoinvent data'!$D$5:$D$21242,0)) -> 1 | J25: =INDEX('Ecoinvent data'!J$5:J$21242,MATCH($D25,'Ecoinvent data'!$D$5:$D$21242,0)) -> 8.4296788 | K25: =INDEX('Ecoinvent data'!K$5:K$21242,MATCH($D25,'Ecoinvent data'!$D$5:$D$21242,0)) -> 17.887181 | L25: =INDEX('Ecoinvent data'!L$5:L$21242,MATCH($D25,'Ecoinvent data'!$D$5:$D$21242,0)) -> 4.8297512e-08 | M25: =INDEX('Ecoinvent data'!M$5:M$21242,MATCH($D25,'Ecoinvent data'!$D$5:$D$21242,0)) -> 1.2276162 | N25: =INDEX('Ecoinvent data'!N$5:N$21242,MATCH($D25,'Ecoinvent data'!$D$5:$D$21242,0)) -> 126.17824 | ... P25: =INDEX('Ecoinvent data'!P$5:P$21242,MATCH($D25,'Ecoinvent data'!$D$5:$D$21242,0)) -> 57.971952
A26: battery production, Li-ion, LiMn2O4, rechargeable, prismaticGLObattery, Li-ion, LiMn2O4, rechargeable, prismatickg | B26: 3621 | C26: =INDEX('Ecoinvent data'!$B$5:$B$21242, MATCH('Selected processes'!D26,'Ecoinvent data'!$D$5:$D$21242,0)) -> 6295 | D26: 6295 | E26: =INDEX('Ecoinvent data'!E$5:E$21242,MATCH($D26,'Ecoinvent data'!$D$5:$D$21242,0)) -> electricity production, photovoltaic, 570kWp open ground installation, multi-Si | F26: =INDEX('Ecoinvent data'!F$5:F$21242,MATCH($D26,'Ecoinvent data'!$D$5:$D$21242,0)) -> RoW | G26: =INDEX('Ecoinvent data'!G$5:G$21242,MATCH($D26,'Ecoinvent data'!$D$5:$D$21242,0)) -> electricity, low voltage | H26: =INDEX('Ecoinvent data'!H$5:H$21242,MATCH($D26,'Ecoinvent data'!$D$5:$D$21242,0)) -> kWh | I26: =INDEX('Ecoinvent data'!I$5:I$21242,MATCH($D26,'Ecoinvent data'!$D$5:$D$21242,0)) -> 1 | J26: =INDEX('Ecoinvent data'!J$5:J$21242,MATCH($D26,'Ecoinvent data'!$D$5:$D$21242,0)) -> 0.080250611 | K26: =INDEX('Ecoinvent data'!K$5:K$21242,MATCH($D26,'Ecoinvent data'!$D$5:$D$21242,0)) -> 0.14759408 | L26: =INDEX('Ecoinvent data'!L$5:L$21242,MATCH($D26,'Ecoinvent data'!$D$5:$D$21242,0)) -> 6.5404219e-10 | ... P26: =INDEX('Ecoinvent data'!P$5:P$21242,MATCH($D26,'Ecoinvent data'!$D$5:$D$21242,0)) -> 65.679209
A27: extrusion of plastic sheets and thermoforming, inlineRoWextrusion of plastic sheets and thermoforming, inlinekg | B27: 3754 | C27: =INDEX('Ecoinvent data'!$B$5:$B$21242, MATCH('Selected processes'!D27,'Ecoinvent data'!$D$5:$D$21242,0)) -> 4527 | D27: 4527 | E27: =INDEX('Ecoinvent data'!E$5:E$21242,MATCH($D27,'Ecoinvent data'!$D$5:$D$21242,0)) -> electricity production, wind, 1-3MW turbine, onshore | F27: =INDEX('Ecoinvent data'!F$5:F$21242,MATCH($D27,'Ecoinvent data'!$D$5:$D$21242,0)) -> RoW | G27: =INDEX('Ecoinvent data'!G$5:G$21242,MATCH($D27,'Ecoinvent data'!$D$5:$D$21242,0)) -> electricity, high voltage | H27: =INDEX('Ecoinvent data'!H$5:H$21242,MATCH($D27,'Ecoinvent data'!$D$5:$D$21242,0)) -> kWh | I27: =INDEX('Ecoinvent data'!I$5:I$21242,MATCH($D27,'Ecoinvent data'!$D$5:$D$21242,0)) -> 1 | J27: =INDEX('Ecoinvent data'!J$5:J$21242,MATCH($D27,'Ecoinvent data'!$D$5:$D$21242,0)) -> 0.014747928 | K27: =INDEX('Ecoinvent data'!K$5:K$21242,MATCH($D27,'Ecoinvent data'!$D$5:$D$21242,0)) -> 0.040992466 | L27: =INDEX('Ecoinvent data'!L$5:L$21242,MATCH($D27,'Ecoinvent data'!$D$5:$D$21242,0)) -> 8.2698819e-11 | ... P27: =INDEX('Ecoinvent data'!P$5:P$21242,MATCH($D27,'Ecoinvent data'!$D$5:$D$21242,0)) -> 65.242525
A28: lubricating oil productionRERlubricating oilkg | B28: 2476 | C28: =INDEX('Ecoinvent data'!$B$5:$B$21242, MATCH('Selected processes'!D28,'Ecoinvent data'!$D$5:$D$21242,0)) -> 3591 | D28: 3591 | E28: =INDEX('Ecoinvent data'!E$5:E$21242,MATCH($D28,'Ecoinvent data'!$D$5:$D$21242,0)) -> electricity production, hard coal | F28: =INDEX('Ecoinvent data'!F$5:F$21242,MATCH($D28,'Ecoinvent data'!$D$5:$D$21242,0)) -> RoW | G28: =INDEX('Ecoinvent data'!G$5:G$21242,MATCH($D28,'Ecoinvent data'!$D$5:$D$21242,0)) -> electricity, high voltage | H28: =INDEX('Ecoinvent data'!H$5:H$21242,MATCH($D28,'Ecoinvent data'!$D$5:$D$21242,0)) -> kWh | I28: =INDEX('Ecoinvent data'!I$5:I$21242,MATCH($D28,'Ecoinvent data'!$D$5:$D$21242,0)) -> 1 | J28: =INDEX('Ecoinvent data'!J$5:J$21242,MATCH($D28,'Ecoinvent data'!$D$5:$D$21242,0)) -> 1.0955326 | K28: =INDEX('Ecoinvent data'!K$5:K$21242,MATCH($D28,'Ecoinvent data'!$D$5:$D$21242,0)) -> 1.6507311 | L28: =INDEX('Ecoinvent data'!L$5:L$21242,MATCH($D28,'Ecoinvent data'!$D$5:$D$21242,0)) -> 5.7761989e-09 | ... P28: =INDEX('Ecoinvent data'!P$5:P$21242,MATCH($D28,'Ecoinvent data'!$D$5:$D$21242,0)) -> 90.129093
A29: market for metal working, average for aluminium product manufacturingGLOmetal working, average for aluminium product manufacturingkg | B29: 11491 | C29: =INDEX('Ecoinvent data'!$B$5:$B$21242, MATCH('Selected processes'!D29,'Ecoinvent data'!$D$5:$D$21242,0)) -> 12471 | D29: 12471 | E29: =INDEX('Ecoinvent data'!E$5:E$21242,MATCH($D29,'Ecoinvent data'!$D$5:$D$21242,0)) -> market for metal working, average for aluminium product manufacturing | F29: =INDEX('Ecoinvent data'!F$5:F$21242,MATCH($D29,'Ecoinvent data'!$D$5:$D$21242,0)) -> GLO | G29: =INDEX('Ecoinvent data'!G$5:G$21242,MATCH($D29,'Ecoinvent data'!$D$5:$D$21242,0)) -> metal working, average for aluminium product manufacturing | H29: =INDEX('Ecoinvent data'!H$5:H$21242,MATCH($D29,'Ecoinvent data'!$D$5:$D$21242,0)) -> kg | I29: =INDEX('Ecoinvent data'!I$5:I$21242,MATCH($D29,'Ecoinvent data'!$D$5:$D$21242,0)) -> 1 | J29: =INDEX('Ecoinvent data'!J$5:J$21242,MATCH($D29,'Ecoinvent data'!$D$5:$D$21242,0)) -> 4.0822947 | K29: =INDEX('Ecoinvent data'!K$5:K$21242,MATCH($D29,'Ecoinvent data'!$D$5:$D$21242,0)) -> 6.1446476 | L29: =INDEX('Ecoinvent data'!L$5:L$21242,MATCH($D29,'Ecoinvent data'!$D$5:$D$21242,0)) -> 1.8516121e-08 | ... P29: =INDEX('Ecoinvent data'!P$5:P$21242,MATCH($D29,'Ecoinvent data'!$D$5:$D$21242,0)) -> 74.594503
A30: metal working, average for steel product manufacturingRERmetal working, average for steel product manufacturingkg | B30: 14811 | C30: =INDEX('Ecoinvent data'!$B$5:$B$21242, MATCH('Selected processes'!D30,'Ecoinvent data'!$D$5:$D$21242,0)) -> 12485 | D30: 12485 | E30: =INDEX('Ecoinvent data'!E$5:E$21242,MATCH($D30,'Ecoinvent data'!$D$5:$D$21242,0)) -> metal working, average for steel product manufacturing | F30: =INDEX('Ecoinvent data'!F$5:F$21242,MATCH($D30,'Ecoinvent data'!$D$5:$D$21242,0)) -> RER | G30: =INDEX('Ecoinvent data'!G$5:G$21242,MATCH($D30,'Ecoinvent data'!$D$5:$D$21242,0)) -> metal working, average for steel product manufacturing | H30: =INDEX('Ecoinvent data'!H$5:H$21242,MATCH($D30,'Ecoinvent data'!$D$5:$D$21242,0)) -> kg | I30: =INDEX('Ecoinvent data'!I$5:I$21242,MATCH($D30,'Ecoinvent data'!$D$5:$D$21242,0)) -> 1 | J30: =INDEX('Ecoinvent data'!J$5:J$21242,MATCH($D30,'Ecoinvent data'!$D$5:$D$21242,0)) -> 1.65316 | K30: =INDEX('Ecoinvent data'!K$5:K$21242,MATCH($D30,'Ecoinvent data'!$D$5:$D$21242,0)) -> 3.143274 | L30: =INDEX('Ecoinvent data'!L$5:L$21242,MATCH($D30,'Ecoinvent data'!$D$5:$D$21242,0)) -> 7.2889071e-09 | ... P30: =INDEX('Ecoinvent data'!P$5:P$21242,MATCH($D30,'Ecoinvent data'!$D$5:$D$21242,0)) -> 57.931103
A31: market for polyurethane, rigid foamRoWpolyurethane, rigid foamkg | B31: 12134 | C31: =INDEX('Ecoinvent data'!$B$5:$B$21242, MATCH('Selected processes'!D31,'Ecoinvent data'!$D$5:$D$21242,0)) -> 14728 | D31: 14728 | E31: =INDEX('Ecoinvent data'!E$5:E$21242,MATCH($D31,'Ecoinvent data'!$D$5:$D$21242,0)) -> market for polyurethane, rigid foam | F31: =INDEX('Ecoinvent data'!F$5:F$21242,MATCH($D31,'Ecoinvent data'!$D$5:$D$21242,0)) -> RoW | G31: =INDEX('Ecoinvent data'!G$5:G$21242,MATCH($D31,'Ecoinvent data'!$D$5:$D$21242,0)) -> polyurethane, rigid foam | H31: =INDEX('Ecoinvent data'!H$5:H$21242,MATCH($D31,'Ecoinvent data'!$D$5:$D$21242,0)) -> kg | I31: =INDEX('Ecoinvent data'!I$5:I$21242,MATCH($D31,'Ecoinvent data'!$D$5:$D$21242,0)) -> 1 | J31: =INDEX('Ecoinvent data'!J$5:J$21242,MATCH($D31,'Ecoinvent data'!$D$5:$D$21242,0)) -> 5.9618436 | K31: =INDEX('Ecoinvent data'!K$5:K$21242,MATCH($D31,'Ecoinvent data'!$D$5:$D$21242,0)) -> 8.1927605 | L31: =INDEX('Ecoinvent data'!L$5:L$21242,MATCH($D31,'Ecoinvent data'!$D$5:$D$21242,0)) -> 2.6642159e-08 | ... P31: =INDEX('Ecoinvent data'!P$5:P$21242,MATCH($D31,'Ecoinvent data'!$D$5:$D$21242,0)) -> 39.108005
A32: market group for transport, freight trainRERtransport, freight trainmetric ton*km | B32: 14738 | C32: =INDEX('Ecoinvent data'!$B$5:$B$21242, MATCH('Selected processes'!D32,'Ecoinvent data'!$D$5:$D$21242,0)) -> 18124 | D32: 18124 | E32: =INDEX('Ecoinvent data'!E$5:E$21242,MATCH($D32,'Ecoinvent data'!$D$5:$D$21242,0)) -> market group for transport, freight train | F32: =INDEX('Ecoinvent data'!F$5:F$21242,MATCH($D32,'Ecoinvent data'!$D$5:$D$21242,0)) -> RER | G32: =INDEX('Ecoinvent data'!G$5:G$21242,MATCH($D32,'Ecoinvent data'!$D$5:$D$21242,0)) -> transport, freight train | H32: =INDEX('Ecoinvent data'!H$5:H$21242,MATCH($D32,'Ecoinvent data'!$D$5:$D$21242,0)) -> metric ton*km | I32: =INDEX('Ecoinvent data'!I$5:I$21242,MATCH($D32,'Ecoinvent data'!$D$5:$D$21242,0)) -> 1 | J32: =INDEX('Ecoinvent data'!J$5:J$21242,MATCH($D32,'Ecoinvent data'!$D$5:$D$21242,0)) -> 0.045728106 | K32: =INDEX('Ecoinvent data'!K$5:K$21242,MATCH($D32,'Ecoinvent data'!$D$5:$D$21242,0)) -> 0.068157807 | L32: =INDEX('Ecoinvent data'!L$5:L$21242,MATCH($D32,'Ecoinvent data'!$D$5:$D$21242,0)) -> 2.5241034e-10 | ... P32: =INDEX('Ecoinvent data'!P$5:P$21242,MATCH($D32,'Ecoinvent data'!$D$5:$D$21242,0)) -> 58.032086
A33: market for transport, freight, lorry 16-32 metric ton, EURO4RoWtransport, freight, lorry 16-32 metric ton, EURO4metric ton*km | B33: 13322 | C33: =INDEX('Ecoinvent data'!$B$5:$B$21242, MATCH('Selected processes'!D33,'Ecoinvent data'!$D$5:$D$21242,0)) -> 18241 | D33: 18241 | E33: =INDEX('Ecoinvent data'!E$5:E$21242,MATCH($D33,'Ecoinvent data'!$D$5:$D$21242,0)) -> market for transport, freight, lorry 16-32 metric ton, EURO4 | F33: =INDEX('Ecoinvent data'!F$5:F$21242,MATCH($D33,'Ecoinvent data'!$D$5:$D$21242,0)) -> RoW | G33: =INDEX('Ecoinvent data'!G$5:G$21242,MATCH($D33,'Ecoinvent data'!$D$5:$D$21242,0)) -> transport, freight, lorry 16-32 metric ton, EURO4 | H33: =INDEX('Ecoinvent data'!H$5:H$21242,MATCH($D33,'Ecoinvent data'!$D$5:$D$21242,0)) -> metric ton*km | I33: =INDEX('Ecoinvent data'!I$5:I$21242,MATCH($D33,'Ecoinvent data'!$D$5:$D$21242,0)) -> 1 | J33: =INDEX('Ecoinvent data'!J$5:J$21242,MATCH($D33,'Ecoinvent data'!$D$5:$D$21242,0)) -> 0.19079134 | K33: =INDEX('Ecoinvent data'!K$5:K$21242,MATCH($D33,'Ecoinvent data'!$D$5:$D$21242,0)) -> 0.20108682 | L33: =INDEX('Ecoinvent data'!L$5:L$21242,MATCH($D33,'Ecoinvent data'!$D$5:$D$21242,0)) -> 8.7787947e-10 | ... P33: =INDEX('Ecoinvent data'!P$5:P$21242,MATCH($D33,'Ecoinvent data'!$D$5:$D$21242,0)) -> 60.008519
A34: transport, freight, sea, container shipGLOtransport, freight, sea, container shipmetric ton*km | B34: 18150 | C34: =INDEX('Ecoinvent data'!$B$5:$B$21242, MATCH('Selected processes'!D34,'Ecoinvent data'!$D$5:$D$21242,0)) -> 18438 | D34: 18438 | E34: =INDEX('Ecoinvent data'!E$5:E$21242,MATCH($D34,'Ecoinvent data'!$D$5:$D$21242,0)) -> transport, freight, sea, container ship | F34: =INDEX('Ecoinvent data'!F$5:F$21242,MATCH($D34,'Ecoinvent data'!$D$5:$D$21242,0)) -> GLO | G34: =INDEX('Ecoinvent data'!G$5:G$21242,MATCH($D34,'Ecoinvent data'!$D$5:$D$21242,0)) -> transport, freight, sea, container ship | H34: =INDEX('Ecoinvent data'!H$5:H$21242,MATCH($D34,'Ecoinvent data'!$D$5:$D$21242,0)) -> metric ton*km | I34: =INDEX('Ecoinvent data'!I$5:I$21242,MATCH($D34,'Ecoinvent data'!$D$5:$D$21242,0)) -> 1 | J34: =INDEX('Ecoinvent data'!J$5:J$21242,MATCH($D34,'Ecoinvent data'!$D$5:$D$21242,0)) -> 0.010163513 | K34: =INDEX('Ecoinvent data'!K$5:K$21242,MATCH($D34,'Ecoinvent data'!$D$5:$D$21242,0)) -> 0.026445888 | L34: =INDEX('Ecoinvent data'!L$5:L$21242,MATCH($D34,'Ecoinvent data'!$D$5:$D$21242,0)) -> 9.6094188e-11 | ... P34: =INDEX('Ecoinvent data'!P$5:P$21242,MATCH($D34,'Ecoinvent data'!$D$5:$D$21242,0)) -> 69.871717
A35: treatment of waste emulsion paint, municipal incinerationCHwaste emulsion paintkg | B35: 20016 | C35: =INDEX('Ecoinvent data'!$B$5:$B$21242, MATCH('Selected processes'!D35,'Ecoinvent data'!$D$5:$D$21242,0)) -> 19437 | D35: 19437 | E35: =INDEX('Ecoinvent data'!E$5:E$21242,MATCH($D35,'Ecoinvent data'!$D$5:$D$21242,0)) -> treatment of waste emulsion paint, municipal incineration | F35: =INDEX('Ecoinvent data'!F$5:F$21242,MATCH($D35,'Ecoinvent data'!$D$5:$D$21242,0)) -> CH | G35: =INDEX('Ecoinvent data'!G$5:G$21242,MATCH($D35,'Ecoinvent data'!$D$5:$D$21242,0)) -> waste emulsion paint | H35: =INDEX('Ecoinvent data'!H$5:H$21242,MATCH($D35,'Ecoinvent data'!$D$5:$D$21242,0)) -> kg | I35: =INDEX('Ecoinvent data'!I$5:I$21242,MATCH($D35,'Ecoinvent data'!$D$5:$D$21242,0)) -> -1 | J35: =INDEX('Ecoinvent data'!J$5:J$21242,MATCH($D35,'Ecoinvent data'!$D$5:$D$21242,0)) -> 1.125218 | K35: =INDEX('Ecoinvent data'!K$5:K$21242,MATCH($D35,'Ecoinvent data'!$D$5:$D$21242,0)) -> 0.70035581 | L35: =INDEX('Ecoinvent data'!L$5:L$21242,MATCH($D35,'Ecoinvent data'!$D$5:$D$21242,0)) -> 3.4690559e-09 | ... P35: =INDEX('Ecoinvent data'!P$5:P$21242,MATCH($D35,'Ecoinvent data'!$D$5:$D$21242,0)) -> 597.31449
A36: treatment of waste glass, municipal incinerationCHwaste glasskg | B36: 20053 | C36: =INDEX('Ecoinvent data'!$B$5:$B$21242, MATCH('Selected processes'!D36,'Ecoinvent data'!$D$5:$D$21242,0)) -> 19516 | D36: 19516 | E36: =INDEX('Ecoinvent data'!E$5:E$21242,MATCH($D36,'Ecoinvent data'!$D$5:$D$21242,0)) -> treatment of waste glass, municipal incineration | F36: =INDEX('Ecoinvent data'!F$5:F$21242,MATCH($D36,'Ecoinvent data'!$D$5:$D$21242,0)) -> CH | G36: =INDEX('Ecoinvent data'!G$5:G$21242,MATCH($D36,'Ecoinvent data'!$D$5:$D$21242,0)) -> waste glass | H36: =INDEX('Ecoinvent data'!H$5:H$21242,MATCH($D36,'Ecoinvent data'!$D$5:$D$21242,0)) -> kg | I36: =INDEX('Ecoinvent data'!I$5:I$21242,MATCH($D36,'Ecoinvent data'!$D$5:$D$21242,0)) -> -1 | J36: =INDEX('Ecoinvent data'!J$5:J$21242,MATCH($D36,'Ecoinvent data'!$D$5:$D$21242,0)) -> 0.014449819 | K36: =INDEX('Ecoinvent data'!K$5:K$21242,MATCH($D36,'Ecoinvent data'!$D$5:$D$21242,0)) -> 0.068567532 | L36: =INDEX('Ecoinvent data'!L$5:L$21242,MATCH($D36,'Ecoinvent data'!$D$5:$D$21242,0)) -> 1.5282403e-10 | ... P36: =INDEX('Ecoinvent data'!P$5:P$21242,MATCH($D36,'Ecoinvent data'!$D$5:$D$21242,0)) -> 41.124391
A37: treatment of waste plastic, mixture, municipal incinerationCHwaste plastic, mixturekg | B37: 20237 | C37: =INDEX('Ecoinvent data'!$B$5:$B$21242, MATCH('Selected processes'!D37,'Ecoinvent data'!$D$5:$D$21242,0)) -> 19923 | D37: 19923 | E37: =INDEX('Ecoinvent data'!E$5:E$21242,MATCH($D37,'Ecoinvent data'!$D$5:$D$21242,0)) -> treatment of waste plastic, mixture, municipal incineration | F37: =INDEX('Ecoinvent data'!F$5:F$21242,MATCH($D37,'Ecoinvent data'!$D$5:$D$21242,0)) -> CH | G37: =INDEX('Ecoinvent data'!G$5:G$21242,MATCH($D37,'Ecoinvent data'!$D$5:$D$21242,0)) -> waste plastic, mixture | H37: =INDEX('Ecoinvent data'!H$5:H$21242,MATCH($D37,'Ecoinvent data'!$D$5:$D$21242,0)) -> kg | I37: =INDEX('Ecoinvent data'!I$5:I$21242,MATCH($D37,'Ecoinvent data'!$D$5:$D$21242,0)) -> -1 | J37: =INDEX('Ecoinvent data'!J$5:J$21242,MATCH($D37,'Ecoinvent data'!$D$5:$D$21242,0)) -> 2.3457342 | K37: =INDEX('Ecoinvent data'!K$5:K$21242,MATCH($D37,'Ecoinvent data'!$D$5:$D$21242,0)) -> 1.3115341 | L37: =INDEX('Ecoinvent data'!L$5:L$21242,MATCH($D37,'Ecoinvent data'!$D$5:$D$21242,0)) -> 6.7933555e-09 | ... P37: =INDEX('Ecoinvent data'!P$5:P$21242,MATCH($D37,'Ecoinvent data'!$D$5:$D$21242,0)) -> 4791.4643
... A49: electricity production, hard coalRoWelectricity, high voltagekWh | B49: 2476 | C49: =INDEX('Ecoinvent data'!$B$5:$B$21242, MATCH('Selected processes'!D49,'Ecoinvent data'!$D$5:$D$21242,0)) -> 3591 | D49: 3591 | E49: =INDEX('Ecoinvent data'!E$5:E$21242,MATCH($D49,'Ecoinvent data'!$D$5:$D$21242,0)) -> electricity production, hard coal | F49: =INDEX('Ecoinvent data'!F$5:F$21242,MATCH($D49,'Ecoinvent data'!$D$5:$D$21242,0)) -> RoW | G49: =INDEX('Ecoinvent data'!G$5:G$21242,MATCH($D49,'Ecoinvent data'!$D$5:$D$21242,0)) -> electricity, high voltage | H49: =INDEX('Ecoinvent data'!H$5:H$21242,MATCH($D49,'Ecoinvent data'!$D$5:$D$21242,0)) -> kWh | I49: =INDEX('Ecoinvent data'!I$5:I$21242,MATCH($D49,'Ecoinvent data'!$D$5:$D$21242,0)) -> 1 | J49: =INDEX('Ecoinvent data'!J$5:J$21242,MATCH($D49,'Ecoinvent data'!$D$5:$D$21242,0)) -> 1.0955326 | K49: =INDEX('Ecoinvent data'!K$5:K$21242,MATCH($D49,'Ecoinvent data'!$D$5:$D$21242,0)) -> 1.6507311 | L49: =INDEX('Ecoinvent data'!L$5:L$21242,MATCH($D49,'Ecoinvent data'!$D$5:$D$21242,0)) -> 5.7761989e-09 | ... P49: =INDEX('Ecoinvent data'!P$5:P$21242,MATCH($D49,'Ecoinvent data'!$D$5:$D$21242,0)) -> 90.129093
B50: 13169 | C50: =INDEX('Ecoinvent data'!$B$5:$B$21242, MATCH('Selected processes'!D50,'Ecoinvent data'!$D$5:$D$21242,0)) -> 17718 | D50: 17718 | E50: =INDEX('Ecoinvent data'!E$5:E$21242,MATCH($D50,'Ecoinvent data'!$D$5:$D$21242,0)) -> market for synthetic rubber | F50: =INDEX('Ecoinvent data'!F$5:F$21242,MATCH($D50,'Ecoinvent data'!$D$5:$D$21242,0)) -> GLO | G50: =INDEX('Ecoinvent data'!G$5:G$21242,MATCH($D50,'Ecoinvent data'!$D$5:$D$21242,0)) -> synthetic rubber | H50: =INDEX('Ecoinvent data'!H$5:H$21242,MATCH($D50,'Ecoinvent data'!$D$5:$D$21242,0)) -> kg | I50: =INDEX('Ecoinvent data'!I$5:I$21242,MATCH($D50,'Ecoinvent data'!$D$5:$D$21242,0)) -> 1 | J50: =INDEX('Ecoinvent data'!J$5:J$21242,MATCH($D50,'Ecoinvent data'!$D$5:$D$21242,0)) -> 2.9677534 | K50: =INDEX('Ecoinvent data'!K$5:K$21242,MATCH($D50,'Ecoinvent data'!$D$5:$D$21242,0)) -> 3.7317246 | L50: =INDEX('Ecoinvent data'!L$5:L$21242,MATCH($D50,'Ecoinvent data'!$D$5:$D$21242,0)) -> 1.3250334e-08 | ... P50: =INDEX('Ecoinvent data'!P$5:P$21242,MATCH($D50,'Ecoinvent data'!$D$5:$D$21242,0)) -> 28.973791
B51: 10194 | C51: =INDEX('Ecoinvent data'!$B$5:$B$21242, MATCH('Selected processes'!D51,'Ecoinvent data'!$D$5:$D$21242,0)) -> 7943 | D51: 7943 | E51: =INDEX('Ecoinvent data'!E$5:E$21242,MATCH($D51,'Ecoinvent data'!$D$5:$D$21242,0)) -> market for flat glass, uncoated | F51: =INDEX('Ecoinvent data'!F$5:F$21242,MATCH($D51,'Ecoinvent data'!$D$5:$D$21242,0)) -> RoW | G51: =INDEX('Ecoinvent data'!G$5:G$21242,MATCH($D51,'Ecoinvent data'!$D$5:$D$21242,0)) -> flat glass, uncoated | H51: =INDEX('Ecoinvent data'!H$5:H$21242,MATCH($D51,'Ecoinvent data'!$D$5:$D$21242,0)) -> kg | I51: =INDEX('Ecoinvent data'!I$5:I$21242,MATCH($D51,'Ecoinvent data'!$D$5:$D$21242,0)) -> 1 | J51: =INDEX('Ecoinvent data'!J$5:J$21242,MATCH($D51,'Ecoinvent data'!$D$5:$D$21242,0)) -> 1.0559546 | K51: =INDEX('Ecoinvent data'!K$5:K$21242,MATCH($D51,'Ecoinvent data'!$D$5:$D$21242,0)) -> 1.4484757 | L51: =INDEX('Ecoinvent data'!L$5:L$21242,MATCH($D51,'Ecoinvent data'!$D$5:$D$21242,0)) -> 5.395704e-09 | ... P51: =INDEX('Ecoinvent data'!P$5:P$21242,MATCH($D51,'Ecoinvent data'!$D$5:$D$21242,0)) -> 81.710726
B52: 5242 | C52: =INDEX('Ecoinvent data'!$B$5:$B$21242, MATCH('Selected processes'!D52,'Ecoinvent data'!$D$5:$D$21242,0)) -> 18715 | D52: 18715 | E52: =INDEX('Ecoinvent data'!E$5:E$21242,MATCH($D52,'Ecoinvent data'!$D$5:$D$21242,0)) -> ethylene glycol production | F52: =INDEX('Ecoinvent data'!F$5:F$21242,MATCH($D52,'Ecoinvent data'!$D$5:$D$21242,0)) -> RoW | G52: =INDEX('Ecoinvent data'!G$5:G$21242,MATCH($D52,'Ecoinvent data'!$D$5:$D$21242,0)) -> triethylene glycol | H52: =INDEX('Ecoinvent data'!H$5:H$21242,MATCH($D52,'Ecoinvent data'!$D$5:$D$21242,0)) -> kg | I52: =INDEX('Ecoinvent data'!I$5:I$21242,MATCH($D52,'Ecoinvent data'!$D$5:$D$21242,0)) -> 1 | J52: =INDEX('Ecoinvent data'!J$5:J$21242,MATCH($D52,'Ecoinvent data'!$D$5:$D$21242,0)) -> 2.4545635 | K52: =INDEX('Ecoinvent data'!K$5:K$21242,MATCH($D52,'Ecoinvent data'!$D$5:$D$21242,0)) -> 2.789618 | L52: =INDEX('Ecoinvent data'!L$5:L$21242,MATCH($D52,'Ecoinvent data'!$D$5:$D$21242,0)) -> 1.0096246e-08 | ... P52: =INDEX('Ecoinvent data'!P$5:P$21242,MATCH($D52,'Ecoinvent data'!$D$5:$D$21242,0)) -> 32.166575
B53: 763 | C53: =INDEX('Ecoinvent data'!$B$5:$B$21242, MATCH('Selected processes'!D53,'Ecoinvent data'!$D$5:$D$21242,0)) -> 1066 | D53: 1066 | E53: =INDEX('Ecoinvent data'!E$5:E$21242,MATCH($D53,'Ecoinvent data'!$D$5:$D$21242,0)) -> bicycle production | F53: =INDEX('Ecoinvent data'!F$5:F$21242,MATCH($D53,'Ecoinvent data'!$D$5:$D$21242,0)) -> RER | G53: =INDEX('Ecoinvent data'!G$5:G$21242,MATCH($D53,'Ecoinvent data'!$D$5:$D$21242,0)) -> bicycle | H53: =INDEX('Ecoinvent data'!H$5:H$21242,MATCH($D53,'Ecoinvent data'!$D$5:$D$21242,0)) -> unit | I53: =INDEX('Ecoinvent data'!I$5:I$21242,MATCH($D53,'Ecoinvent data'!$D$5:$D$21242,0)) -> 1 | J53: =INDEX('Ecoinvent data'!J$5:J$21242,MATCH($D53,'Ecoinvent data'!$D$5:$D$21242,0)) -> 145.40026 | K53: =INDEX('Ecoinvent data'!K$5:K$21242,MATCH($D53,'Ecoinvent data'!$D$5:$D$21242,0)) -> 343.6029 | L53: =INDEX('Ecoinvent data'!L$5:L$21242,MATCH($D53,'Ecoinvent data'!$D$5:$D$21242,0)) -> 6.755806e-07 | ... P53: =INDEX('Ecoinvent data'!P$5:P$21242,MATCH($D53,'Ecoinvent data'!$D$5:$D$21242,0)) -> 72.666443
B54: 12858 | C54: =INDEX('Ecoinvent data'!$B$5:$B$21242, MATCH('Selected processes'!D54,'Ecoinvent data'!$D$5:$D$21242,0)) -> 16717 | D54: 16717 | E54: =INDEX('Ecoinvent data'!E$5:E$21242,MATCH($D54,'Ecoinvent data'!$D$5:$D$21242,0)) -> market for skimmed milk, from cow milk | F54: =INDEX('Ecoinvent data'!F$5:F$21242,MATCH($D54,'Ecoinvent data'!$D$5:$D$21242,0)) -> GLO | G54: =INDEX('Ecoinvent data'!G$5:G$21242,MATCH($D54,'Ecoinvent data'!$D$5:$D$21242,0)) -> skimmed milk, from cow milk | H54: =INDEX('Ecoinvent data'!H$5:H$21242,MATCH($D54,'Ecoinvent data'!$D$5:$D$21242,0)) -> kg | I54: =INDEX('Ecoinvent data'!I$5:I$21242,MATCH($D54,'Ecoinvent data'!$D$5:$D$21242,0)) -> 1 | J54: =INDEX('Ecoinvent data'!J$5:J$21242,MATCH($D54,'Ecoinvent data'!$D$5:$D$21242,0)) -> 1.0414387 | K54: =INDEX('Ecoinvent data'!K$5:K$21242,MATCH($D54,'Ecoinvent data'!$D$5:$D$21242,0)) -> 1.2896236 | L54: =INDEX('Ecoinvent data'!L$5:L$21242,MATCH($D54,'Ecoinvent data'!$D$5:$D$21242,0)) -> 5.1858481e-08 | ... P54: =INDEX('Ecoinvent data'!P$5:P$21242,MATCH($D54,'Ecoinvent data'!$D$5:$D$21242,0)) -> 87.242986
D55: 6611 | E55: =INDEX('Ecoinvent data'!E$5:E$21242,MATCH($D55,'Ecoinvent data'!$D$5:$D$21242,0)) -> market for electricity, low voltage | F55: =INDEX('Ecoinvent data'!F$5:F$21242,MATCH($D55,'Ecoinvent data'!$D$5:$D$21242,0)) -> DK | G55: =INDEX('Ecoinvent data'!G$5:G$21242,MATCH($D55,'Ecoinvent data'!$D$5:$D$21242,0)) -> electricity, low voltage | H55: =INDEX('Ecoinvent data'!H$5:H$21242,MATCH($D55,'Ecoinvent data'!$D$5:$D$21242,0)) -> kWh | I55: =INDEX('Ecoinvent data'!I$5:I$21242,MATCH($D55,'Ecoinvent data'!$D$5:$D$21242,0)) -> 1 | J55: =INDEX('Ecoinvent data'!J$5:J$21242,MATCH($D55,'Ecoinvent data'!$D$5:$D$21242,0)) -> 0.21996088 | K55: =INDEX('Ecoinvent data'!K$5:K$21242,MATCH($D55,'Ecoinvent data'!$D$5:$D$21242,0)) -> 0.30005943 | L55: =INDEX('Ecoinvent data'!L$5:L$21242,MATCH($D55,'Ecoinvent data'!$D$5:$D$21242,0)) -> 1.422833e-09 | ... P55: =INDEX('Ecoinvent data'!P$5:P$21242,MATCH($D55,'Ecoinvent data'!$D$5:$D$21242,0)) -> 51.622323
E56: =INDEX('Ecoinvent data'!E$5:E$21242,MATCH($D56,'Ecoinvent data'!$D$5:$D$21242,0)) -> #N/A | F56: =INDEX('Ecoinvent data'!F$5:F$21242,MATCH($D56,'Ecoinvent data'!$D$5:$D$21242,0)) -> #N/A | G56: =INDEX('Ecoinvent data'!G$5:G$21242,MATCH($D56,'Ecoinvent data'!$D$5:$D$21242,0)) -> #N/A | H56: =INDEX('Ecoinvent data'!H$5:H$21242,MATCH($D56,'Ecoinvent data'!$D$5:$D$21242,0)) -> #N/A | I56: =INDEX('Ecoinvent data'!I$5:I$21242,MATCH($D56,'Ecoinvent data'!$D$5:$D$21242,0)) -> #N/A | J56: =INDEX('Ecoinvent data'!J$5:J$21242,MATCH($D56,'Ecoinvent data'!$D$5:$D$21242,0)) -> #N/A | K56: =INDEX('Ecoinvent data'!K$5:K$21242,MATCH($D56,'Ecoinvent data'!$D$5:$D$21242,0)) -> #N/A | L56: =INDEX('Ecoinvent data'!L$5:L$21242,MATCH($D56,'Ecoinvent data'!$D$5:$D$21242,0)) -> #N/A | ... P56: =INDEX('Ecoinvent data'!P$5:P$21242,MATCH($D56,'Ecoinvent data'!$D$5:$D$21242,0)) -> #N/A
E57: =INDEX('Ecoinvent data'!E$5:E$21242,MATCH($D57,'Ecoinvent data'!$D$5:$D$21242,0)) -> #N/A | F57: =INDEX('Ecoinvent data'!F$5:F$21242,MATCH($D57,'Ecoinvent data'!$D$5:$D$21242,0)) -> #N/A | G57: =INDEX('Ecoinvent data'!G$5:G$21242,MATCH($D57,'Ecoinvent data'!$D$5:$D$21242,0)) -> #N/A | H57: =INDEX('Ecoinvent data'!H$5:H$21242,MATCH($D57,'Ecoinvent data'!$D$5:$D$21242,0)) -> #N/A | I57: =INDEX('Ecoinvent data'!I$5:I$21242,MATCH($D57,'Ecoinvent data'!$D$5:$D$21242,0)) -> #N/A | J57: =INDEX('Ecoinvent data'!J$5:J$21242,MATCH($D57,'Ecoinvent data'!$D$5:$D$21242,0)) -> #N/A | K57: =INDEX('Ecoinvent data'!K$5:K$21242,MATCH($D57,'Ecoinvent data'!$D$5:$D$21242,0)) -> #N/A | L57: =INDEX('Ecoinvent data'!L$5:L$21242,MATCH($D57,'Ecoinvent data'!$D$5:$D$21242,0)) -> #N/A | ... P57: =INDEX('Ecoinvent data'!P$5:P$21242,MATCH($D57,'Ecoinvent data'!$D$5:$D$21242,0)) -> #N/A
E58: =INDEX('Ecoinvent data'!E$5:E$21242,MATCH($D58,'Ecoinvent data'!$D$5:$D$21242,0)) -> #N/A | F58: =INDEX('Ecoinvent data'!F$5:F$21242,MATCH($D58,'Ecoinvent data'!$D$5:$D$21242,0)) -> #N/A | G58: =INDEX('Ecoinvent data'!G$5:G$21242,MATCH($D58,'Ecoinvent data'!$D$5:$D$21242,0)) -> #N/A | H58: =INDEX('Ecoinvent data'!H$5:H$21242,MATCH($D58,'Ecoinvent data'!$D$5:$D$21242,0)) -> #N/A | I58: =INDEX('Ecoinvent data'!I$5:I$21242,MATCH($D58,'Ecoinvent data'!$D$5:$D$21242,0)) -> #N/A | J58: =INDEX('Ecoinvent data'!J$5:J$21242,MATCH($D58,'Ecoinvent data'!$D$5:$D$21242,0)) -> #N/A | K58: =INDEX('Ecoinvent data'!K$5:K$21242,MATCH($D58,'Ecoinvent data'!$D$5:$D$21242,0)) -> #N/A | L58: =INDEX('Ecoinvent data'!L$5:L$21242,MATCH($D58,'Ecoinvent data'!$D$5:$D$21242,0)) -> #N/A | ... P58: =INDEX('Ecoinvent data'!P$5:P$21242,MATCH($D58,'Ecoinvent data'!$D$5:$D$21242,0)) -> #N/A
E59: =INDEX('Ecoinvent data'!E$5:E$21242,MATCH($D59,'Ecoinvent data'!$D$5:$D$21242,0)) -> #N/A | F59: =INDEX('Ecoinvent data'!F$5:F$21242,MATCH($D59,'Ecoinvent data'!$D$5:$D$21242,0)) -> #N/A | G59: =INDEX('Ecoinvent data'!G$5:G$21242,MATCH($D59,'Ecoinvent data'!$D$5:$D$21242,0)) -> #N/A | H59: =INDEX('Ecoinvent data'!H$5:H$21242,MATCH($D59,'Ecoinvent data'!$D$5:$D$21242,0)) -> #N/A | I59: =INDEX('Ecoinvent data'!I$5:I$21242,MATCH($D59,'Ecoinvent data'!$D$5:$D$21242,0)) -> #N/A | J59: =INDEX('Ecoinvent data'!J$5:J$21242,MATCH($D59,'Ecoinvent data'!$D$5:$D$21242,0)) -> #N/A | K59: =INDEX('Ecoinvent data'!K$5:K$21242,MATCH($D59,'Ecoinvent data'!$D$5:$D$21242,0)) -> #N/A | L59: =INDEX('Ecoinvent data'!L$5:L$21242,MATCH($D59,'Ecoinvent data'!$D$5:$D$21242,0)) -> #N/A | ... P59: =INDEX('Ecoinvent data'!P$5:P$21242,MATCH($D59,'Ecoinvent data'!$D$5:$D$21242,0)) -> #N/A
E60: =INDEX('Ecoinvent data'!E$5:E$21242,MATCH($D60,'Ecoinvent data'!$D$5:$D$21242,0)) -> #N/A | F60: =INDEX('Ecoinvent data'!F$5:F$21242,MATCH($D60,'Ecoinvent data'!$D$5:$D$21242,0)) -> #N/A | G60: =INDEX('Ecoinvent data'!G$5:G$21242,MATCH($D60,'Ecoinvent data'!$D$5:$D$21242,0)) -> #N/A | H60: =INDEX('Ecoinvent data'!H$5:H$21242,MATCH($D60,'Ecoinvent data'!$D$5:$D$21242,0)) -> #N/A | I60: =INDEX('Ecoinvent data'!I$5:I$21242,MATCH($D60,'Ecoinvent data'!$D$5:$D$21242,0)) -> #N/A | J60: =INDEX('Ecoinvent data'!J$5:J$21242,MATCH($D60,'Ecoinvent data'!$D$5:$D$21242,0)) -> #N/A | K60: =INDEX('Ecoinvent data'!K$5:K$21242,MATCH($D60,'Ecoinvent data'!$D$5:$D$21242,0)) -> #N/A | L60: =INDEX('Ecoinvent data'!L$5:L$21242,MATCH($D60,'Ecoinvent data'!$D$5:$D$21242,0)) -> #N/A | ... P60: =INDEX('Ecoinvent data'!P$5:P$21242,MATCH($D60,'Ecoinvent data'!$D$5:$D$21242,0)) -> #N/A
E61: =INDEX('Ecoinvent data'!E$5:E$21242,MATCH($D61,'Ecoinvent data'!$D$5:$D$21242,0)) -> #N/A | F61: =INDEX('Ecoinvent data'!F$5:F$21242,MATCH($D61,'Ecoinvent data'!$D$5:$D$21242,0)) -> #N/A | G61: =INDEX('Ecoinvent data'!G$5:G$21242,MATCH($D61,'Ecoinvent data'!$D$5:$D$21242,0)) -> #N/A | H61: =INDEX('Ecoinvent data'!H$5:H$21242,MATCH($D61,'Ecoinvent data'!$D$5:$D$21242,0)) -> #N/A | I61: =INDEX('Ecoinvent data'!I$5:I$21242,MATCH($D61,'Ecoinvent data'!$D$5:$D$21242,0)) -> #N/A | J61: =INDEX('Ecoinvent data'!J$5:J$21242,MATCH($D61,'Ecoinvent data'!$D$5:$D$21242,0)) -> #N/A | K61: =INDEX('Ecoinvent data'!K$5:K$21242,MATCH($D61,'Ecoinvent data'!$D$5:$D$21242,0)) -> #N/A | L61: =INDEX('Ecoinvent data'!L$5:L$21242,MATCH($D61,'Ecoinvent data'!$D$5:$D$21242,0)) -> #N/A | ... P61: =INDEX('Ecoinvent data'!P$5:P$21242,MATCH($D61,'Ecoinvent data'!$D$5:$D$21242,0)) -> #N/A
E62: =INDEX('Ecoinvent data'!E$5:E$21242,MATCH($D62,'Ecoinvent data'!$D$5:$D$21242,0)) -> #N/A | F62: =INDEX('Ecoinvent data'!F$5:F$21242,MATCH($D62,'Ecoinvent data'!$D$5:$D$21242,0)) -> #N/A | G62: =INDEX('Ecoinvent data'!G$5:G$21242,MATCH($D62,'Ecoinvent data'!$D$5:$D$21242,0)) -> #N/A | H62: =INDEX('Ecoinvent data'!H$5:H$21242,MATCH($D62,'Ecoinvent data'!$D$5:$D$21242,0)) -> #N/A | I62: =INDEX('Ecoinvent data'!I$5:I$21242,MATCH($D62,'Ecoinvent data'!$D$5:$D$21242,0)) -> #N/A | J62: =INDEX('Ecoinvent data'!J$5:J$21242,MATCH($D62,'Ecoinvent data'!$D$5:$D$21242,0)) -> #N/A | K62: =INDEX('Ecoinvent data'!K$5:K$21242,MATCH($D62,'Ecoinvent data'!$D$5:$D$21242,0)) -> #N/A | L62: =INDEX('Ecoinvent data'!L$5:L$21242,MATCH($D62,'Ecoinvent data'!$D$5:$D$21242,0)) -> #N/A | ... P62: =INDEX('Ecoinvent data'!P$5:P$21242,MATCH($D62,'Ecoinvent data'!$D$5:$D$21242,0)) -> #N/A
E63: =INDEX('Ecoinvent data'!E$5:E$21242,MATCH($D63,'Ecoinvent data'!$D$5:$D$21242,0)) -> #N/A | F63: =INDEX('Ecoinvent data'!F$5:F$21242,MATCH($D63,'Ecoinvent data'!$D$5:$D$21242,0)) -> #N/A | G63: =INDEX('Ecoinvent data'!G$5:G$21242,MATCH($D63,'Ecoinvent data'!$D$5:$D$21242,0)) -> #N/A | H63: =INDEX('Ecoinvent data'!H$5:H$21242,MATCH($D63,'Ecoinvent data'!$D$5:$D$21242,0)) -> #N/A | I63: =INDEX('Ecoinvent data'!I$5:I$21242,MATCH($D63,'Ecoinvent data'!$D$5:$D$21242,0)) -> #N/A | J63: =INDEX('Ecoinvent data'!J$5:J$21242,MATCH($D63,'Ecoinvent data'!$D$5:$D$21242,0)) -> #N/A | K63: =INDEX('Ecoinvent data'!K$5:K$21242,MATCH($D63,'Ecoinvent data'!$D$5:$D$21242,0)) -> #N/A | L63: =INDEX('Ecoinvent data'!L$5:L$21242,MATCH($D63,'Ecoinvent data'!$D$5:$D$21242,0)) -> #N/A | ... P63: =INDEX('Ecoinvent data'!P$5:P$21242,MATCH($D63,'Ecoinvent data'!$D$5:$D$21242,0)) -> #N/A
E64: =INDEX('Ecoinvent data'!E$5:E$21242,MATCH($D64,'Ecoinvent data'!$D$5:$D$21242,0)) -> #N/A | F64: =INDEX('Ecoinvent data'!F$5:F$21242,MATCH($D64,'Ecoinvent data'!$D$5:$D$21242,0)) -> #N/A | G64: =INDEX('Ecoinvent data'!G$5:G$21242,MATCH($D64,'Ecoinvent data'!$D$5:$D$21242,0)) -> #N/A | H64: =INDEX('Ecoinvent data'!H$5:H$21242,MATCH($D64,'Ecoinvent data'!$D$5:$D$21242,0)) -> #N/A | I64: =INDEX('Ecoinvent data'!I$5:I$21242,MATCH($D64,'Ecoinvent data'!$D$5:$D$21242,0)) -> #N/A | J64: =INDEX('Ecoinvent data'!J$5:J$21242,MATCH($D64,'Ecoinvent data'!$D$5:$D$21242,0)) -> #N/A | K64: =INDEX('Ecoinvent data'!K$5:K$21242,MATCH($D64,'Ecoinvent data'!$D$5:$D$21242,0)) -> #N/A | L64: =INDEX('Ecoinvent data'!L$5:L$21242,MATCH($D64,'Ecoinvent data'!$D$5:$D$21242,0)) -> #N/A | ... P64: =INDEX('Ecoinvent data'!P$5:P$21242,MATCH($D64,'Ecoinvent data'!$D$5:$D$21242,0)) -> #N/A
E65: =INDEX('Ecoinvent data'!E$5:E$21242,MATCH($D65,'Ecoinvent data'!$D$5:$D$21242,0)) -> #N/A | F65: =INDEX('Ecoinvent data'!F$5:F$21242,MATCH($D65,'Ecoinvent data'!$D$5:$D$21242,0)) -> #N/A | G65: =INDEX('Ecoinvent data'!G$5:G$21242,MATCH($D65,'Ecoinvent data'!$D$5:$D$21242,0)) -> #N/A | H65: =INDEX('Ecoinvent data'!H$5:H$21242,MATCH($D65,'Ecoinvent data'!$D$5:$D$21242,0)) -> #N/A | I65: =INDEX('Ecoinvent data'!I$5:I$21242,MATCH($D65,'Ecoinvent data'!$D$5:$D$21242,0)) -> #N/A | J65: =INDEX('Ecoinvent data'!J$5:J$21242,MATCH($D65,'Ecoinvent data'!$D$5:$D$21242,0)) -> #N/A | K65: =INDEX('Ecoinvent data'!K$5:K$21242,MATCH($D65,'Ecoinvent data'!$D$5:$D$21242,0)) -> #N/A | L65: =INDEX('Ecoinvent data'!L$5:L$21242,MATCH($D65,'Ecoinvent data'!$D$5:$D$21242,0)) -> #N/A | ... P65: =INDEX('Ecoinvent data'!P$5:P$21242,MATCH($D65,'Ecoinvent data'!$D$5:$D$21242,0)) -> #N/A
E66: =INDEX('Ecoinvent data'!E$5:E$21242,MATCH($D66,'Ecoinvent data'!$D$5:$D$21242,0)) -> #N/A | F66: =INDEX('Ecoinvent data'!F$5:F$21242,MATCH($D66,'Ecoinvent data'!$D$5:$D$21242,0)) -> #N/A | G66: =INDEX('Ecoinvent data'!G$5:G$21242,MATCH($D66,'Ecoinvent data'!$D$5:$D$21242,0)) -> #N/A | H66: =INDEX('Ecoinvent data'!H$5:H$21242,MATCH($D66,'Ecoinvent data'!$D$5:$D$21242,0)) -> #N/A | I66: =INDEX('Ecoinvent data'!I$5:I$21242,MATCH($D66,'Ecoinvent data'!$D$5:$D$21242,0)) -> #N/A | J66: =INDEX('Ecoinvent data'!J$5:J$21242,MATCH($D66,'Ecoinvent data'!$D$5:$D$21242,0)) -> #N/A | K66: =INDEX('Ecoinvent data'!K$5:K$21242,MATCH($D66,'Ecoinvent data'!$D$5:$D$21242,0)) -> #N/A | L66: =INDEX('Ecoinvent data'!L$5:L$21242,MATCH($D66,'Ecoinvent data'!$D$5:$D$21242,0)) -> #N/A | ... P66: =INDEX('Ecoinvent data'!P$5:P$21242,MATCH($D66,'Ecoinvent data'!$D$5:$D$21242,0)) -> #N/A
E67: =INDEX('Ecoinvent data'!E$5:E$21242,MATCH($D67,'Ecoinvent data'!$D$5:$D$21242,0)) -> #N/A | F67: =INDEX('Ecoinvent data'!F$5:F$21242,MATCH($D67,'Ecoinvent data'!$D$5:$D$21242,0)) -> #N/A | G67: =INDEX('Ecoinvent data'!G$5:G$21242,MATCH($D67,'Ecoinvent data'!$D$5:$D$21242,0)) -> #N/A | H67: =INDEX('Ecoinvent data'!H$5:H$21242,MATCH($D67,'Ecoinvent data'!$D$5:$D$21242,0)) -> #N/A | I67: =INDEX('Ecoinvent data'!I$5:I$21242,MATCH($D67,'Ecoinvent data'!$D$5:$D$21242,0)) -> #N/A | J67: =INDEX('Ecoinvent data'!J$5:J$21242,MATCH($D67,'Ecoinvent data'!$D$5:$D$21242,0)) -> #N/A | K67: =INDEX('Ecoinvent data'!K$5:K$21242,MATCH($D67,'Ecoinvent data'!$D$5:$D$21242,0)) -> #N/A | L67: =INDEX('Ecoinvent data'!L$5:L$21242,MATCH($D67,'Ecoinvent data'!$D$5:$D$21242,0)) -> #N/A | ... P67: =INDEX('Ecoinvent data'!P$5:P$21242,MATCH($D67,'Ecoinvent data'!$D$5:$D$21242,0)) -> #N/A
B68: 100004 | D68: 100004 | E68: Biking gain in health average, conventional bike | F68: bicycling average | H68: km | K68: =-'Physical exercise data'!G17 -> -9.3263497 | P68: =INDEX('Ecoinvent data'!P$5:P$21242,MATCH($D68,'Ecoinvent data'!$D$5:$D$21242,0)) -> #N/A
B69: 100003 | D69: 100003 | E69: Biking gain in health, electric bike | F69: e.biking | H69: km | K69: =-'Physical exercise data'!G18 -> -6.2175665
B70: 100002 | D70: 100002 | E70: Driving a car | F70: driving an automobile | H70: km | K70: =-'Physical exercise data'!G19 -> -0.72627994
B71: 100001 | D71: 100001 | E71: Emissions & operation of vehicle | F71: RER | G71: transport, passenger car, medium size, petrol, EURO 4 | H71: kg petrol | I71: 1 | J71: =0.2024/0.065*1.1 -> 3.4252308 | K71: =M74 -> 4.5694635 | L71: =N74 -> 1.7432418e-08 | M71: 0 | N71: 0 | O71: =J71/1.1 -> 3.1138462
K73: Fuel consumption | L73: Reduction life cycle
K74: 0.0619 | L74: 1.35 | M74: ='Ecoinvent data'!K18547/'Selected processes'!$K$74/'Selected processes'!$L$74 -> 4.5694635 | N74: ='Ecoinvent data'!L18547/'Selected processes'!$K$74/'Selected processes'!$L$74 -> 1.7432418e-08
D86: 17446
D87: 17078
D88: 323
D89: 17076
D90: 16311
D91: 12104 | F91: 13169 | G91: Bike production+A95:A108
D92: 5070
D93: 5253
D94: 17736
D95: 6843
D96: 14708
D97: 14738
D98: 13322
D99: 18150
D100: 11946
D101: 100001
D102: 20237
D103: 20052
... D110: 2476

Sheet Physical exercise data
A1: CONFIDENTIAL | C1: Health benefit per hour of activity available if you expand the rows 31-854 by clicking + in the left margin
A2: Source | C2: Activity level | D2: PA Status | E2: Inactive | F2: Low activity | G2: Medium activity | H2: High activity
A3: J. Namovitc and O. Jolliet, 2024 | C3: Activity level | D3: Definition (min/week) | E3: <10 | F3: <150 | G3: 150-300 | H3: >300
C4: Reference activity level | D4: Reference Minutes per week: | E4: 5 | F4: 80 | G4: 200 | H4: 400
D5: Hours Per Week | E5: 0.083333333 | F5: 1.3333333 | G5: 3.3333333 | H5: 6.6666667
C6: PA reference level | D6: PA mMET-h/week | E6: 0.5 | F6: 8 | G6: 20 | H6: 40
C7: Health gain per marginal MET-hour, mMET-h | D7: Metric | E7: Average health benefit minutes of healthy life gained/MET-h
D8: Activity level | E8: Inactive | F8: Low Activity | G8: Moderate Activity | H8: High Activity
C9: Characterization factor | D9: CF | E9: 77.495596 | F9: 54.938323 | G9: 29.051198 | H9: 16.909872
C14: Transportation: Physical activity gain per km | E14: Average health benefit minutes of healthy life gained/km
A15: MET | B15: Activity category | C15: For coupling with inventory for transportation studies | D15: Marginal MET mMET | E15: Inactive | F15: Low Activity | G15: Moderate Activity | H15: High Activity
B16: transportation | C16: Walking / running | E16: 71.865491 | F16: 50.947019 | G16: 26.94061 | H16: 15.681359
B17: transportation | C17: bicycling average | E17: 24.878528 | F17: 17.636933 | G17: 9.3263497 | H17: 5.4286017
B18: transportation | C18: e-biking | E18: 16.585685 | F18: 11.757955 | G18: 6.2175665 | H18: 3.6190678
A19: =A33 -> 2.5 | B19: transportation | C19: driving an automobile or light truck (not a semi) | D19: 1.5 | E19: 1.9373899 | F19: 1.3734581 | G19: 0.72627994 | H19: 0.4227468
A20: =A34 -> 1.3 | B20: transportation | C20: riding in a car | D20: 0.3 | E20: 0.38747798 | F20: 0.27469162 | G20: 0.14525599 | H20: 0.08454936
A21: =A34 -> 1.3 | B21: transportation | C21: riding in a bus | D21: 0.3 | E21: 1.1624339 | F21: 0.82407485 | G21: 0.43576797 | H21: 0.25364808
A22: =A34 -> 1.3 | B22: transportation | C22: riding in a train | D22: 0.3 | E22: 0.23248679 | F22: 0.16481497 | G22: 0.087153593 | H22: 0.050729616
A23: =A36 -> 1.8 | B23: transportation | C23: flying airplane or helicopter | D23: 0.8 | E23: 0.10332746 | F23: 0.073251097 | G23: 0.03873493 | H23: 0.022546496
A24: =A37 -> 3.5 | B24: transportation | C24: motor scooter, motorcycle | D24: 2.5 | E24: 3.2289832 | F24: 2.2890968 | G24: 1.2104666 | H24: 0.704578
A25: =A38 -> 6.3 | B25: transportation | C25: pulling rickshaw | D25: 5.3 | E25: 136.90889 | F25: 97.057704 | G25: 51.323783 | H25: 29.874107
A26: =A39 -> 6 | B26: transportation | C26: driving a truck, semi, tractor, > 1 ton, or bus, driving | D26: 5 | E26: 9.6869495 | F26: 6.8672904 | G26: 3.6313997 | H26: 2.113734
A27: =A34 -> 1.3 | B27: transportation | C27: riding in a truck | D27: 0.3 | E27: 0.58121697 | F27: 0.41203742 | G27: 0.21788398 | H27: 0.12682404
A30: Data | C30: Health benefit per MET-h available if you expand the rows 1-14 by clicking + in the left margin
C31: Physical activity: gain per hour of activity | E31: Average health benefit minutes of healthy life gained/hour activity
A32: MET | B32: Activity category | C32: Specific activity | D32: mMET | E32: Inactive | F32: Low Activity | G32: Moderate Activity | H32: High Activity
A33: 2.5 | B33: transportation | C33: automobile or light truck (not a semi) driving | D33: 1.5 | E33: 116.24339 | F33: 82.407485 | G33: 43.576797 | H33: 25.364808
A34: 1.3 | B34: transportation | C34: riding in a car or truck | D34: 0.3 | E34: 23.248679 | F34: 16.481497 | G34: 8.7153593 | H34: 5.0729616
A35: 1.3 | B35: transportation | C35: riding in a bus or train | D35: 0.3 | E35: 23.248679 | F35: 16.481497 | G35: 8.7153593 | H35: 5.0729616
A36: 1.8 | B36: transportation | C36: flying airplane or helicopter | D36: 0.8 | E36: 61.996477 | F36: 43.950658 | G36: 23.240958 | H36: 13.527898
A37: 3.5 | B37: transportation | C37: motor scooter, motorcycle | D37: 2.5 | E37: 193.73899 | F37: 137.34581 | G37: 72.627994 | H37: 42.27468
A38: 6.3 | B38: transportation | C38: pulling rickshaw | D38: 5.3 | E38: 410.72666 | F38: 291.17311 | G38: 153.97135 | H38: 89.622322
A39: 6 | B39: transportation | C39: pushing plane in and out of hangar | D39: 5 | E39: 387.47798 | F39: 274.69162 | G39: 145.25599 | H39: 84.54936
A40: 2.5 | B40: transportation | C40: truck, semi, tractor, > 1 ton, or bus, driving | D40: 1.5 | E40: 116.24339 | F40: 82.407485 | G40: 43.576797 | H40: 25.364808
A41: 3.5 | B41: transportation | C41: walking for transportation, 2.8-3.2 mph, level, moderate pace, firm surface | D41: 2.5 | E41: 193.73899 | F41: 137.34581 | G41: 72.627994 | H41: 42.27468
A42: 14 | B42: bicycling | C42: bicycling, mountain, uphill, vigorous | D42: 13 | E42: 1007.4427 | F42: 714.1982 | G42: 377.66557 | H42: 219.82834
A43: 16 | B43: bicycling | C43: bicycling, mountain, competitive, racing | D43: 15 | E43: 1162.4339 | F43: 824.07485 | G43: 435.76797 | H43: 253.64808
A44: 8.5 | B44: bicycling | C44: bicycling, BMX | D44: 7.5 | E44: 581.21697 | F44: 412.03742 | G44: 217.88398 | H44: 126.82404
... A854: 3 | B854: volunteer activities | C854: walk/stand combination, for volunteer purposes | D854: 2 | E854: 154.99119 | F854: 109.87665 | G854: 58.102395 | H854: 33.819744

Sheet Ecoinvent data
D1: Conversion factors | E1: treatment of metal scrap, mixed | F1: g/kg | G1: 1000 | I1: Method | J1: IPCC 2021 | K1: ReCiPe 2016 v1.03, endpoint (H) | L1: ReCiPe 2016 v1.03, endpoint (H) | M1: ReCiPe 2016 v1.03, endpoint (H) | N1: Cumulative Energy Demand (CED) | O1: selected LCI results | P1: Ratio CO2 fossil/non ren. cum. energy demand
I2: Category | J2: climate change | K2: total: human health | L2: total: ecosystem quality | M2: total: natural resources | N2: energy resources: non-renewable | O2: air | P2: CO2 fossil/total non renewable energy
I3: Indicator | J3: global warming potential (GWP100) | K3: human health | L3: ecosystem quality | M3: natural resources | N3: energy content (HHV) | O3: CO2, fossil | P3: Check combustion included
D4: Process # | E4: Activity Name | F4: Geography | G4: Reference Product Name | H4: Reference Product Unit | I4: Reference Product Amount | J4: kg CO2-Eq | K4: min.lost | L4: species.yr | M4: USD 2013 | N4: MJ-Eq | O4: kg | P4: gCO2/MJ
A5: [sulfonyl]urea-compound productionRoW[sulfonyl]urea-compoundkg | B5: 1 | C5: 101 | D5: 1 | E5: [sulfonyl]urea-compound production | F5: RoW | G5: [sulfonyl]urea-compound | H5: kg | I5: 1 | J5: 11.626408 | K5: 18.528391 | L5: 5.842408e-08 | M5: 1.5078495 | N5: 180.31692 | O5: 9.8487974 | P5: 54.619375
A6: [sulfonyl]urea-compound productionRER[sulfonyl]urea-compoundkg | B6: 2 | C6: 102 | D6: 2 | E6: [sulfonyl]urea-compound production | F6: RER | G6: [sulfonyl]urea-compound | H6: kg | I6: 1 | J6: 9.2409541 | K6: 14.867009 | L6: 4.8480757e-08 | M6: 1.0758414 | N6: 174.9647 | O6: 7.9578741 | P6: 45.482741
A7: market for [sulfonyl]urea-compoundGLO[sulfonyl]urea-compoundkg | B7: 3 | C7: 8317 | D7: 3 | E7: market for [sulfonyl]urea-compound | F7: GLO | G7: [sulfonyl]urea-compound | H7: kg | I7: 1 | J7: 11.229117 | K7: 17.89712 | L7: 5.6833249e-08 | M7: 1.432525 | N7: 180.36287 | O7: 9.5422554 | P7: 52.905876
A8: [thio]carbamate-compound productionRoW[thio]carbamate-compoundkg | B8: 4 | C8: 103 | D8: 4 | E8: [thio]carbamate-compound production | F8: RoW | G8: [thio]carbamate-compound | H8: kg | I8: 1 | J8: 10.948101 | K8: 15.655207 | L8: 5.4967346e-08 | M8: 1.3211625 | N8: 178.88454 | O8: 9.2553434 | P8: 51.739202
A9: [thio]carbamate-compound productionRER[thio]carbamate-compoundkg | B9: 5 | C9: 104 | D9: 5 | E9: [thio]carbamate-compound production | F9: RER | G9: [thio]carbamate-compound | H9: kg | I9: 1 | J9: 8.4650094 | K9: 11.767285 | L9: 4.4224082e-08 | M9: 1.2967167 | N9: 173.40819 | O9: 7.3478648 | P9: 42.373228
A10: market for [thio]carbamate-compoundGLO[thio]carbamate-compoundkg | B10: 6 | C10: 8318 | D10: 6 | E10: market for [thio]carbamate-compound | F10: GLO | G10: [thio]carbamate-compound | H10: kg | I10: 1 | J10: 10.531528 | K10: 14.979196 | L10: 5.3218535e-08 | M10: 1.3263276 | N10: 178.90597 | O10: 8.9455318 | P10: 50.001304
A11: =E11&F11&G11&H11 -> 1,1-difluoroethane production, HFC-152aRoW1,1-difluoroethane, HFC-152akg | B11: 7 | C11: 1 | D11: 7 | E11: 1,1-difluoroethane production, HFC-152a | F11: RoW | G11: 1,1-difluoroethane, HFC-152a | H11: kg | I11: 1 | J11: 6.3669866 | K11: 9.032636 | L11: 2.8845757e-08 | M11: 2.8315726 | N11: 57.000554 | O11: 3.6634447 | P11: =O11/N11*$G$1 -> 64.270335
A12: 1,1-difluoroethane production, HFC-152aUS1,1-difluoroethane, HFC-152akg | B12: 8 | C12: 2 | D12: 8 | E12: 1,1-difluoroethane production, HFC-152a | F12: US | G12: 1,1-difluoroethane, HFC-152a | H12: kg | I12: 1 | J12: 6.3243048 | K12: 9.1446625 | L12: 2.8543092e-08 | M12: 3.7242399 | N12: 57.113361 | O12: 3.6345028 | P12: 63.636648
A13: market for 1,1-difluoroethane, HFC-152aGLO1,1-difluoroethane, HFC-152akg | B13: 9 | C13: 8249 | D13: 9 | E13: market for 1,1-difluoroethane, HFC-152a | F13: GLO | G13: 1,1-difluoroethane, HFC-152a | H13: kg | I13: 1 | J13: 6.4071794 | K13: 9.1462453 | L13: 2.9052097e-08 | M13: 3.136106 | N13: 57.822225 | O13: 3.7032085 | P13: 64.044725
A14: market for 1,1-dimethylcyclopentaneGLO1,1-dimethylcyclopentanekg | B14: 10 | C14: 8250 | D14: 10 | E14: market for 1,1-dimethylcyclopentane | F14: GLO | G14: 1,1-dimethylcyclopentane | H14: kg | I14: 1 | J14: 1.2741876 | K14: 1.4549727 | L14: 6.1231367e-09 | M14: 0.63869104 | N14: 67.659529 | O14: 0.88045713 | P14: 13.013054
A15: molecular sieve separation of naphthaRoW1,1-dimethylcyclopentanekg | B15: 11 | C15: 14941 | D15: 11 | E15: molecular sieve separation of naphtha | F15: RoW | G15: 1,1-dimethylcyclopentane | H15: kg | I15: 1 | J15: 1.2381645 | K15: 1.4625637 | L15: 6.0318991e-09 | M15: 0.63271298 | N15: 66.992035 | O15: 0.86517473 | P15: 12.914591
A16: molecular sieve separation of naphthaRER1,1-dimethylcyclopentanekg | B16: 12 | C16: 14951 | D16: 12 | E16: molecular sieve separation of naphtha | F16: RER | G16: 1,1-dimethylcyclopentane | H16: kg | I16: 1 | J16: 1.2330253 | K16: 1.2976203 | L16: 5.7080156e-09 | M16: 0.63549161 | N16: 67.318661 | O16: 0.80832645 | P16: 12.007465
A17: hydroformylation of propyleneRoW1-butanolkg | B17: 13 | C17: 7034 | D17: 13 | E17: hydroformylation of propylene | F17: RoW | G17: 1-butanol | H17: kg | I17: 1 | J17: 3.5843893 | K17: 4.1948851 | L17: 1.5427309e-08 | M17: 0.6434165 | N17: 88.160905 | O17: 3.0280644 | P17: 34.34702
A18: hydroformylation of propyleneRER1-butanolkg | B18: 14 | C18: 7036 | D18: 14 | E18: hydroformylation of propylene | F18: RER | G18: 1-butanol | H18: kg | I18: 1 | J18: 2.6033862 | K18: 2.6596689 | L18: 1.1070048e-08 | M18: 0.63000176 | N18: 84.3551 | O18: 2.1625944 | P18: 25.636795
A19: market for 1-butanolGLO1-butanolkg | B19: 15 | C19: 8251 | D19: 15 | E19: market for 1-butanol | F19: GLO | G19: 1-butanol | H19: kg | I19: 1 | J19: 3.673819 | K19: 4.2772912 | L19: 1.6238854e-08 | M19: 0.63833849 | N19: 91.392438 | O19: 3.1379718 | P19: 34.335136
A20: synthetic fuel production, from coal, high temperature Fisher-Tropsch operationsZA1-butanolkg | B20: 16 | C20: 17686 | D20: 16 | E20: synthetic fuel production, from coal, high temperature Fisher-Tropsch operations | F20: ZA | G20: 1-butanol | H20: kg | I20: 1 | J20: 9.5618599 | K20: 12.659035 | L20: 4.8360311e-08 | M20: 0.49577961 | N20: 153.65289 | O20: 8.8434158 | P20: 57.554502
A21: 1-methoxy-2-propanol productionGLO1-methoxy-2-propanolkg | B21: 17 | C21: 4 | D21: 17 | E21: 1-methoxy-2-propanol production | F21: GLO | G21: 1-methoxy-2-propanol | H21: kg | I21: 1 | J21: 3.9718327 | K21: 5.2243008 | L21: 1.7485765e-08 | M21: 0.62054372 | N21: 88.075687 | O21: 3.4048359 | P21: 38.658068
A22: market for 1-methoxy-2-propanolGLO1-methoxy-2-propanolkg | B22: 18 | C22: 8252 | D22: 18 | E22: market for 1-methoxy-2-propanol | F22: GLO | G22: 1-methoxy-2-propanol | H22: kg | I22: 1 | J22: 4.0262528 | K22: 5.300568 | L22: 1.7792993e-08 | M22: 0.62752139 | N22: 88.859756 | O22: 3.454247 | P22: 38.873019
A23: 1-methylcyclopropene productionGLO1-methylcyclopropenekg | B23: 19 | C23: 5 | D23: 19 | E23: 1-methylcyclopropene production | F23: GLO | G23: 1-methylcyclopropene | H23: kg | I23: 1 | J23: 8.5951782 | K23: 10.788915 | L23: 3.7664497e-08 | M23: 1.1996844 | N23: 165.86597 | O23: 7.4160599 | P23: 44.711159
... A422: market for aluminium removed by turning, primarily roughing, conventionalGLOaluminium removed by turning, primarily roughing, conventionalkg | B422: 418 | C422: 8431 | D422: 418 | E422: market for aluminium removed by turning, primarily roughing, conventional | F422: GLO | G422: aluminium removed by turning, primarily roughing, conventional | H422: kg | I422: 1 | J422: 12.903963 | K422: 21.226181 | L422: 6.0587323e-08 | M422: 0.57519472 | N422: 128.6611 | O422: 10.713549 | P422: 83.269534
A423: aluminium scrap, new, Recycled Content cut-offGLOaluminium scrap, newkg | B423: 419 | C423: 344 | D423: 419 | E423: aluminium scrap, new, Recycled Content cut-off | F423: GLO | G423: aluminium scrap, new | H423: kg | I423: 1 | J423: 0 | K423: 0 | L423: 0 | M423: 0 | N423: 0 | O423: 0 | P423: #DIV/0!
A424: market for aluminium scrap, newRoWaluminium scrap, newkg | B424: 420 | C424: 8432 | D424: 420 | E424: market for aluminium scrap, new | F424: RoW | G424: aluminium scrap, new | H424: kg | I424: 1 | J424: 0.037790897 | K424: 0.047559232 | L424: 1.9966874e-10 | M424: 0.0050504584 | N424: 0.55811885 | O424: 0.034314086 | P424: 61.481683
A425: market for aluminium scrap, newRERaluminium scrap, newkg | B425: 421 | C425: 8433 | D425: 421 | E425: market for aluminium scrap, new | F425: RER | G425: aluminium scrap, new | H425: kg | I425: 1 | J425: 0.034848373 | K425: 0.039723378 | L425: 1.7263974e-10 | M425: 0.0047579086 | N425: 0.53689135 | O425: 0.031282824 | P425: 58.266583
A426: aluminium scrap, post-consumer, Recycled Content cut-offGLOaluminium scrap, post-consumerkg | B426: 422 | C426: 345 | D426: 422 | E426: aluminium scrap, post-consumer, Recycled Content cut-off | F426: GLO | G426: aluminium scrap, post-consumer | H426: kg | I426: 1 | J426: 0 | K426: 0 | L426: 0 | M426: 0 | N426: 0 | O426: 0 | P426: #DIV/0!
A427: market for aluminium scrap, post-consumerGLOaluminium scrap, post-consumerkg | B427: 423 | C427: 8434 | D427: 423 | E427: market for aluminium scrap, post-consumer | F427: GLO | G427: aluminium scrap, post-consumer | H427: kg | I427: 1 | J427: 0.037736148 | K427: 0.047390142 | L427: 1.9919877e-10 | M427: 0.0050518436 | N427: 0.55861824 | O427: 0.03423183 | P427: 61.27947
A428: aluminium scrap, post-consumer, prepared for melting, Recycled Content cut-offGLOaluminium scrap, post-consumer, prepared for meltingkg | B428: 424 | C428: 346 | D428: 424 | E428: aluminium scrap, post-consumer, prepared for melting, Recycled Content cut-off | F428: GLO | G428: aluminium scrap, post-consumer, prepared for melting | H428: kg | I428: 1 | J428: 0 | K428: 0 | L428: 0 | M428: 0 | N428: 0 | O428: 0 | P428: #DIV/0!
A429: market for aluminium scrap, post-consumer, prepared for meltingGLOaluminium scrap, post-consumer, prepared for meltingkg | B429: 425 | C429: 8435 | D429: 425 | E429: market for aluminium scrap, post-consumer, prepared for melting | F429: GLO | G429: aluminium scrap, post-consumer, prepared for melting | H429: kg | I429: 1 | J429: 0.29304652 | K429: 0.59488307 | L429: 1.0928401e-08 | M429: 0.014683271 | N429: 2.1880713 | O429: 0.2745417 | P429: 125.47201
A430: treatment of aluminium scrap, post-consumer, by collecting, sorting, cleaning, pressingRoWaluminium scrap, post-consumer, prepared for meltingkg | B430: 426 | C430: 18345 | D430: 426 | E430: treatment of aluminium scrap, post-consumer, by collecting, sorting, cleaning, pressing | F430: RoW | G430: aluminium scrap, post-consumer, prepared for melting | H430: kg | I430: 1 | J430: 0.31959292 | K430: 0.65023574 | L430: 1.1956103e-08 | M430: 0.015338793 | N430: 2.3129318 | O430: 0.30007132 | P430: 129.73634
A431: treatment of aluminium scrap, post-consumer, by collecting, sorting, cleaning, pressingRERaluminium scrap, post-consumer, prepared for meltingkg | B431: 427 | C431: 18346 | D431: 427 | E431: treatment of aluminium scrap, post-consumer, by collecting, sorting, cleaning, pressing | F431: RER | G431: aluminium scrap, post-consumer, prepared for melting | H431: kg | I431: 1 | J431: 0.30234663 | K431: 0.61722061 | L431: 1.1868231e-08 | M431: 0.016330365 | N431: 2.4031795 | O431: 0.28651877 | P431: 119.22487
A432: treatment of metal scrap, mixed, for recycling, unsorted, sortingCHaluminium scrap, post-consumer, prepared for meltingkg | B432: 428 | C432: 18858 | D432: 428 | E432: treatment of metal scrap, mixed, for recycling, unsorted, sorting | F432: CH | G432: aluminium scrap, post-consumer, prepared for melting | H432: kg | I432: 1 | J432: 0.024098665 | K432: 0.047628259 | L432: 1.4251434e-10 | M432: 0.0016560852 | N432: 0.23316465 | O432: 0.022139561 | P432: 94.952479
A433: treatment of metal scrap, mixed, for recycling, unsorted, sortingEurope without Switzerlandaluminium scrap, post-consumer, prepared for meltingkg | B433: 429 | C433: 18861 | D433: 429 | E433: treatment of metal scrap, mixed, for recycling, unsorted, sorting | F433: Europe without Switzerland | G433: aluminium scrap, post-consumer, prepared for melting | H433: kg | I433: 1 | J433: 0.033282732 | K433: 0.05968612 | L433: 1.859784e-10 | M433: 0.0023804149 | N433: 0.3284659 | O433: 0.023799193 | P433: 72.455596
A434: treatment of metal scrap, mixed, for recycling, unsorted, sortingRoWaluminium scrap, post-consumer, prepared for meltingkg | B434: 430 | C434: 18864 | D434: 430 | E434: treatment of metal scrap, mixed, for recycling, unsorted, sorting | F434: RoW | G434: aluminium scrap, post-consumer, prepared for melting | H434: kg | I434: 1 | J434: 0.070849677 | K434: 0.1176173 | L434: 3.8218081e-10 | M434: 0.0061611954 | N434: 0.74595307 | O434: 0.049545939 | P434: 66.419647
A435: treatment of used beverage cans, for recycling, unsorted, sortingCHaluminium scrap, post-consumer, prepared for meltingkg | B435: 431 | C435: 19748 | D435: 431 | E435: treatment of used beverage cans, for recycling, unsorted, sorting | F435: CH | G435: aluminium scrap, post-consumer, prepared for melting | H435: kg | I435: 1 | J435: 0.024096639 | K435: 0.047625409 | L435: 1.4250331e-10 | M435: 0.0016558112 | N435: 0.23313625 | O435: 0.022137713 | P435: 94.956118
A436: treatment of used beverage cans, for recycling, unsorted, sortingEurope without Switzerlandaluminium scrap, post-consumer, prepared for meltingkg | B436: 432 | C436: 19749 | D436: 432 | E436: treatment of used beverage cans, for recycling, unsorted, sorting | F436: Europe without Switzerland | G436: aluminium scrap, post-consumer, prepared for melting | H436: kg | I436: 1 | J436: 0.033280707 | K436: 0.059683271 | L436: 1.8596737e-10 | M436: 0.0023801408 | N436: 0.3284375 | O436: 0.023797345 | P436: 72.456234
A437: treatment of used beverage cans, for recycling, unsorted, sortingRoWaluminium scrap, post-consumer, prepared for meltingkg | B437: 433 | C437: 19750 | D437: 433 | E437: treatment of used beverage cans, for recycling, unsorted, sorting | F437: RoW | G437: aluminium scrap, post-consumer, prepared for melting | H437: kg | I437: 1 | J437: 0.070847651 | K437: 0.11761445 | L437: 3.8216979e-10 | M437: 0.0061609214 | N437: 0.74592467 | O437: 0.049544091 | P437: 66.419698
A438: aluminium sulfate production, powderRoWaluminium sulfate, powderkg | B438: 434 | C438: 347 | D438: 434 | E438: aluminium sulfate production, powder | F438: RoW | G438: aluminium sulfate, powder | H438: kg | I438: 1 | J438: 0.78323423 | K438: 2.406247 | L438: 5.042356e-09 | M438: 0.048387601 | N438: 9.5464753 | O438: 0.69797665 | P438: 73.113545
A439: aluminium sulfate production, powderRERaluminium sulfate, powderkg | B439: 435 | C439: 348 | D439: 435 | E439: aluminium sulfate production, powder | F439: RER | G439: aluminium sulfate, powder | H439: kg | I439: 1 | J439: 0.5424879 | K439: 1.9013187 | L439: 3.940815e-09 | M439: 0.037755348 | N439: 8.544232 | O439: 0.49048512 | P439: 57.405408
A440: market for aluminium sulfate, powderRoWaluminium sulfate, powderkg | B440: 436 | C440: 8436 | D440: 436 | E440: market for aluminium sulfate, powder | F440: RoW | G440: aluminium sulfate, powder | H440: kg | I440: 1 | J440: 0.8377824 | K440: 2.4828355 | L440: 5.3505822e-09 | M440: 0.055374095 | N440: 10.329698 | O440: 0.74754153 | P440: 72.36819
... A450: treatment of aluminium scrap, post-consumer, prepared for recycling, at refinerRERaluminium, cast alloykg | B450: 446 | C450: 18350 | D450: 446 | E450: treatment of aluminium scrap, post-consumer, prepared for recycling, at refiner | F450: RER | G450: aluminium, cast alloy | H450: kg | I450: 1 | J450: 0.89030506 | K450: 1.9624939 | L450: 1.4157157e-08 | M450: 0.067407839 | N450: 10.234142 | O450: 0.81913109 | P450: 80.039062
A451: aluminium, in mixed metal scrap, Recycled Content cut-offGLOaluminium, in mixed metal scrapkg | B451: 447 | C451: 363 | D451: 447 | E451: aluminium, in mixed metal scrap, Recycled Content cut-off | F451: GLO | G451: aluminium, in mixed metal scrap | H451: kg | I451: 1 | J451: 0 | K451: 0 | L451: 0 | M451: 0 | N451: 0 | O451: 0 | P451: #DIV/0!
A452: market for aluminium, in mixed metal scrapCHaluminium, in mixed metal scrapkg | B452: 448 | C452: 8440 | D452: 448 | E452: market for aluminium, in mixed metal scrap | F452: CH | G452: aluminium, in mixed metal scrap | H452: kg | I452: 1 | J452: 0.0069008847 | K452: 0.0090567184 | L452: 3.6078012e-11 | M452: 0.00092464257 | N452: 0.11752539 | O452: 0.0061323295 | P452: 52.178763
A453: market for aluminium, in mixed metal scrapEurope without Switzerlandaluminium, in mixed metal scrapkg | B453: 449 | C453: 8441 | D453: 449 | E453: market for aluminium, in mixed metal scrap | F453: Europe without Switzerland | G453: aluminium, in mixed metal scrap | H453: kg | I453: 1 | J453: 0.010042995 | K453: 0.0109676 | L453: 4.8916979e-11 | M453: 0.0014228588 | N453: 0.15466618 | O453: 0.0090055023 | P453: 58.225414
A454: market for aluminium, in mixed metal scrapRoWaluminium, in mixed metal scrapkg | B454: 450 | C454: 8442 | D454: 450 | E454: market for aluminium, in mixed metal scrap | F454: RoW | G454: aluminium, in mixed metal scrap | H454: kg | I454: 1 | J454: 0.037790897 | K454: 0.047559232 | L454: 1.9966874e-10 | M454: 0.0050504584 | N454: 0.55811885 | O454: 0.034314086 | P454: 61.481683
A455: aluminium production, primary, cast alloy slab from continuous castingCA-QCaluminium, primary, cast alloy slab from continuous castingkg | B455: 451 | C455: 317 | D455: 451 | E455: aluminium production, primary, cast alloy slab from continuous casting | F455: CA-QC | G455: aluminium, primary, cast alloy slab from continuous casting | H455: kg | I455: 1 | J455: 7.2018726 | K455: 18.285801 | L455: 3.5598944e-08 | M455: 0.48002908 | N455: 70.633584 | O455: 6.2578998 | P455: 88.596662
A456: aluminium production, primary, cast alloy slab from continuous castingRoWaluminium, primary, cast alloy slab from continuous castingkg | B456: 452 | C456: 318 | D456: 452 | E456: aluminium production, primary, cast alloy slab from continuous casting | F456: RoW | G456: aluminium, primary, cast alloy slab from continuous casting | H456: kg | I456: 1 | J456: 20.85958 | K456: 41.957699 | L456: 1.0745482e-07 | M456: 0.72599925 | N456: 222.82798 | O456: 18.74387 | P456: 84.118118
A457: market for aluminium, primary, cast alloy slab from continuous castingGLOaluminium, primary, cast alloy slab from continuous castingkg | B457: 453 | C457: 8443 | D457: 453 | E457: market for aluminium, primary, cast alloy slab from continuous casting | F457: GLO | G457: aluminium, primary, cast alloy slab from continuous casting | H457: kg | I457: 1 | J457: 20.153857 | K457: 40.699281 | L457: 1.0374483e-07 | M457: 0.72203893 | N457: 215.23628 | O457: 18.098155 | P457: 84.085056
A458: aluminium production, primary, ingotCAaluminium, primary, ingotkg | B458: 454 | C458: 319 | D458: 454 | E458: aluminium production, primary, ingot | F458: CA | G458: aluminium, primary, ingot | H458: kg | I458: 1 | J458: 7.5319549 | K458: 18.078525 | L458: 3.7577458e-08 | M458: 0.48977291 | N458: 72.578587 | O458: 6.5357885 | P458: 90.051195
A459: aluminium production, primary, ingotCNaluminium, primary, ingotkg | B459: 455 | C459: 320 | D459: 455 | E459: aluminium production, primary, ingot | F459: CN | G459: aluminium, primary, ingot | H459: kg | I459: 1 | J459: 23.459726 | K459: 34.902809 | L459: 1.0432571e-07 | M459: 0.76456816 | N459: 214.33509 | O459: 19.378257 | P459: 90.411035
A460: aluminium production, primary, ingotIAI Area, Africaaluminium, primary, ingotkg | B460: 456 | C460: 321 | D460: 456 | E460: aluminium production, primary, ingot | F460: IAI Area, Africa | G460: aluminium, primary, ingot | H460: kg | I460: 1 | J460: 14.890682 | K460: 29.568143 | L460: 8.0578032e-08 | M460: 0.6289157 | N460: 163.94537 | O460: 13.51221 | P460: 82.418979
A461: aluminium production, primary, ingotIAI Area, Asia, without China and GCCaluminium, primary, ingotkg | B461: 457 | C461: 322 | D461: 457 | E461: aluminium production, primary, ingot | F461: IAI Area, Asia, without China and GCC | G461: aluminium, primary, ingot | H461: kg | I461: 1 | J461: 28.766396 | K461: 67.55814 | L461: 1.3231984e-07 | M461: 0.90791599 | N461: 319.71849 | O461: 26.749602 | P461: 83.666108
A462: aluminium production, primary, ingotIAI Area, EU27 & EFTAaluminium, primary, ingotkg | B462: 458 | C462: 323 | D462: 458 | E462: aluminium production, primary, ingot | F462: IAI Area, EU27 & EFTA | G462: aluminium, primary, ingot | H462: kg | I462: 1 | J462: 7.209838 | K462: 13.333429 | L462: 3.2653298e-08 | M462: 0.57610667 | N462: 115.04046 | O462: 6.4231875 | P462: 55.834159
A463: aluminium production, primary, ingotIAI Area, Gulf Cooperation Councilaluminium, primary, ingotkg | B463: 459 | C463: 324 | D463: 459 | E463: aluminium production, primary, ingot | F463: IAI Area, Gulf Cooperation Council | G463: aluminium, primary, ingot | H463: kg | I463: 1 | J463: 16.821971 | K463: 21.894854 | L463: 6.5242915e-08 | M463: 1.8293481 | N463: 249.90454 | O463: 14.979395 | P463: 59.940467
... A677: market for anthraquinoneGLOanthraquinonekg | B677: 673 | C677: 8506 | D677: 673 | E677: market for anthraquinone | F677: GLO | G677: anthraquinone | H677: kg | I677: 1 | J677: 20.607094 | K677: 253.60261 | L677: 1.0381659e-07 | M677: 1.7698132 | N677: 299.25941 | O677: 18.456353 | P677: 61.673427
A678: market for antifouling paint emissionsGLOantifouling paint emissionskg | B678: 674 | C678: 8508 | D678: 674 | E678: market for antifouling paint emissions | F678: GLO | G678: antifouling paint emissions | H678: kg | I678: -1 | J678: 0 | K678: 4.8574124 | L678: 5.6905997e-08 | M678: 0 | N678: 0 | O678: 0 | P678: #DIV/0!
A679: treatment of Cu-based antifouling paint emissionsRoWantifouling paint emissionskg | B679: 675 | C679: 18330 | D679: 675 | E679: treatment of Cu-based antifouling paint emissions | F679: RoW | G679: antifouling paint emissions | H679: kg | I679: -1 | J679: 0 | K679: 2.1051964 | L679: 6.5186214e-08 | M679: 0 | N679: 0 | O679: 0 | P679: #DIV/0!
A680: treatment of Cu-based antifouling paint emissionsPEantifouling paint emissionskg | B680: 676 | C680: 18331 | D680: 676 | E680: treatment of Cu-based antifouling paint emissions | F680: PE | G680: antifouling paint emissions | H680: kg | I680: -1 | J680: 0 | K680: 2.1051964 | L680: 6.5186214e-08 | M680: 0 | N680: 0 | O680: 0 | P680: #DIV/0!
A681: treatment of Sn-based antifouling paint emissionsRoWantifouling paint emissionskg | B681: 677 | C681: 18334 | D681: 677 | E681: treatment of Sn-based antifouling paint emissions | F681: RoW | G681: antifouling paint emissions | H681: kg | I681: -1 | J681: 0 | K681: 7.6096285 | L681: 4.8625779e-08 | M681: 0 | N681: 0 | O681: 0 | P681: #DIV/0!
A682: treatment of Sn-based antifouling paint emissionsPEantifouling paint emissionskg | B682: 678 | C682: 18335 | D682: 678 | E682: treatment of Sn-based antifouling paint emissions | F682: PE | G682: antifouling paint emissions | H682: kg | I682: -1 | J682: 0 | K682: 7.6096285 | L682: 4.8625779e-08 | M682: 0 | N682: 0 | O682: 0 | P682: #DIV/0!
A683: antimony productionCNantimonykg | B683: 679 | C683: 492 | D683: 679 | E683: antimony production | F683: CN | G683: antimony | H683: kg | I683: 1 | J683: 23.148471 | K683: 331.86476 | L683: 2.0025255e-07 | M683: 1.4731083 | N683: 268.55577 | O683: 19.654369 | P683: 73.185426
A684: antimony productionRoWantimonykg | B684: 680 | C684: 493 | D684: 680 | E684: antimony production | F684: RoW | G684: antimony | H684: kg | I684: 1 | J684: 23.064146 | K684: 331.79101 | L684: 1.9990775e-07 | M684: 1.474844 | N684: 268.48752 | O684: 19.590668 | P684: 72.966774
A685: market for antimonyGLOantimonykg | B685: 681 | C685: 8509 | D685: 681 | E685: market for antimony | F685: GLO | G685: antimony | H685: kg | I685: 1 | J685: 23.206675 | K685: 331.94671 | L685: 2.0058401e-07 | M685: 1.4836393 | N685: 269.67322 | O685: 19.710058 | P685: 73.088674
A686: market for antimony slag, desulfurisedGLOantimony slag, desulfurisedkg | B686: 682 | C686: 8510 | D686: 682 | E686: market for antimony slag, desulfurised | F686: GLO | G686: antimony slag, desulfurised | H686: kg | I686: -1 | J686: 0.047235649 | K686: 8.7222852 | L686: 2.2878956e-09 | M686: 0.0076503641 | N686: 0.84008454 | O686: 0.04204718 | P686: 50.051129
A687: treatment of antimony slag, desulfurised, residual material landfillGLOantimony slag, desulfurisedkg | B687: 683 | C687: 18353 | D687: 683 | E687: treatment of antimony slag, desulfurised, residual material landfill | F687: GLO | G687: antimony slag, desulfurised | H687: kg | I687: -1 | J687: 0.0094995011 | K687: 8.674895 | L687: 2.0886969e-09 | M687: 0.0025985206 | N687: 0.2814663 | O687: 0.0078153499 | P687: 27.766557
A688: market for antimony slag, water-quenchedGLOantimony slag, water-quenchedkg | B688: 684 | C688: 8511 | D688: 684 | E688: market for antimony slag, water-quenched | F688: GLO | G688: antimony slag, water-quenched | H688: kg | I688: -1 | J688: 0.047235652 | K688: 64.912275 | L688: 4.1432148e-09 | M688: 0.0076503651 | N688: 0.84008465 | O688: 0.042047183 | P688: 50.051126
A689: treatment of antimony slag, water-quenched, residual material landfillGLOantimony slag, water-quenchedkg | B689: 685 | C689: 18354 | D689: 685 | E689: treatment of antimony slag, water-quenched, residual material landfill | F689: GLO | G689: antimony slag, water-quenched | H689: kg | I689: -1 | J689: 0.0094995047 | K689: 64.864885 | L689: 3.944016e-09 | M689: 0.0025985215 | N689: 0.2814664 | O689: 0.0078153528 | P689: 27.766557
